Workbook
Name _Ref166757325: 'Consumo Eléctrico'!$AJ$163
Name _Ref166765020: 'Consumo Eléctrico'!$G$75
Name POWER_USER_EXCEL_CHART_0C3E92C7_7122_4BCD_BE41_CA79122D9A12: 'Balance Energético'!$H$4:$S$6
Name POWER_USER_EXCEL_CHART_32786930_8C68_4D96_B573_65ADC75C9CB6: 'Balance Energético'!$H$4:$S$6
Name POWER_USER_EXCEL_CHART_8CFC428E_CDBF_457F_A59C_577F12BD97F4: 'Balance Térmico'!$E$73:$H$76
Name POWER_USER_EXCEL_CHART_F369CD19_B1EC_48BB_85C9_292C8ACCD36A: 'Balance Energético'!$H$4:$S$6

Sheet Consumo Eléctrico
D2: Histórico de Factura Eléctrica 2022-2023
F3: Medio | G3: Alto | H3: Económico
B5: PERÍODO FACTURA | F5: CONSUMO [kWh]
B6: Mes | C6: Inicio | D6: Término | E6: Días | F6: Horario Llano (08:00 - 18:00) | G6: Horario Punta (18:00 - 22:00) | H6: Horario Valle (22:00 - 08:00) | I6: Total Consumo [kWh]
J7: [kWh] *10³
B8: 44562 | C8: 44564 | D8: 44595 | E8: =D8-C8 -> 31 | F8: 4980.29 | G8: 1781.62 | H8: 1912.92 | I8: =SUM(F8:H8) -> 8674.83 | J8: =I8/1000 -> 8.67483
B9: 44593 | C9: =D8 -> 44595 | D9: 44625 | E9: =D9-C9 -> 30 | F9: 6850.63 | G9: 1401.2 | H9: 1641.29 | I9: =SUM(F9:H9) -> 9893.12 | J9: =I9/1000 -> 9.89312 | AR9: 4980.29 | AS9: 1781.62 | AT9: 1912.92
B10: 44621 | C10: =D9 -> 44625 | D10: 44655 | E10: =D10-C10 -> 30 | F10: 6449.2 | G10: 1485.63 | H10: 1754.42 | I10: =SUM(F10:H10) -> 9689.25 | J10: =I10/1000 -> 9.68925 | AR10: 6850.63 | AS10: 1401.2 | AT10: 1641.29
B11: 44652 | C11: =D10 -> 44655 | D11: 44686 | E11: =D11-C11 -> 31 | F11: 6612.52 | G11: 1598.12 | H11: 1612.92 | I11: =SUM(F11:H11) -> 9823.56 | J11: =I11/1000 -> 9.82356 | AR11: 6449.2 | AS11: 1485.63 | AT11: 1754.42
B12: 44682 | C12: =D11 -> 44686 | D12: 44716 | E12: =D12-C12 -> 30 | F12: 7284.73 | G12: 1650.53 | H12: 1568.63 | I12: =SUM(F12:H12) -> 10503.89 | J12: =I12/1000 -> 10.50389 | AR12: 6612.52 | AS12: 1598.12 | AT12: 1612.92
B13: 44713 | C13: =D12 -> 44716 | D13: 44747 | E13: =D13-C13 -> 31 | F13: 7217.46 | G13: 1246.34 | H13: 1467.53 | I13: =SUM(F13:H13) -> 9931.33 | J13: =I13/1000 -> 9.93133 | AR13: 7284.73 | AS13: 1650.53 | AT13: 1568.63
B14: 44743 | C14: =D13 -> 44747 | D14: 44777 | E14: =D14-C14 -> 30 | F14: 6847.8 | G14: 1287.75 | H14: 1533.18 | I14: =SUM(F14:H14) -> 9668.73 | J14: =I14/1000 -> 9.66873 | AR14: 7217.46 | AS14: 1246.34 | AT14: 1467.53
B15: 44774 | C15: =D14 -> 44777 | D15: 44807 | E15: =D15-C15 -> 30 | F15: 6895.23 | G15: 1189.23 | H15: 1413.67 | I15: =SUM(F15:H15) -> 9498.13 | J15: =I15/1000 -> 9.49813 | AR15: 6847.8 | AS15: 1287.75 | AT15: 1533.18
B16: 44805 | C16: =D15 -> 44807 | D16: 44837 | E16: =D16-C16 -> 30 | F16: 6853.88 | G16: 1096.88 | H16: 1334.23 | I16: =SUM(F16:H16) -> 9284.99 | J16: =I16/1000 -> 9.28499 | AR16: 6895.23 | AS16: 1189.23 | AT16: 1413.67
B17: 44835 | C17: =D16 -> 44837 | D17: 44868 | E17: =D17-C17 -> 31 | F17: 6495.31 | G17: 1172.61 | H17: 1377.64 | I17: =SUM(F17:H17) -> 9045.56 | J17: =I17/1000 -> 9.04556 | AR17: 6853.88 | AS17: 1096.88 | AT17: 1334.23
B18: 44866 | C18: =D17 -> 44868 | D18: 44899 | E18: =D18-C18 -> 31 | F18: 6921.53 | G18: 1262.5 | H18: 1492.78 | I18: =SUM(F18:H18) -> 9676.81 | J18: =I18/1000 -> 9.67681 | AR18: 6495.31 | AS18: 1172.61 | AT18: 1377.64
B19: 44896 | C19: =D18 -> 44899 | D19: 44929 | E19: =D19-C19 -> 30 | F19: 6019.6 | G19: 1188.77 | H19: 1369.56 | I19: =SUM(F19:H19) -> 8577.93 | J19: =I19/1000 -> 8.57793 | AR19: 6921.53 | AS19: 1262.5 | AT19: 1492.78
B20: 44927 | C20: =D19 -> 44929 | D20: 44960 | E20: =D20-C20 -> 31 | F20: 5203.63 | G20: 1498.52 | H20: 1772.85 | I20: =SUM(F20:H20) -> 8475 | J20: =I20/1000 -> 8.475 | AR20: 6019.6 | AS20: 1188.77 | AT20: 1369.56
... B31: 45261 | C31: =D30 -> 45263 | D31: 45294 | E31: =D31-C31 -> 31 | F31: 5795.3 | G31: 1251.45 | H31: 1421.5 | I31: =SUM(F31:H31) -> 8468.25 | J31: =I31/1000 -> 8.46825 | AR31: 7195.65 | AS31: 1312.5 | AT31: 1551.9
B32: Media (mes) 2022 | F32: =AVERAGE(F8:F19) -> 6619.015 | G32: =AVERAGE(G8:G19) -> 1363.4317 | H32: =AVERAGE(H8:H19) -> 1539.8975 | I32: =AVERAGE(I8:I19) -> 9522.3442 | J32: =I32/1000 -> 9.5223442 | AR32: 5795.3 | AS32: 1251.45 | AT32: 1421.5
B33: Total (anual) 2022 | F33: =SUM(F8:F19) -> 79428.18 | G33: =SUM(G8:G19) -> 16361.18 | H33: =SUM(H8:H19) -> 18478.77 | I33: =SUM(I8:I19) -> 114268.13 | J33: =I33/1000 -> 114.26813
B34: Media (mes) 2023 | F34: =AVERAGE(F20:F31) -> 6633.5175 | G34: =AVERAGE(G20:G31) -> 1291.82 | H34: =AVERAGE(H20:H31) -> 1496.7833 | I34: =AVERAGE(I20:I31) -> 9422.1208 | J34: =I34/1000 -> 9.4221208
B35: Total (anual) 2023 | F35: =SUM(F20:F31) -> 79602.21 | G35: =SUM(G20:G31) -> 15501.84 | H35: =SUM(H20:H31) -> 17961.4 | I35: =SUM(I20:I31) -> 113065.45 | J35: =I35/1000 -> 113.06545
I36: =I33+I35 -> 227333.58
E38: Horas x día | F38: 10 | G38: 4 | H38: 10
J39: [kWh] *10³
G40: Media mensual período 2022--2023 | J40: =AVERAGE(J8:J31) -> 9.4722325
G41: Media anaull período 2022--2023 | J41: =AVERAGE(J33,J35) -> 113.66679
H65: http://guiaiso50001.cl/guia/wp-content/uploads/2017/05/herramientas-para-la-planeacion-energetica-P-2-AP-1.pdf
B66: Línea de Base Energética - LBE PGF
J67: Protocolos de IPMVP | P67: Datos Planta Oil Malal San Antonio
B69: 1) Definición del período base | P69: 1) Definición del período base | X69: 6) Verificación de R² y filtrado de datos
X70: Z es el valor que da el ancho de la franja de flitrado
B71: 2) Definición de la muestra de datos mínima | P71: 2) Definición de la muestra de datos mínima | X71: Generalmente se comienza por el valor 4 y puede irse bajando hasta lograr el ancho de filtrado deseado
Y72: P | Z72: E
E73: Mes | F73: Consumo [kWh/mes] | G73: ='Indicadores Energéticos'!D4 -> Emulsión Asfáltica [m³/mes] | H73: DIF Consumo - Promedio | I73: Cuadrado de las diferencias | P73: Mes | Q73: Consumo [kWh/mes] | R73: ='Indicadores Energéticos'!D4 -> Emulsión Asfáltica [m³/mes] | S73: DIF Consumo - Promedio | T73: Cuadrado de las diferencias | X73: Mes | Y73: Producción [m³/mes] | Z73: Consumo [kWh/mes] | AA73: Consumo [MWh/mes] | AB73: E*E | AC73: E*P | AD73: Emodelo | AE73: Emod+Z*Sxy | AF73: Emod-Z*Sxy
E74: =B8 -> 44562 | F74: =I8 -> 8674.83 | G74: ='Indicadores Energéticos'!D8 -> 72.34458 | H74: =F74-$F$99 -> -797.4025 | I74: =H74^2 -> 635850.75 | P74: =B8 -> 44562 | Q74: =I8 -> 8674.83 | R74: ='Indicadores Energéticos'!D8 -> 72.34458 | S74: =Q74-$Q$98 -> -797.4025 | T74: =S74^2 -> 635850.75 | X74: =P74 -> 44562 | Y74: =R74 -> 72.34458 | Z74: =Q74 -> 8674.83 | AA74: =Z74/1000 -> 8.67483 | AB74: =Z74*Z74 -> 75252676 | AC74: =Z74*Y74 -> 627576.93 | AD74: =($AI$75*Y74)+$AI$77 -> 8810.6352 | AE74: =AD74+($AI$78*$Z$100) -> 9573.8949 | AF74: =AD74-($AI$78*$Z$100) -> 8047.3755 | AH74: Datos para cálculos
E75: =B9 -> 44593 | F75: =I9 -> 9893.12 | G75: ='Indicadores Energéticos'!D9 -> 99.4455 | H75: =F75-$F$99 -> 420.8875 | I75: =H75^2 -> 177146.29 | P75: =B9 -> 44593 | Q75: =I9 -> 9893.12 | R75: ='Indicadores Energéticos'!D9 -> 99.4455 | S75: =Q75-$Q$98 -> 420.8875 | T75: =S75^2 -> 177146.29 | X75: =P75 -> 44593 | Y75: =R75 -> 99.4455 | Z75: =Q75 -> 9893.12 | AA75: =Z75/1000 -> 9.89312 | AB75: =Z75*Z75 -> 97873823 | AC75: =Z75*Y75 -> 983826.26 | AD75: =($AI$75*Y75)+$AI$77 -> 9058.8477 | AE75: =AD75+($AI$78*$Z$100) -> 9822.1075 | AF75: =AD75-($AI$78*$Z$100) -> 8295.588 | AH75: Pendiente | AI75: =SLOPE(Z74:Z97,Y74:Y97) -> 9.1588228 | AJ75: m
E76: =B10 -> 44621 | F76: =I10 -> 9689.25 | G76: ='Indicadores Energéticos'!D10 -> 104.69536 | H76: =F76-$F$99 -> 217.0175 | I76: =H76^2 -> 47096.595 | P76: =B10 -> 44621 | Q76: =I10 -> 9689.25 | R76: ='Indicadores Energéticos'!D10 -> 104.69536 | S76: =Q76-$Q$98 -> 217.0175 | T76: =S76^2 -> 47096.595 | X76: =P76 -> 44621 | Y76: =R76 -> 104.69536 | Z76: =Q76 -> 9689.25 | AA76: =Z76/1000 -> 9.68925 | AB76: =Z76*Z76 -> 93881566 | AC76: =Z76*Y76 -> 1014419.5 | AD76: =($AI$75*Y76)+$AI$77 -> 9106.9303 | AE76: =AD76+($AI$78*$Z$100) -> 9870.19 | AF76: =AD76-($AI$78*$Z$100) -> 8343.6706 | AH76: Variable independiente | AJ76: P
E77: =B11 -> 44652 | F77: =I11 -> 9823.56 | G77: ='Indicadores Energéticos'!D11 -> 198.85866 | H77: =F77-$F$99 -> 351.3275 | I77: =H77^2 -> 123431.01 | P77: =B11 -> 44652 | Q77: =I11 -> 9823.56 | R77: ='Indicadores Energéticos'!D11 -> 198.85866 | S77: =Q77-$Q$98 -> 351.3275 | T77: =S77^2 -> 123431.01 | X77: =P77 -> 44652 | Y77: =R77 -> 198.85866 | Z77: =Q77 -> 9823.56 | AA77: =Z77/1000 -> 9.82356 | AB77: =Z77*Z77 -> 96502331 | AC77: =Z77*Y77 -> 1953500 | AD77: =($AI$75*Y77)+$AI$77 -> 9969.3553 | AE77: =AD77+($AI$78*$Z$100) -> 10732.615 | AF77: =AD77-($AI$78*$Z$100) -> 9206.0956 | AH77: Intercepto | AI77: =INTERCEPT(Z74:Z97,Y74:Y97) -> 8148.044 | AJ77: E₀
E78: =B12 -> 44682 | F78: =I12 -> 10503.89 | G78: ='Indicadores Energéticos'!D12 -> 265.41 | H78: =F78-$F$99 -> 1031.6575 | I78: =H78^2 -> 1064317.2 | P78: =B12 -> 44682 | Q78: =I12 -> 10503.89 | R78: ='Indicadores Energéticos'!D12 -> 265.41 | S78: =Q78-$Q$98 -> 1031.6575 | T78: =S78^2 -> 1064317.2 | X78: =P78 -> 44682 | Y78: =R78 -> 265.41 | Z78: =Q78 -> 10503.89 | AA78: =Z78/1000 -> 10.50389 | AB78: =Z78*Z78 -> 1.1033171e+08 | AC78: =Z78*Y78 -> 2787837.4 | AD78: =($AI$75*Y78)+$AI$77 -> 10578.887 | AE78: =AD78+($AI$78*$Z$100) -> 11342.147 | AF78: =AD78-($AI$78*$Z$100) -> 9815.6275 | AH78: Z | AI78: 2.2 | AJ78: 4
E79: =B13 -> 44713 | F79: =I13 -> 9931.33 | G79: ='Indicadores Energéticos'!D13 -> 188.35894 | H79: =F79-$F$99 -> 459.0975 | I79: =H79^2 -> 210770.51 | P79: =B13 -> 44713 | Q79: =I13 -> 9931.33 | R79: ='Indicadores Energéticos'!D13 -> 188.35894 | S79: =Q79-$Q$98 -> 459.0975 | T79: =S79^2 -> 210770.51 | X79: =P79 -> 44713 | Y79: =R79 -> 188.35894 | Z79: =Q79 -> 9931.33 | AA79: =Z79/1000 -> 9.93133 | AB79: =Z79*Z79 -> 98631316 | AC79: =Z79*Y79 -> 1870654.8 | AD79: =($AI$75*Y79)+$AI$77 -> 9873.1902 | AE79: =AD79+($AI$78*$Z$100) -> 10636.45 | AF79: =AD79-($AI$78*$Z$100) -> 9109.9305
E80: =B14 -> 44743 | F80: =I14 -> 9668.73 | G80: ='Indicadores Energéticos'!D14 -> 177.69752 | H80: =F80-$F$99 -> 196.4975 | I80: =H80^2 -> 38611.268 | P80: =B14 -> 44743 | Q80: =I14 -> 9668.73 | R80: ='Indicadores Energéticos'!D14 -> 177.69752 | S80: =Q80-$Q$98 -> 196.4975 | T80: =S80^2 -> 38611.268 | X80: =P80 -> 44743 | Y80: =R80 -> 177.69752 | Z80: =Q80 -> 9668.73 | AA80: =Z80/1000 -> 9.66873 | AB80: =Z80*Z80 -> 93484340 | AC80: =Z80*Y80 -> 1718109.3 | AD80: =($AI$75*Y80)+$AI$77 -> 9775.5441 | AE80: =AD80+($AI$78*$Z$100) -> 10538.804 | AF80: =AD80-($AI$78*$Z$100) -> 9012.2844
E81: =B15 -> 44774 | F81: =I15 -> 9498.13 | G81: ='Indicadores Energéticos'!D15 -> 190.06218 | H81: =F81-$F$99 -> 25.8975 | I81: =H81^2 -> 670.68051 | P81: =B15 -> 44774 | Q81: =I15 -> 9498.13 | R81: ='Indicadores Energéticos'!D15 -> 190.06218 | S81: =Q81-$Q$98 -> 25.8975 | T81: =S81^2 -> 670.68051 | X81: =P81 -> 44774 | Y81: =R81 -> 190.06218 | Z81: =Q81 -> 9498.13 | AA81: =Z81/1000 -> 9.49813 | AB81: =Z81*Z81 -> 90214473 | AC81: =Z81*Y81 -> 1805235.3 | AD81: =($AI$75*Y81)+$AI$77 -> 9888.7899 | AE81: =AD81+($AI$78*$Z$100) -> 10652.05 | AF81: =AD81-($AI$78*$Z$100) -> 9125.5301 | AH81: Resumen
E82: =B16 -> 44805 | F82: =I16 -> 9284.99 | G82: ='Indicadores Energéticos'!D16 -> 118.91 | H82: =F82-$F$99 -> -187.2425 | I82: =H82^2 -> 35059.754 | P82: =B16 -> 44805 | Q82: =I16 -> 9284.99 | R82: ='Indicadores Energéticos'!D16 -> 118.91 | S82: =Q82-$Q$98 -> -187.2425 | T82: =S82^2 -> 35059.754 | X82: =P82 -> 44805 | Y82: =R82 -> 118.91 | Z82: =Q82 -> 9284.99 | AA82: =Z82/1000 -> 9.28499 | AB82: =Z82*Z82 -> 86211039 | AC82: =Z82*Y82 -> 1104078.2 | AD82: =($AI$75*Y82)+$AI$77 -> 9237.1196 | AE82: =AD82+($AI$78*$Z$100) -> 10000.379 | AF82: =AD82-($AI$78*$Z$100) -> 8473.8599
E83: =B17 -> 44835 | F83: =I17 -> 9045.56 | G83: ='Indicadores Energéticos'!D17 -> 112 | H83: =F83-$F$99 -> -426.6725 | I83: =H83^2 -> 182049.42 | P83: =B17 -> 44835 | Q83: =I17 -> 9045.56 | R83: ='Indicadores Energéticos'!D17 -> 112 | S83: =Q83-$Q$98 -> -426.6725 | T83: =S83^2 -> 182049.42 | X83: =P83 -> 44835 | Y83: =R83 -> 112 | Z83: =Q83 -> 9045.56 | AA83: =Z83/1000 -> 9.04556 | AB83: =Z83*Z83 -> 81822156 | AC83: =Z83*Y83 -> 1013102.7 | AD83: =($AI$75*Y83)+$AI$77 -> 9173.8322 | AE83: =AD83+($AI$78*$Z$100) -> 9937.0919 | AF83: =AD83-($AI$78*$Z$100) -> 8410.5725 | AH83: Estadísticas de la regresión
E84: =B18 -> 44866 | F84: =I18 -> 9676.81 | G84: ='Indicadores Energéticos'!D18 -> 151.82552 | H84: =F84-$F$99 -> 204.5775 | I84: =H84^2 -> 41851.954 | P84: =B18 -> 44866 | Q84: =I18 -> 9676.81 | R84: ='Indicadores Energéticos'!D18 -> 151.82552 | S84: =Q84-$Q$98 -> 204.5775 | T84: =S84^2 -> 41851.954 | X84: =P84 -> 44866 | Y84: =R84 -> 151.82552 | Z84: =Q84 -> 9676.81 | AA84: =Z84/1000 -> 9.67681 | AB84: =Z84*Z84 -> 93640652 | AC84: =Z84*Y84 -> 1469186.7 | AD84: =($AI$75*Y84)+$AI$77 -> 9538.5871 | AE84: =AD84+($AI$78*$Z$100) -> 10301.847 | AF84: =AD84-($AI$78*$Z$100) -> 8775.3274 | AH84: Coeficiente de correlación múltiple | AI84: 0.88204666
E85: =B19 -> 44896 | F85: =I19 -> 8577.93 | G85: ='Indicadores Energéticos'!D19 -> 41.00712 | H85: =F85-$F$99 -> -894.3025 | I85: =H85^2 -> 799776.96 | P85: =B19 -> 44896 | Q85: =I19 -> 8577.93 | R85: ='Indicadores Energéticos'!D19 -> 41.00712 | S85: =Q85-$Q$98 -> -894.3025 | T85: =S85^2 -> 799776.96 | X85: =P85 -> 44896 | Y85: =R85 -> 41.00712 | Z85: =Q85 -> 8577.93 | AA85: =Z85/1000 -> 8.57793 | AB85: =Z85*Z85 -> 73580883 | AC85: =Z85*Y85 -> 351756.2 | AD85: =($AI$75*Y85)+$AI$77 -> 8523.621 | AE85: =AD85+($AI$78*$Z$100) -> 9286.8807 | AF85: =AD85-($AI$78*$Z$100) -> 7760.3613 | AH85: Coeficiente de determinación R^2 | AI85: 0.77800631
E86: =B20 -> 44927 | F86: =I20 -> 8475 | G86: ='Indicadores Energéticos'!P8 -> 81.25 | H86: =F86-$F$99 -> -997.2325 | I86: =H86^2 -> 994472.66 | P86: =B20 -> 44927 | Q86: =I20 -> 8475 | R86: ='Indicadores Energéticos'!P8 -> 81.25 | S86: =Q86-$Q$98 -> -997.2325 | T86: =S86^2 -> 994472.66 | X86: =P86 -> 44927 | Y86: =R86 -> 81.25 | Z86: =Q86 -> 8475 | AA86: =Z86/1000 -> 8.475 | AB86: =Z86*Z86 -> 71825625 | AC86: =Z86*Y86 -> 688593.75 | AD86: =($AI$75*Y86)+$AI$77 -> 8892.1984 | AE86: =AD86+($AI$78*$Z$100) -> 9655.4581 | AF86: =AD86-($AI$78*$Z$100) -> 8128.9387 | AH86: R^2 ajustado | AI86: 0.76791568
E87: =B21 -> 44958 | F87: =I21 -> 8802.64 | G87: ='Indicadores Energéticos'!P9 -> 104.56 | H87: =F87-$F$99 -> -669.5925 | I87: =H87^2 -> 448354.12 | P87: =B21 -> 44958 | Q87: =I21 -> 8802.64 | R87: ='Indicadores Energéticos'!P9 -> 104.56 | S87: =Q87-$Q$98 -> -669.5925 | T87: =S87^2 -> 448354.12 | X87: =P87 -> 44958 | Y87: =R87 -> 104.56 | Z87: =Q87 -> 8802.64 | AA87: =Z87/1000 -> 8.80264 | AB87: =Z87*Z87 -> 77486471 | AC87: =Z87*Y87 -> 920404.04 | AD87: =($AI$75*Y87)+$AI$77 -> 9105.6905 | AE87: =AD87+($AI$78*$Z$100) -> 9868.9503 | AF87: =AD87-($AI$78*$Z$100) -> 8342.4308 | AH87: Error típico | AI87: 346.93623
E88: =B22 -> 44986 | F88: =I22 -> 9633.16 | G88: ='Indicadores Energéticos'!P10 -> 117.89 | H88: =F88-$F$99 -> 160.9275 | I88: =H88^2 -> 25897.66 | P88: =B22 -> 44986 | Q88: =I22 -> 9633.16 | R88: ='Indicadores Energéticos'!P10 -> 117.89 | S88: =Q88-$Q$98 -> 160.9275 | T88: =S88^2 -> 25897.66 | X88: =P88 -> 44986 | Y88: =R88 -> 117.89 | Z88: =Q88 -> 9633.16 | AA88: =Z88/1000 -> 9.63316 | AB88: =Z88*Z88 -> 92797772 | AC88: =Z88*Y88 -> 1135653.2 | AD88: =($AI$75*Y88)+$AI$77 -> 9227.7776 | AE88: =AD88+($AI$78*$Z$100) -> 9991.0374 | AF88: =AD88-($AI$78*$Z$100) -> 8464.5179 | AH88: Observaciones | AI88: 24
E89: =B23 -> 45017 | F89: =I23 -> 9796.5 | G89: ='Indicadores Energéticos'!P11 -> 214.56 | H89: =F89-$F$99 -> 324.2675 | I89: =H89^2 -> 105149.41 | P89: =B23 -> 45017 | Q89: =I23 -> 9796.5 | R89: ='Indicadores Energéticos'!P11 -> 214.56 | S89: =Q89-$Q$98 -> 324.2675 | T89: =S89^2 -> 105149.41 | X89: =P89 -> 45017 | Y89: =R89 -> 214.56 | Z89: =Q89 -> 9796.5 | AA89: =Z89/1000 -> 9.7965 | AB89: =Z89*Z89 -> 95971412 | AC89: =Z89*Y89 -> 2101937 | AD89: =($AI$75*Y89)+$AI$77 -> 10113.161 | AE89: =AD89+($AI$78*$Z$100) -> 10876.421 | AF89: =AD89-($AI$78*$Z$100) -> 9349.9013
E90: =B24 -> 45047 | F90: =I24 -> 11503.69 | G90: ='Indicadores Energéticos'!P12 -> 314.16 | H90: =F90-$F$99 -> 2031.4575 | I90: =H90^2 -> 4126819.6 | P90: =B24 -> 45047 | Q90: =I24 -> 11503.69 | R90: ='Indicadores Energéticos'!P12 -> 314.16 | S90: =Q90-$Q$98 -> 2031.4575 | T90: =S90^2 -> 4126819.6 | X90: =P90 -> 45047 | Y90: =R90 -> 314.16 | Z90: =Q90 -> 11503.69 | AA90: =Z90/1000 -> 11.50369 | AB90: =Z90*Z90 -> 1.3233488e+08 | AC90: =Z90*Y90 -> 3613999.3 | AD90: =($AI$75*Y90)+$AI$77 -> 11025.38 | AE90: =AD90+($AI$78*$Z$100) -> 11788.64 | AF90: =AD90-($AI$78*$Z$100) -> 10262.12 | AH90: ANÁLISIS DE VARIANZA
E91: =B25 -> 45078 | F91: =I25 -> 9636.34 | G91: ='Indicadores Energéticos'!P13 -> 199.52 | H91: =F91-$F$99 -> 164.1075 | I91: =H91^2 -> 26931.272 | P91: =B25 -> 45078 | Q91: =I25 -> 9636.34 | R91: ='Indicadores Energéticos'!P13 -> 199.52 | S91: =Q91-$Q$98 -> 164.1075 | T91: =S91^2 -> 26931.272 | X91: =P91 -> 45078 | Y91: =R91 -> 199.52 | Z91: =Q91 -> 9636.34 | AA91: =Z91/1000 -> 9.63634 | AB91: =Z91*Z91 -> 92859049 | AC91: =Z91*Y91 -> 1922642.6 | AD91: =($AI$75*Y91)+$AI$77 -> 9975.4124 | AE91: =AD91+($AI$78*$Z$100) -> 10738.672 | AF91: =AD91-($AI$78*$Z$100) -> 9212.1526 | AI91: Grados de libertad | AJ91: Suma de cuadrados | AK91: Promedio de los cuadrados | AL91: F | AM91: Valor crítico de F
E92: =B26 -> 45108 | F92: =I26 -> 10051.65 | G92: ='Indicadores Energéticos'!P14 -> 212.12 | H92: =F92-$F$99 -> 579.4175 | I92: =H92^2 -> 335724.64 | P92: =B26 -> 45108 | Q92: =I26 -> 10051.65 | R92: ='Indicadores Energéticos'!P14 -> 212.12 | S92: =Q92-$Q$98 -> 579.4175 | T92: =S92^2 -> 335724.64 | X92: =P92 -> 45108 | Y92: =R92 -> 212.12 | Z92: =Q92 -> 10051.65 | AA92: =Z92/1000 -> 10.05165 | AB92: =Z92*Z92 -> 1.0103567e+08 | AC92: =Z92*Y92 -> 2132156 | AD92: =($AI$75*Y92)+$AI$77 -> 10090.814 | AE92: =AD92+($AI$78*$Z$100) -> 10854.073 | AF92: =AD92-($AI$78*$Z$100) -> 9327.5538 | AH92: Regresión | AI92: 1 | AJ92: 9280352.5 | AK92: 9280352.5 | AL92: 77.101914 | AM92: 1.2162427e-08
E93: =B27 -> 45139 | F93: =I27 -> 8620.61 | G93: ='Indicadores Energéticos'!P15 -> 112.32 | H93: =F93-$F$99 -> -851.6225 | I93: =H93^2 -> 725260.88 | P93: =B27 -> 45139 | Q93: =I27 -> 8620.61 | R93: ='Indicadores Energéticos'!P15 -> 112.32 | S93: =Q93-$Q$98 -> -851.6225 | T93: =S93^2 -> 725260.88 | X93: =P93 -> 45139 | Y93: =R93 -> 112.32 | Z93: =Q93 -> 8620.61 | AA93: =Z93/1000 -> 8.62061 | AB93: =Z93*Z93 -> 74314917 | AC93: =Z93*Y93 -> 968266.92 | AD93: =($AI$75*Y93)+$AI$77 -> 9176.763 | AE93: =AD93+($AI$78*$Z$100) -> 9940.0227 | AF93: =AD93-($AI$78*$Z$100) -> 8413.5033 | AH93: Residuos | AI93: 22 | AJ93: 2648024.5 | AK93: 120364.75
E94: =B28 -> 45170 | F94: =I28 -> 9013.66 | G94: ='Indicadores Energéticos'!P16 -> 81.5 | H94: =F94-$F$99 -> -458.5725 | I94: =H94^2 -> 210288.74 | P94: =B28 -> 45170 | Q94: =I28 -> 9013.66 | R94: ='Indicadores Energéticos'!P16 -> 81.5 | S94: =Q94-$Q$98 -> -458.5725 | T94: =S94^2 -> 210288.74 | X94: =P94 -> 45170 | Y94: =R94 -> 81.5 | Z94: =Q94 -> 9013.66 | AA94: =Z94/1000 -> 9.01366 | AB94: =Z94*Z94 -> 81246067 | AC94: =Z94*Y94 -> 734613.29 | AD94: =($AI$75*Y94)+$AI$77 -> 8894.4881 | AE94: =AD94+($AI$78*$Z$100) -> 9657.7478 | AF94: =AD94-($AI$78*$Z$100) -> 8131.2284 | AH94: Total | AI94: 23 | AJ94: 11928377
E95: =B29 -> 45200 | F95: =I29 -> 9003.9 | G95: ='Indicadores Energéticos'!P17 -> 70.14 | H95: =F95-$F$99 -> -468.3325 | I95: =H95^2 -> 219335.33 | P95: =B29 -> 45200 | Q95: =I29 -> 9003.9 | R95: ='Indicadores Energéticos'!P17 -> 70.14 | S95: =Q95-$Q$98 -> -468.3325 | T95: =S95^2 -> 219335.33 | X95: =P95 -> 45200 | Y95: =R95 -> 70.14 | Z95: =Q95 -> 9003.9 | AA95: =Z95/1000 -> 9.0039 | AB95: =Z95*Z95 -> 81070215 | AC95: =Z95*Y95 -> 631533.55 | AD95: =($AI$75*Y95)+$AI$77 -> 8790.4439 | AE95: =AD95+($AI$78*$Z$100) -> 9553.7036 | AF95: =AD95-($AI$78*$Z$100) -> 8027.1842
E96: =B30 -> 45231 | F96: =I30 -> 10060.05 | G96: ='Indicadores Energéticos'!P18 -> 181.45 | H96: =F96-$F$99 -> 587.8175 | I96: =H96^2 -> 345529.41 | P96: =B30 -> 45231 | Q96: =I30 -> 10060.05 | R96: ='Indicadores Energéticos'!P18 -> 181.45 | S96: =Q96-$Q$98 -> 587.8175 | T96: =S96^2 -> 345529.41 | X96: =P96 -> 45231 | Y96: =R96 -> 181.45 | Z96: =Q96 -> 10060.05 | AA96: =Z96/1000 -> 10.06005 | AB96: =Z96*Z96 -> 1.0120461e+08 | AC96: =Z96*Y96 -> 1825396.1 | AD96: =($AI$75*Y96)+$AI$77 -> 9809.9124 | AE96: =AD96+($AI$78*$Z$100) -> 10573.172 | AF96: =AD96-($AI$78*$Z$100) -> 9046.6527 | AI96: Coeficientes | AJ96: Error típico | AK96: Estadístico t | AL96: Probabilidad | AM96: Inferior 95% | AN96: Superior 95% | AO96: Inferior 95,0% | AP96: Superior 95,0%
E97: =B31 -> 45261 | F97: =I31 -> 8468.25 | G97: ='Indicadores Energéticos'!P19 -> 59.85 | H97: =F97-$F$99 -> -1003.9825 | I97: =H97^2 -> 1007980.9 | P97: =B31 -> 45261 | Q97: =I31 -> 8468.25 | R97: ='Indicadores Energéticos'!P19 -> 59.85 | S97: =Q97-$Q$98 -> -1003.9825 | T97: =S97^2 -> 1007980.9 | X97: =P97 -> 45261 | Y97: =R97 -> 59.85 | Z97: =Q97 -> 8468.25 | AA97: =Z97/1000 -> 8.46825 | AB97: =Z97*Z97 -> 71711258 | AC97: =Z97*Y97 -> 506824.76 | AD97: =($AI$75*Y97)+$AI$77 -> 8696.1996 | AE97: =AD97+($AI$78*$Z$100) -> 9459.4593 | AF97: =AD97-($AI$78*$Z$100) -> 7932.9399 | AH97: Intercepción | AI97: 8148.044 | AJ97: 166.60583 | AK97: 48.906117 | AL97: 6.088862e-24 | AM97: 7802.5247 | AN97: 8493.5634 | AO97: 7802.5247 | AP97: 8493.5634
P98: media | Q98: =AVERAGE(Q74:Q97) -> 9472.2325 | S98: Sumatoria □s | T98: =SUM(T74:T97) -> 11928377 | Y98: suma | Z98: =SUM(Z74:Z97) -> 227333.58 | AA98: suma | AB98: =SUM(AB74:AB97) -> 2.1652849e+09 | AC98: =SUM(AC74:AC97) -> 33881304 | AH98: Variable X 1 | AI98: 9.1588228 | AJ98: 1.0430547 | AK98: 8.7807695 | AL98: 1.2162427e-08 | AM98: 6.9956598 | AN98: 11.321986 | AO98: 6.9956598 | AP98: 11.321986
E99: media | F99: =AVERAGE(F74:F97) -> 9472.2325 | H99: Sumatoria □s | I99: =SUM(I74:I97) -> 11928377 | S99: varianza | T99: =T98/23 -> 518625.08
H100: varianza | I100: =I99/23 -> 518625.08 | S100: desv std | T100: =SQRT(T99) -> 720.15629 | Y100: Sxy | Z100: =STEYX(Z74:Z97,Y74:Y97) -> 346.93623
H101: desv std | I101: =SQRT(I100) -> 720.15629 | L101: Tamaño mínimo de la Muestra | P101: n₀ | S101: Coef. de var. (cv) | T101: =T100/Q98 -> 0.076028148
H102: Coef. de var. (cv) | I102: =I101/F99 -> 0.076028148 | Q102: =(O103^2*O105^2)/O104^2 -> 384.16 | R102: =(K103^2*K105^2)/K104^2 -> 428.49
K103: 2.07 | L103: 1.64 | M103: 1.96 | N103: z | O103: 1.96 | P103: valor de distribución normal estándar | X103: 6) Filtrado de datos
K104: =1-K106 -> 0.05 | L104: =1-L106 -> 0.1 | M104: =1-M106 -> 0.05 | N104: e | O104: =1-O106 -> 0.05 | P104: nivel deseado de precisión
K105: 0.5 | L105: 0.5 | M105: 0.5 | N105: cv | O105: 0.5 | P105: coeficiente de varianza | X105: Mes | Y105: Producción [m³/mes] | Z105: Consumo [kWh/mes] | AA105: Consumo [MWh/mes] | AB105: E*E | AC105: E*P | AD105: Emodelo | AE105: Emod+Z*Sxy | AF105: Emod-Z*Sxy
D106: n₀ | E106: =(D111^2*D113^2)/D112^2 -> 67.24 | K106: 0.95 | L106: 0.9 | M106: 0.95 | N106: ic | O106: 0.95 | P106: intervalo de confianza | X106: =X74 -> 44562 | Y106: =Y74 -> 72.34458 | Z106: =Z74 -> 8674.83 | AA106: =AA74 -> 8.67483 | AB106: =Z106*Z106 -> 75252676 | AC106: =Z106*Y106 -> 627576.93 | AD106: =($AI$75*Y106)+$AI$77 -> 8810.6352 | AE106: =AD106+($AI$78*$Z$100) -> 9573.8949 | AF106: =AD106-($AI$78*$Z$100) -> 8047.3755
U107: Dato filtrado | V107: =X75 -> 44593 | X107: =X76 -> 44621 | Y107: =Y76 -> 104.69536 | Z107: =Z76 -> 9689.25 | AA107: =AA76 -> 9.68925 | AB107: =Z107*Z107 -> 93881566 | AC107: =Z107*Y107 -> 1014419.5 | AD107: =($AI$75*Y107)+$AI$77 -> 9106.9303 | AE107: =AD107+($AI$78*$Z$100) -> 9870.19 | AF107: =AD107-($AI$78*$Z$100) -> 8343.6706
M108: 2a) Ajustar la estimación inicial para grupos pequeños | X108: =X77 -> 44652 | Y108: =Y77 -> 198.85866 | Z108: =Z77 -> 9823.56 | AA108: =AA77 -> 9.82356 | AB108: =Z108*Z108 -> 96502331 | AC108: =Z108*Y108 -> 1953500 | AD108: =($AI$75*Y108)+$AI$77 -> 9969.3553 | AE108: =AD108+($AI$78*$Z$100) -> 10732.615 | AF108: =AD108-($AI$78*$Z$100) -> 9206.0956
X109: =X78 -> 44682 | Y109: =Y78 -> 265.41 | Z109: =Z78 -> 10503.89 | AA109: =AA78 -> 10.50389 | AB109: =Z109*Z109 -> 1.1033171e+08 | AC109: =Z109*Y109 -> 2787837.4 | AD109: =($AI$75*Y109)+$AI$77 -> 10578.887 | AE109: =AD109+($AI$78*$Z$100) -> 11342.147 | AF109: =AD109-($AI$78*$Z$100) -> 9815.6275
P110: n | Q110: =(Q102*O112)/(Q102+O112) -> 22.588789 | R110: =(R102*O112)/(R102+O112) -> 22.727044 | X110: =X79 -> 44713 | Y110: =Y79 -> 188.35894 | Z110: =Z79 -> 9931.33 | AA110: =AA79 -> 9.93133 | AB110: =Z110*Z110 -> 98631316 | AC110: =Z110*Y110 -> 1870654.8 | AD110: =($AI$75*Y110)+$AI$77 -> 9873.1902 | AE110: =AD110+($AI$78*$Z$100) -> 10636.45 | AF110: =AD110-($AI$78*$Z$100) -> 9109.9305
B111: 1.96 | C111: z | D111: 1.64 | E111: valor de distribución normal estándar | H111: 1.64 | Q111: =Q110 -> 22.588789 | R111: , solo se requieren 23 datos | X111: =X80 -> 44743 | Y111: =Y80 -> 177.69752 | Z111: =Z80 -> 9668.73 | AA111: =AA80 -> 9.66873 | AB111: =Z111*Z111 -> 93484340 | AC111: =Z111*Y111 -> 1718109.3 | AD111: =($AI$75*Y111)+$AI$77 -> 9775.5441 | AE111: =AD111+($AI$78*$Z$100) -> 10538.804 | AF111: =AD111-($AI$78*$Z$100) -> 9012.2844
B112: =1-B114 -> 0.05 | C112: e | D112: =1-D114 -> 0.1 | E112: nivel deseado de precisión | H112: =1-H114 -> 0.1 | N112: N | O112: 24 | X112: =X81 -> 44774 | Y112: =Y81 -> 190.06218 | Z112: =Z81 -> 9498.13 | AA112: =AA81 -> 9.49813 | AB112: =Z112*Z112 -> 90214473 | AC112: =Z112*Y112 -> 1805235.3 | AD112: =($AI$75*Y112)+$AI$77 -> 9888.7899 | AE112: =AD112+($AI$78*$Z$100) -> 10652.05 | AF112: =AD112-($AI$78*$Z$100) -> 9125.5301
B113: 0.5 | C113: cv | D113: 0.5 | E113: coeficiente de varianza | H113: 0.5 | X113: =X82 -> 44805 | Y113: =Y82 -> 118.91 | Z113: =Z82 -> 9284.99 | AA113: =AA82 -> 9.28499 | AB113: =Z113*Z113 -> 86211039 | AC113: =Z113*Y113 -> 1104078.2 | AD113: =($AI$75*Y113)+$AI$77 -> 9237.1196 | AE113: =AD113+($AI$78*$Z$100) -> 10000.379 | AF113: =AD113-($AI$78*$Z$100) -> 8473.8599
B114: 0.95 | C114: ic | D114: 0.9 | E114: intervalo de confianza | H114: 0.9 | X114: =X83 -> 44835 | Y114: =Y83 -> 112 | Z114: =Z83 -> 9045.56 | AA114: =AA83 -> 9.04556 | AB114: =Z114*Z114 -> 81822156 | AC114: =Z114*Y114 -> 1013102.7 | AD114: =($AI$75*Y114)+$AI$77 -> 9173.8322 | AE114: =AD114+($AI$78*$Z$100) -> 9937.0919 | AF114: =AD114-($AI$78*$Z$100) -> 8410.5725
X115: =X84 -> 44866 | Y115: =Y84 -> 151.82552 | Z115: =Z84 -> 9676.81 | AA115: =AA84 -> 9.67681 | AB115: =Z115*Z115 -> 93640652 | AC115: =Z115*Y115 -> 1469186.7 | AD115: =($AI$75*Y115)+$AI$77 -> 9538.5871 | AE115: =AD115+($AI$78*$Z$100) -> 10301.847 | AF115: =AD115-($AI$78*$Z$100) -> 8775.3274
B116: 2a) Ajustar la estimación inicial para grupos pequeños | M116: 3) Definir las variables que influyen en la LBE | X116: =X85 -> 44896 | Y116: =Y85 -> 41.00712 | Z116: =Z85 -> 8577.93 | AA116: =AA85 -> 8.57793 | AB116: =Z116*Z116 -> 73580883 | AC116: =Z116*Y116 -> 351756.2 | AD116: =($AI$75*Y116)+$AI$77 -> 8523.621 | AE116: =AD116+($AI$78*$Z$100) -> 9286.8807 | AF116: =AD116-($AI$78*$Z$100) -> 7760.3613
M117: =R73 -> Emulsión Asfáltica [m³/mes] | O117: variable independiente | X117: =X86 -> 44927 | Y117: =Y86 -> 81.25 | Z117: =Z86 -> 8475 | AA117: =AA86 -> 8.475 | AB117: =Z117*Z117 -> 71825625 | AC117: =Z117*Y117 -> 688593.75 | AD117: =($AI$75*Y117)+$AI$77 -> 8892.1984 | AE117: =AD117+($AI$78*$Z$100) -> 9655.4581 | AF117: =AD117-($AI$78*$Z$100) -> 8128.9387
E118: n | F118: =(E106*D120)/(E106+D120) -> 10.182736 | M118: =Q73 -> Consumo [kWh/mes] | O118: variable dependiente | X118: =X87 -> 44958 | Y118: =Y87 -> 104.56 | Z118: =Z87 -> 8802.64 | AA118: =AA87 -> 8.80264 | AB118: =Z118*Z118 -> 77486471 | AC118: =Z118*Y118 -> 920404.04 | AD118: =($AI$75*Y118)+$AI$77 -> 9105.6905 | AE118: =AD118+($AI$78*$Z$100) -> 9868.9503 | AF118: =AD118-($AI$78*$Z$100) -> 8342.4308
F119: =F118 -> 10.182736 | G119: , solo se requieren 10 datos | X119: =X88 -> 44986 | Y119: =Y88 -> 117.89 | Z119: =Z88 -> 9633.16 | AA119: =AA88 -> 9.63316 | AB119: =Z119*Z119 -> 92797772 | AC119: =Z119*Y119 -> 1135653.2 | AD119: =($AI$75*Y119)+$AI$77 -> 9227.7776 | AE119: =AD119+($AI$78*$Z$100) -> 9991.0374 | AF119: =AD119-($AI$78*$Z$100) -> 8464.5179
C120: N | D120: 12 | X120: =X89 -> 45017 | Y120: =Y89 -> 214.56 | Z120: =Z89 -> 9796.5 | AA120: =AA89 -> 9.7965 | AB120: =Z120*Z120 -> 95971412 | AC120: =Z120*Y120 -> 2101937 | AD120: =($AI$75*Y120)+$AI$77 -> 10113.161 | AE120: =AD120+($AI$78*$Z$100) -> 10876.421 | AF120: =AD120-($AI$78*$Z$100) -> 9349.9013
M121: 4) Toma de datos | X121: =X90 -> 45047 | Y121: =Y90 -> 314.16 | Z121: =Z90 -> 11503.69 | AA121: =AA90 -> 11.50369 | AB121: =Z121*Z121 -> 1.3233488e+08 | AC121: =Z121*Y121 -> 3613999.3 | AD121: =($AI$75*Y121)+$AI$77 -> 11025.38 | AE121: =AD121+($AI$78*$Z$100) -> 11788.64 | AF121: =AD121-($AI$78*$Z$100) -> 10262.12
O122: Período anual, 12 datos por año | X122: =X91 -> 45078 | Y122: =Y91 -> 199.52 | Z122: =Z91 -> 9636.34 | AA122: =AA91 -> 9.63634 | AB122: =Z122*Z122 -> 92859049 | AC122: =Z122*Y122 -> 1922642.6 | AD122: =($AI$75*Y122)+$AI$77 -> 9975.4124 | AE122: =AD122+($AI$78*$Z$100) -> 10738.672 | AF122: =AD122-($AI$78*$Z$100) -> 9212.1526
X123: =X92 -> 45108 | Y123: =Y92 -> 212.12 | Z123: =Z92 -> 10051.65 | AA123: =AA92 -> 10.05165 | AB123: =Z123*Z123 -> 1.0103567e+08 | AC123: =Z123*Y123 -> 2132156 | AD123: =($AI$75*Y123)+$AI$77 -> 10090.814 | AE123: =AD123+($AI$78*$Z$100) -> 10854.073 | AF123: =AD123-($AI$78*$Z$100) -> 9327.5538
B124: 3) Definir las variables que influyen en la LBE | X124: =X93 -> 45139 | Y124: =Y93 -> 112.32 | Z124: =Z93 -> 8620.61 | AA124: =AA93 -> 8.62061 | AB124: =Z124*Z124 -> 74314917 | AC124: =Z124*Y124 -> 968266.92 | AD124: =($AI$75*Y124)+$AI$77 -> 9176.763 | AE124: =AD124+($AI$78*$Z$100) -> 9940.0227 | AF124: =AD124-($AI$78*$Z$100) -> 8413.5033
B125: =G73 -> Emulsión Asfáltica [m³/mes] | D125: variable independiente | M125: 5) Verificación de cv de los datos tomados | X125: =X94 -> 45170 | Y125: =Y94 -> 81.5 | Z125: =Z94 -> 9013.66 | AA125: =AA94 -> 9.01366 | AB125: =Z125*Z125 -> 81246067 | AC125: =Z125*Y125 -> 734613.29 | AD125: =($AI$75*Y125)+$AI$77 -> 8894.4881 | AE125: =AD125+($AI$78*$Z$100) -> 9657.7478 | AF125: =AD125-($AI$78*$Z$100) -> 8131.2284
B126: =F73 -> Consumo [kWh/mes] | D126: variable dependiente | N126: 1. Cantidad de datos requeridos | R126: =Q111 -> 22.588789 | X126: =X95 -> 45200 | Y126: =Y95 -> 70.14 | Z126: =Z95 -> 9003.9 | AA126: =AA95 -> 9.0039 | AB126: =Z126*Z126 -> 81070215 | AC126: =Z126*Y126 -> 631533.55 | AD126: =($AI$75*Y126)+$AI$77 -> 8790.4439 | AE126: =AD126+($AI$78*$Z$100) -> 9553.7036 | AF126: =AD126-($AI$78*$Z$100) -> 8027.1842
N127: 2. Comprobación del cv asumido | R127: cv = | S127: =T101 -> 0.076028148 | T127: < | U127: =O105 -> 0.5 | X127: =X96 -> 45231 | Y127: =Y96 -> 181.45 | Z127: =Z96 -> 10060.05 | AA127: =AA96 -> 10.06005 | AB127: =Z127*Z127 -> 1.0120461e+08 | AC127: =Z127*Y127 -> 1825396.1 | AD127: =($AI$75*Y127)+$AI$77 -> 9809.9124 | AE127: =AD127+($AI$78*$Z$100) -> 10573.172 | AF127: =AD127-($AI$78*$Z$100) -> 9046.6527
R128: =IF(S127<U127,"Si los datos son buenos","No los datos son malos") -> Si los datos son buenos | X128: =X97 -> 45261 | Y128: =Y97 -> 59.85 | Z128: =Z97 -> 8468.25 | AA128: =AA97 -> 8.46825 | AB128: =Z128*Z128 -> 71711258 | AC128: =Z128*Y128 -> 506824.76 | AD128: =($AI$75*Y128)+$AI$77 -> 8696.1996 | AE128: =AD128+($AI$78*$Z$100) -> 9459.4593 | AF128: =AD128-($AI$78*$Z$100) -> 7932.9399
B129: 4) Toma de datos | Y129: suma | Z129: =SUM(Z106:Z128) -> 217440.46 | AA129: suma | AB129: =SUM(AB106:AB128) -> 2.0674111e+09 | AC129: =SUM(AC106:AC128) -> 32897478
D130: Período anual, 12 datos por año
O131: N | P131: 24 | T131: 543098
M132: Nivel de confianza 95% | O132: z | P132: 1.96 | Q132: =P132^2 -> 3.8416 | T132: 1.96 | U132: =T132^2 -> 3.8416 | Y132: Sxy | Z132: =STEYX(Z106:Z128,Y106:Y128) -> 301.38764
B133: 5) Verificación de cv de los datos tomados | M133: error | O133: e | P133: 0.03 | Q133: =P133^2 -> 0.0009 | T133: 0.03 | U133: =T133^2 -> 0.0009
C134: 1. Cantidad de datos requeridos | G134: =F119 -> 10.182736 | M134: probabilidad que ocurra el evento | O134: p | P134: 0.5 | T134: 0.5
C135: 2. Comprobación del cv asumido | G135: cv = | H135: =I102 -> 0.076028148 | I135: < | J135: =D113 -> 0.5 | M135: probabilidad que no ocurra el evento | O135: q | P135: 0.5 | T135: 0.5
G136: =IF(H135<J135,"Si los datos son buenos","No los datos son malos") -> Si los datos son buenos
O137: num | P137: =P131*Q132*P134*P135 -> 23.0496 | T137: =T131*U132*T134*T135 -> 521591.32 | AH137: 7) Determinación del modelo de línea base y su nivel de significancia respecto a la variable independiente
...

Sheet Consumo Térmico de la empresa
B2: media | C2: parafina | D2: 889
B3: top | C3: kerosene | D3: =D4/20 -> 1091
C4: 20 litros | D4: =21820 -> 21820
B5: 3.78541 | C5: galon $ | D5: =B5*D3 -> 4129.8823 | J5: Conversterin
C6: 1 dollar | D6: 966.19 | J6: https://es.converterin.com/economia-de-combustible/us-galones-de-gasoil-to-joule.html | R6: Factor de conversión de GJ a kW
C7: galon USD | D7: =D5/D6 -> 4.2743998 | L7: US galon de kerosene | N7: Joule | O7: Giga Joule | R7: https://es.converterin.com/economia-de-combustible/gigajoule-to-us-galones-de-kerosene.html
C8: galones x día | D8: =B5*3 -> 11.35623 | L8: 1 | N8: 140500000 | O8: =N8/1000000000 -> 0.1405 | R8: =277.77777778 -> 277.77778
N9: =142200000 -> 142200000 | O9: =N9/1000000000 -> 0.1422 | P9: Oficial
B10: CONSUMO [Kerosene] | N10: 130001500 | O10: =N10/1000000000 -> 0.1300015
N11: 140900000
B12: Datos de consumo de combustible 2022 | F12: Costo energía térmica | G12: =G13*G14*O8 -> 4119.7641 | N12: 140500000
F13: Galones | G13: 7.1 | N13: 146520000 | O13: =N13/1000000000 -> 0.14652
C14: Kerosene [gal] | D14: Kerosene [US$] | F14: Valor Galón | G14: =D5 -> 4129.8823
B15: Media Consumo mes | C15: =C37 -> 287.09912 | D15: 0
B16: Media Consumo anual | C16: =C15*12 -> 3445.1894 | D16: 0 | F16: Conversión
B17: Media Costo mes | C17: 0 | D17: =C15*D19 -> 1227.1764 | F17: Galón | G17: [GJ]
B18: Media Costo anual | C18: 0 | D18: =D17*12 -> 14726.117 | F18: 1 | G18: =F18*$O$8 -> 0.1405 | S18: =C25 -> 176.702 | T18: =S18*O9 -> 25.127024 | U18: =T18*R8 -> 6979.729
B19: Media Costo Galón | C19: 0 | D19: =$D$7 -> 4.2743998
B22: Historia de consumo de combustible y energía de la empresa 2022 | M22: Comportamiento del consumo de combustible expresado en Giga Joule de energía
M23: Consumo de Kerosene año 2022
B24: Mes | C24: Kerosene [gal] | D24: Total Energía [GJ] | J24: Días | K24: gal diarios
B25: ='Consumo Eléctrico'!B8 -> 44562 | C25: 176.702 | D25: =C25*$O$8 -> 24.826631 | F25: =D25*D5 -> 102531.06 | J25: ='Consumo Eléctrico'!E8 -> 31 | K25: =C25/J25 -> 5.7000645 | S25: Consumo [kwh]
B26: ='Consumo Eléctrico'!B9 -> 44593 | C26: 229.2886 | D26: =C26*$O$8 -> 32.215048 | J26: ='Consumo Eléctrico'!E9 -> 30 | K26: =C26/J26 -> 7.6429533 | S26: =D25*$R$8 -> 6896.2864
B27: ='Consumo Eléctrico'!B10 -> 44621 | C27: 239.4646 | D27: =C27*$O$8 -> 33.644776 | J27: ='Consumo Eléctrico'!E10 -> 30 | K27: =C27/J27 -> 7.9821533 | S27: =D26*$R$8 -> 8948.6245
B28: ='Consumo Eléctrico'!B11 -> 44652 | C28: 422.1238 | D28: =C28*$O$8 -> 59.308394 | J28: ='Consumo Eléctrico'!E11 -> 31 | K28: =C28/J28 -> 13.616897 | S28: =D27*$R$8 -> 9345.7712
B29: ='Consumo Eléctrico'!B12 -> 44682 | C29: 396.8852 | D29: =C29*$O$8 -> 55.762371 | J29: ='Consumo Eléctrico'!E12 -> 30 | K29: =C29/J29 -> 13.229507 | S29: =D28*$R$8 -> 16474.554
B30: ='Consumo Eléctrico'!B13 -> 44713 | C30: 401.7506 | D30: =C30*$O$8 -> 56.445959 | J30: ='Consumo Eléctrico'!E13 -> 31 | K30: =C30/J30 -> 12.959697 | S30: =D29*$R$8 -> 15489.547
B31: ='Consumo Eléctrico'!B14 -> 44743 | C31: 381.07 | D31: =C31*$O$8 -> 53.540335 | J31: ='Consumo Eléctrico'!E14 -> 30 | K31: =C31/J31 -> 12.702333 | S31: =D30*$R$8 -> 15679.433
B32: ='Consumo Eléctrico'!B15 -> 44774 | C32: 405.0578 | D32: =C32*$O$8 -> 56.910621 | J32: ='Consumo Eléctrico'!E15 -> 30 | K32: =C32/J32 -> 13.501927 | S32: =D31*$R$8 -> 14872.315
B33: ='Consumo Eléctrico'!B16 -> 44805 | C33: 173.5856 | D33: =C33*$O$8 -> 24.388777 | J33: ='Consumo Eléctrico'!E16 -> 30 | K33: =C33/J33 -> 5.7861867 | S33: =D32*$R$8 -> 15808.506
B34: ='Consumo Eléctrico'!B17 -> 44835 | C34: 172.45 | D34: =C34*$O$8 -> 24.229225 | J34: ='Consumo Eléctrico'!E17 -> 31 | K34: =C34/J34 -> 5.5629032 | S34: =D33*$R$8 -> 6774.6602
B35: ='Consumo Eléctrico'!B18 -> 44866 | C35: 330.9002 | D35: =C35*$O$8 -> 46.491478 | J35: ='Consumo Eléctrico'!E18 -> 31 | K35: =C35/J35 -> 10.6742 | S35: =D34*$R$8 -> 6730.3403
B36: ='Consumo Eléctrico'!B19 -> 44896 | C36: 115.911 | D36: =C36*$O$8 -> 16.285496 | J36: ='Consumo Eléctrico'!E19 -> 30 | K36: =C36/J36 -> 3.8637 | S36: =D35*$R$8 -> 12914.299
B37: Media Consumo mes | C37: =AVERAGE(C25:C36) -> 287.09912 | D37: =AVERAGE(D25:D36) -> 40.337426 | J37: =AVERAGE(J25:J36) -> 30.416667 | K37: =AVERAGE(K25:K36) -> 9.4352101 | S37: =D36*$R$8 -> 4523.7488
B38: Total (anual) 2022 | C38: =SUM(C25:C36) -> 3445.1894 | D38: =SUM(D25:D36) -> 484.04911 | S38: =AVERAGE(S26:S37) -> 11204.841
F39: =B24 -> Mes | G39: =D24 -> Total Energía [GJ] | S39: =SUM(S26:S37) -> 134458.09
F40: =B25 -> 44562 | G40: =D25 -> 24.826631
F41: =B26 -> 44593 | G41: =D26 -> 32.215048
F42: =B27 -> 44621 | G42: =D27 -> 33.644776
B43: Datos de consumo de combustible 2023 | F43: =B28 -> 44652 | G43: =D28 -> 59.308394
F44: =B29 -> 44682 | G44: =D29 -> 55.762371
C45: Kerosene [gal] | D45: Kerosene [US$] | F45: =B30 -> 44713 | G45: =D30 -> 56.445959
B46: Media Consumo mes | C46: =C68 -> 272.81274 | D46: 0 | F46: =B31 -> 44743 | G46: =D31 -> 53.540335
B47: Media Consumo anual | C47: =C46*12 -> 3273.7529 | D47: 0 | F47: =B32 -> 44774 | G47: =D32 -> 56.910621
B48: Media Costo mes | C48: 0 | D48: =C46*D50 -> 1166.1107 | F48: =B33 -> 44805 | G48: =D33 -> 24.388777
B49: Media Costo anual | C49: 0 | D49: =D48*12 -> 13993.329 | F49: =B34 -> 44835 | G49: =D34 -> 24.229225
B50: Media Costo Galón | C50: 0 | D50: =$D$7 -> 4.2743998 | F50: =B35 -> 44866 | G50: =D35 -> 46.491478
F51: =B36 -> 44896 | G51: =D36 -> 16.285496
F52: =B56 -> 44927 | G52: =D56 -> 23.186715
B53: Historia de consumo de combustible y energía de la empresa 2023 | F53: =B57 -> 44958 | G53: =D57 -> 31.607217
F54: =B58 -> 44986 | G54: =D58 -> 33.009969 | M54: Consumo de Kerosene año 2023
B55: Mes | C55: Kerosene [gal] | D55: Total Energía [GJ] | F55: =B59 -> 45017 | G55: =D59 -> 58.189368 | J55: Días | K55: gal diarios | S55: Consumo [kwh]
B56: ='Consumo Eléctrico'!B20 -> 44927 | C56: 165.03 | D56: =C56*$O$8 -> 23.186715 | F56: =B60 -> 45047 | G56: =D60 -> 51.02783 | J56: ='Consumo Eléctrico'!E20 -> 31 | K56: =C56/J56 -> 5.3235484 | S56: =D56*$R$8 -> 6440.7542
B57: ='Consumo Eléctrico'!B21 -> 44958 | C57: 224.9624 | D57: =C57*$O$8 -> 31.607217 | F57: =B61 -> 45078 | G57: =D61 -> 49.523342 | J57: ='Consumo Eléctrico'!E21 -> 30 | K57: =C57/J57 -> 7.4987467 | S57: =D57*$R$8 -> 8779.7826
B58: ='Consumo Eléctrico'!B22 -> 44986 | C58: 234.9464 | D58: =C58*$O$8 -> 33.009969 | F58: =B62 -> 45108 | G58: =D62 -> 51.519945 | J58: ='Consumo Eléctrico'!E22 -> 30 | K58: =C58/J58 -> 7.8315467 | S58: =D58*$R$8 -> 9169.4359
B59: ='Consumo Eléctrico'!B23 -> 45017 | C59: 414.1592 | D59: =C59*$O$8 -> 58.189368 | F59: =B63 -> 45139 | G59: =D63 -> 54.76305 | J59: ='Consumo Eléctrico'!E23 -> 31 | K59: =C59/J59 -> 13.359974 | S59: =D59*$R$8 -> 16163.713
B60: ='Consumo Eléctrico'!B24 -> 45047 | C60: 363.1874 | D60: =C60*$O$8 -> 51.02783 | F60: =B64 -> 45170 | G60: =D64 -> 23.468446 | J60: ='Consumo Eléctrico'!E24 -> 30 | K60: =C60/J60 -> 12.106247 | S60: =D60*$R$8 -> 14174.397
B61: ='Consumo Eléctrico'!B25 -> 45078 | C61: 352.4793 | D61: =C61*$O$8 -> 49.523342 | F61: =B65 -> 45200 | G61: =D65 -> 23.25837 | J61: ='Consumo Eléctrico'!E25 -> 30 | K61: =C61/J61 -> 11.74931 | S61: =D61*$R$8 -> 13756.484
B62: ='Consumo Eléctrico'!B26 -> 45108 | C62: 366.69 | D62: =C62*$O$8 -> 51.519945 | F62: =B66 -> 45231 | G62: =D66 -> 44.737083 | J62: ='Consumo Eléctrico'!E26 -> 31 | K62: =C62/J62 -> 11.82871 | S62: =D62*$R$8 -> 14311.096
B63: ='Consumo Eléctrico'!B27 -> 45139 | C63: 389.7726 | D63: =C63*$O$8 -> 54.76305 | F63: =B67 -> 45261 | G63: =D67 -> 15.670948 | J63: ='Consumo Eléctrico'!E27 -> 30 | K63: =C63/J63 -> 12.99242 | S63: =D63*$R$8 -> 15211.958
B64: ='Consumo Eléctrico'!B28 -> 45170 | C64: 167.0352 | D64: =C64*$O$8 -> 23.468446 | J64: ='Consumo Eléctrico'!E28 -> 31 | K64: =C64/J64 -> 5.3882323 | S64: =D64*$R$8 -> 6519.0127
B65: ='Consumo Eléctrico'!B29 -> 45200 | C65: 165.54 | D65: =C65*$O$8 -> 23.25837 | F65: Media mensual | G65: =AVERAGE(G40:G63) -> 39.333808 | J65: ='Consumo Eléctrico'!E29 -> 30 | K65: =C65/J65 -> 5.518 | S65: =D65*$R$8 -> 6460.6583
B66: ='Consumo Eléctrico'!B30 -> 45231 | C66: 318.4134 | D66: =C66*$O$8 -> 44.737083 | F66: Media anual | G66: =AVERAGE(D38,D69) -> 472.0057 | J66: ='Consumo Eléctrico'!E30 -> 30 | K66: =C66/J66 -> 10.61378 | S66: =D66*$R$8 -> 12426.967
B67: ='Consumo Eléctrico'!B31 -> 45261 | C67: 111.537 | D67: =C67*$O$8 -> 15.670948 | J67: ='Consumo Eléctrico'!E31 -> 31 | K67: =C67/J67 -> 3.5979677 | S67: =D67*$R$8 -> 4353.0413
B68: Media Consumo mes | C68: =AVERAGE(C56:C67) -> 272.81274 | D68: =AVERAGE(D56:D67) -> 38.33019 | J68: =AVERAGE(J56:J67) -> 30.416667 | K68: =AVERAGE(K56:K67) -> 8.9840402 | S68: =AVERAGE(S56:S67) -> 10647.275
B69: Total (anual) 2023 | C69: =SUM(C56:C67) -> 3273.7529 | D69: =SUM(D56:D67) -> 459.96228 | S69: =SUM(S56:S67) -> 127767.3
S77: =S39+S69 -> 262225.39

Sheet Indicadores Energéticos
B2: Indicadores Energéticos de empresa 2022 | N2: Indicadores Energéticos de empresa 2023
A4: Mes | B4: Consumo Energía Eléctrica [kWh/mes] | C4: Consumo Térmico [Gal Kerosene] | D4: Emulsión Asfáltica [m³/mes] | E4: Mezcla Asfáltica [m³] /mes | F4: kWh/m³ Emulsión | G4: kWh/m³ Mezcla | H4: kg CO₂/m³ Emulsión | I4: kg CO₂/m³ Mezcla | J4: Kerosene gal /m³ Emulsión | M4: Mes | N4: Consumo Energía Eléctrica [kWh] | O4: Consumo Térmico [Gal Kerosene] | P4: Emulsión Asfáltica [m³] | Q4: Mezcla Asfáltica [m³] | R4: kWh/m³ Emulsión | S4: kWh/m³ Mezcla | T4: kg CO₂/m³ Emulsión | U4: kg CO₂/m³ Mezcla | V4: Kerosene gal /m³ Emulsión | Z4: kWh/m³ Emulsión | AA4: kWh/m³ Mezcla | AB4: Kerosene gal /m³ Emulsión
A8: ='Consumo Eléctrico'!B8 -> 44562 | B8: ='Consumo Eléctrico'!I8 -> 8674.83 | C8: ='Consumo Térmico de la empresa'!C25 -> 176.702 | D8: 72.34458 | E8: 114.1602 | F8: =B8/D8 -> 119.90988 | G8: =B8/E8 -> 75.988217 | H8: =F8*$H$25 -> 28.586516 | I8: =G8*$H$25 -> 18.115591 | J8: =C8/D8 -> 2.442505 | M8: ='Consumo Eléctrico'!B20 -> 44927 | N8: ='Consumo Eléctrico'!I20 -> 8475 | O8: ='Consumo Térmico de la empresa'!C56 -> 165.03 | P8: 81.25 | Q8: 140.2 | R8: =N8/P8 -> 104.30769 | S8: =N8/Q8 -> 60.449358 | T8: =R8*$T$25 -> 24.866954 | U8: =S8*$T$25 -> 14.411127 | V8: =O8/P8 -> 2.0311385 | Z8: =AVERAGE(F21,R21) -> 975.30607 | AA8: =AVERAGE(G20,S20) -> 59.98047 | AB8: =AVERAGE(J20,V20) -> 2.0551352
A9: ='Consumo Eléctrico'!B9 -> 44593 | B9: ='Consumo Eléctrico'!I9 -> 9893.12 | C9: ='Consumo Térmico de la empresa'!C26 -> 229.2886 | D9: 99.4455 | E9: 194.39574 | F9: =B9/D9 -> 99.482832 | G9: =B9/E9 -> 50.89165 | H9: =F9*$H$25 -> 23.716707 | I9: =G9*$H$25 -> 12.132569 | J9: =C9/D9 -> 2.3056709 | M9: ='Consumo Eléctrico'!B21 -> 44958 | N9: ='Consumo Eléctrico'!I21 -> 8802.64 | O9: ='Consumo Térmico de la empresa'!C57 -> 224.9624 | P9: 104.56 | Q9: 225.66 | R9: =N9/P9 -> 84.187452 | S9: =N9/Q9 -> 39.00842 | T9: =R9*$T$25 -> 20.070289 | U9: =S9*$T$25 -> 9.2996073 | V9: =O9/P9 -> 2.1515149
A10: ='Consumo Eléctrico'!B10 -> 44621 | B10: ='Consumo Eléctrico'!I10 -> 9689.25 | C10: ='Consumo Térmico de la empresa'!C27 -> 239.4646 | D10: 104.69536 | E10: 57.60832 | F10: =B10/D10 -> 92.547081 | G10: =B10/E10 -> 168.19185 | H10: =F10*$H$25 -> 22.063224 | I10: =G10*$H$25 -> 40.096937 | J10: =C10/D10 -> 2.2872513 | M10: ='Consumo Eléctrico'!B22 -> 44986 | N10: ='Consumo Eléctrico'!I22 -> 9633.16 | O10: ='Consumo Térmico de la empresa'!C58 -> 234.9464 | P10: 117.89 | Q10: 54.56 | R10: =N10/P10 -> 81.713122 | S10: =N10/Q10 -> 176.56085 | T10: =R10*$T$25 -> 19.480408 | U10: =S10*$T$25 -> 42.092107 | V10: =O10/P10 -> 1.992929
A11: ='Consumo Eléctrico'!B11 -> 44652 | B11: ='Consumo Eléctrico'!I11 -> 9823.56 | C11: ='Consumo Térmico de la empresa'!C28 -> 422.1238 | D11: 198.85866 | E11: 80.99014 | F11: =B11/D11 -> 49.399709 | G11: =B11/E11 -> 121.29328 | H11: =F11*$H$25 -> 11.776891 | I11: =G11*$H$25 -> 28.916319 | J11: =C11/D11 -> 2.1227328 | M11: ='Consumo Eléctrico'!B23 -> 45017 | N11: ='Consumo Eléctrico'!I23 -> 9796.5 | O11: ='Consumo Térmico de la empresa'!C59 -> 414.1592 | P11: 214.56 | Q11: 91.56 | R11: =N11/P11 -> 45.658557 | S11: =N11/Q11 -> 106.99541 | T11: =R11*$T$25 -> 10.885 | U11: =S11*$T$25 -> 25.507706 | V11: =O11/P11 -> 1.9302722 | AB11: GJ /m³ Emulsión
A12: ='Consumo Eléctrico'!B12 -> 44682 | B12: ='Consumo Eléctrico'!I12 -> 10503.89 | C12: ='Consumo Térmico de la empresa'!C29 -> 396.8852 | D12: 265.41 | E12: 383.84346 | F12: =B12/D12 -> 39.57609 | G12: =B12/E12 -> 27.365036 | H12: =F12*$H$25 -> 9.4349398 | I12: =G12*$H$25 -> 6.5238245 | J12: =C12/D12 -> 1.4953664 | M12: ='Consumo Eléctrico'!B24 -> 45047 | N12: ='Consumo Eléctrico'!I24 -> 11503.69 | O12: ='Consumo Térmico de la empresa'!C60 -> 363.1874 | P12: 314.16 | Q12: 456.25 | R12: =N12/P12 -> 36.617297 | S12: =N12/Q12 -> 25.213567 | T12: =R12*$T$25 -> 8.7295636 | U12: =S12*$T$25 -> 6.0109144 | V12: =O12/P12 -> 1.1560587
A13: ='Consumo Eléctrico'!B13 -> 44713 | B13: ='Consumo Eléctrico'!I13 -> 9931.33 | C13: ='Consumo Térmico de la empresa'!C30 -> 401.7506 | D13: 188.35894 | E13: 102.21596 | F13: =B13/D13 -> 52.725557 | G13: =B13/E13 -> 97.160267 | H13: =F13*$H$25 -> 12.569773 | I13: =G13*$H$25 -> 23.163008 | J13: =C13/D13 -> 2.132899 | M13: ='Consumo Eléctrico'!B25 -> 45078 | N13: ='Consumo Eléctrico'!I25 -> 9636.34 | O13: ='Consumo Térmico de la empresa'!C61 -> 352.4793 | P13: 199.52 | Q13: 101.15 | R13: =N13/P13 -> 48.297614 | S13: =N13/Q13 -> 95.26782 | T13: =R13*$T$25 -> 11.514151 | U13: =S13*$T$25 -> 22.711848 | V13: =O13/P13 -> 1.7666364
A14: ='Consumo Eléctrico'!B14 -> 44743 | B14: ='Consumo Eléctrico'!I14 -> 9668.73 | C14: ='Consumo Térmico de la empresa'!C31 -> 381.07 | D14: 177.69752 | E14: 170.0006 | F14: =B14/D14 -> 54.41117 | G14: =B14/E14 -> 56.874682 | H14: =F14*$H$25 -> 12.971623 | I14: =G14*$H$25 -> 13.558924 | J14: =C14/D14 -> 2.1444869 | M14: ='Consumo Eléctrico'!B26 -> 45108 | N14: ='Consumo Eléctrico'!I26 -> 10051.65 | O14: ='Consumo Térmico de la empresa'!C62 -> 366.69 | P14: 212.12 | Q14: 160.52 | R14: =N14/P14 -> 47.386621 | S14: =N14/Q14 -> 62.6193 | T14: =R14*$T$25 -> 11.29697 | U14: =S14*$T$25 -> 14.928441 | V14: =O14/P14 -> 1.7286913
A15: ='Consumo Eléctrico'!B15 -> 44774 | B15: ='Consumo Eléctrico'!I15 -> 9498.13 | C15: ='Consumo Térmico de la empresa'!C32 -> 405.0578 | D15: 190.06218 | E15: 619.7422 | F15: =B15/D15 -> 49.973803 | G15: =B15/E15 -> 15.325937 | H15: =F15*$H$25 -> 11.913755 | I15: =G15*$H$25 -> 3.6537034 | J15: =C15/D15 -> 2.1311857 | M15: ='Consumo Eléctrico'!B27 -> 45139 | N15: ='Consumo Eléctrico'!I27 -> 8620.61 | O15: ='Consumo Térmico de la empresa'!C63 -> 389.7726 | P15: 112.32 | Q15: 685.25 | R15: =N15/P15 -> 76.750445 | S15: =N15/Q15 -> 12.580241 | T15: =R15*$T$25 -> 18.297306 | U15: =S15*$T$25 -> 2.9991294 | V15: =O15/P15 -> 3.4701976 | AB15: =AB8*'Consumo Térmico de la empresa'!O8 -> 0.28874649
A16: ='Consumo Eléctrico'!B16 -> 44805 | B16: ='Consumo Eléctrico'!I16 -> 9284.99 | C16: ='Consumo Térmico de la empresa'!C33 -> 173.5856 | D16: 118.91 | E16: 663.0778 | F16: =B16/D16 -> 78.084181 | G16: =B16/E16 -> 14.002867 | H16: =F16*$H$25 -> 18.615269 | I16: =G16*$H$25 -> 3.3382834 | J16: =C16/D16 -> 1.4598066 | M16: ='Consumo Eléctrico'!B28 -> 45170 | N16: ='Consumo Eléctrico'!I28 -> 9013.66 | O16: ='Consumo Térmico de la empresa'!C64 -> 167.0352 | P16: 81.5 | Q16: 701.25 | R16: =N16/P16 -> 110.59706 | S16: =N16/Q16 -> 12.853704 | T16: =R16*$T$25 -> 26.366338 | U16: =S16*$T$25 -> 3.0643231 | V16: =O16/P16 -> 2.0495117
A17: ='Consumo Eléctrico'!B17 -> 44835 | B17: ='Consumo Eléctrico'!I17 -> 9045.56 | C17: 172.45 | D17: 112 | E17: 291.34028 | F17: =B17/D17 -> 80.763929 | G17: =B17/E17 -> 31.048093 | H17: =F17*$H$25 -> 19.254121 | I17: =G17*$H$25 -> 7.4018653 | J17: =C17/D17 -> 1.5397321 | M17: ='Consumo Eléctrico'!B29 -> 45200 | N17: ='Consumo Eléctrico'!I29 -> 9003.9 | O17: 165.54 | P17: 70.14 | Q17: 301.56 | R17: =N17/P17 -> 128.3704 | S17: =N17/Q17 -> 29.85774 | T17: =R17*$T$25 -> 30.603504 | U17: =S17*$T$25 -> 7.1180852 | V17: =O17/P17 -> 2.3601369
A18: ='Consumo Eléctrico'!B18 -> 44866 | B18: ='Consumo Eléctrico'!I18 -> 9676.81 | C18: ='Consumo Térmico de la empresa'!C35 -> 330.9002 | D18: 151.82552 | E18: 658.03276 | F18: =B18/D18 -> 63.736386 | G18: =B18/E18 -> 14.705666 | H18: =F18*$H$25 -> 15.194755 | I18: =G18*$H$25 -> 3.5058308 | J18: =C18/D18 -> 2.1794768 | M18: ='Consumo Eléctrico'!B30 -> 45231 | N18: ='Consumo Eléctrico'!I30 -> 10060.05 | O18: ='Consumo Térmico de la empresa'!C66 -> 318.4134 | P18: 181.45 | Q18: 764.23 | R18: =N18/P18 -> 55.442546 | S18: =N18/Q18 -> 13.163642 | T18: =R18*$T$25 -> 13.217503 | U18: =S18*$T$25 -> 3.1382122 | V18: =O18/P18 -> 1.7548272
A19: ='Consumo Eléctrico'!B19 -> 44896 | B19: ='Consumo Eléctrico'!I19 -> 8577.93 | C19: ='Consumo Térmico de la empresa'!C36 -> 115.911 | D19: 41.00712 | E19: 118.65546 | F19: =B19/D19 -> 209.18148 | G19: =B19/E19 -> 72.292754 | H19: =F19*$H$25 -> 49.868865 | I19: =G19*$H$25 -> 17.234593 | J19: =C19/D19 -> 2.8266067 | M19: ='Consumo Eléctrico'!B31 -> 45261 | N19: ='Consumo Eléctrico'!I31 -> 8468.25 | O19: ='Consumo Térmico de la empresa'!C67 -> 111.537 | P19: 59.85 | Q19: 141.56 | R19: =N19/P19 -> 141.49123 | S19: =N19/Q19 -> 59.820924 | T19: =R19*$T$25 -> 33.731509 | U19: =S19*$T$25 -> 14.261308 | V19: =O19/P19 -> 1.863609
A20: Media | B20: =AVERAGE(B8:B19) -> 9522.3442 | C20: =AVERAGE(C8:C19) -> 287.09912 | D20: =AVERAGE(D8:D19) -> 143.38462 | E20: =AVERAGE(E8:E19) -> 287.83858 | F20: =AVERAGE(F8:F19) -> 82.482675 | G20: =AVERAGE(G8:G19) -> 62.095025 | H20: =AVERAGE(H8:H19) -> 19.66387 | I20: =AVERAGE(I8:I19) -> 14.803454 | J20: =AVERAGE(J8:J19) -> 2.0889767 | M20: Media | N20: =AVERAGE(N8:N19) -> 9422.1208 | O20: =AVERAGE(O8:O19) -> 272.81274 | P20: =AVERAGE(P8:P19) -> 145.77667 | Q20: =AVERAGE(Q8:Q19) -> 318.64583 | R20: =AVERAGE(R8:R19) -> 80.068336 | S20: =AVERAGE(S8:S19) -> 57.865915 | T20: =AVERAGE(T8:T19) -> 19.088291 | U20: =AVERAGE(U8:U19) -> 13.795234 | V20: =AVERAGE(V8:V19) -> 2.0212936
A21: Total | B21: =SUM(B8:B19) -> 114268.13 | C21: =SUM(C8:C19) -> 3445.1894 | D21: =SUM(D8:D19) -> 1720.6154 | E21: =SUM(E8:E19) -> 3454.0629 | F21: =SUM(F8:F19) -> 989.7921 | G21: =SUM(G8:G19) -> 745.1403 | H21: =SUM(H8:H19) -> 235.96644 | I21: =SUM(I8:I19) -> 177.64145 | J21: =SUM(J8:J19) -> 25.06772 | M21: Total | N21: =SUM(N8:N19) -> 113065.45 | O21: =SUM(O8:O19) -> 3273.7529 | P21: =SUM(P8:P19) -> 1749.32 | Q21: =SUM(Q8:Q19) -> 3823.75 | R21: =SUM(R8:R19) -> 960.82003 | S21: =SUM(S8:S19) -> 694.39098 | T21: =SUM(T8:T19) -> 229.0595 | U21: =SUM(U8:U19) -> 165.54281 | V21: =SUM(V8:V19) -> 24.255523
R23: =AVERAGE(F20,R20) -> 81.275505
H24: factor | I24: directo pgf | T24: factor | U24: directo pgf
H25: 0.2384 | T25: 0.2384
O29: Mes | P29: =B4 -> Consumo Energía Eléctrica [kWh/mes] | Q29: Consumo Predicho línea base | R29: Diferencia | S29: Concepto
O30: 1 | P30: =B8 -> 8674.83 | Q30: =-87.831*O30+10325 -> 10237.169 | R30: =P30-Q30 -> -1562.339 | S30: =IF(R30>0,"Sobre Consumo","-") -> - | AB30: Análisis previo Linea Base de Consumo Energético - PGF
O31: 2 | P31: =B9 -> 9893.12 | Q31: =-87.831*O31+10325 -> 10149.338 | R31: =P31-Q31 -> -256.218 | S31: =IF(R31>0,"Sobre Consumo","-") -> -
O32: 3 | P32: =B10 -> 9689.25 | Q32: =-87.831*O32+10325 -> 10061.507 | R32: =P32-Q32 -> -372.257 | S32: =IF(R32>0,"Sobre Consumo","-") -> -
O33: 4 | P33: =B11 -> 9823.56 | Q33: =-87.831*O33+10325 -> 9973.676 | R33: =P33-Q33 -> -150.116 | S33: =IF(R33>0,"Sobre Consumo","-") -> -
O34: 5 | P34: =B12 -> 10503.89 | Q34: =-87.831*O34+10325 -> 9885.845 | R34: =P34-Q34 -> 618.045 | S34: =IF(R34>0,"Sobre Consumo","-") -> Sobre Consumo
O35: 6 | P35: =B13 -> 9931.33 | Q35: =-87.831*O35+10325 -> 9798.014 | R35: =P35-Q35 -> 133.316 | S35: =IF(R35>0,"Sobre Consumo","-") -> Sobre Consumo
O36: 7 | P36: =B14 -> 9668.73 | Q36: =-87.831*O36+10325 -> 9710.183 | R36: =P36-Q36 -> -41.453 | S36: =IF(R36>0,"Sobre Consumo","-") -> -
O37: 8 | P37: =B15 -> 9498.13 | Q37: =-87.831*O37+10325 -> 9622.352 | R37: =P37-Q37 -> -124.222 | S37: =IF(R37>0,"Sobre Consumo","-") -> -
O38: 9 | P38: =B16 -> 9284.99 | Q38: =-87.831*O38+10325 -> 9534.521 | R38: =P38-Q38 -> -249.531 | S38: =IF(R38>0,"Sobre Consumo","-") -> -
O39: 10 | P39: =B17 -> 9045.56 | Q39: =-87.831*O39+10325 -> 9446.69 | R39: =P39-Q39 -> -401.13 | S39: =IF(R39>0,"Sobre Consumo","-") -> -
O40: 11 | P40: =B18 -> 9676.81 | Q40: =-87.831*O40+10325 -> 9358.859 | R40: =P40-Q40 -> 317.951 | S40: =IF(R40>0,"Sobre Consumo","-") -> Sobre Consumo
O41: 12 | P41: =B19 -> 8577.93 | Q41: =-87.831*O41+10325 -> 9271.028 | R41: =P41-Q41 -> -693.098 | S41: =IF(R41>0,"Sobre Consumo","-") -> -
J47: [kWh] | K47: [m³] | X47: [kWh] | Y47: [m³]
I48: =A8 -> 44562 | J48: =B8/100 -> 86.7483 | K48: =D8 -> 72.34458 | W48: =M8 -> 44927 | X48: =N8/100 -> 84.75 | Y48: =P8 -> 81.25
B49: Comportamiento de indicador de desempeño energético para emulsión asfáltica | I49: =A9 -> 44593 | J49: =B9/100 -> 98.9312 | K49: =D9 -> 99.4455 | W49: =M9 -> 44958 | X49: =N9/100 -> 88.0264 | Y49: =P9 -> 104.56
I50: =A10 -> 44621 | J50: =B10/100 -> 96.8925 | K50: =D10 -> 104.69536 | W50: =M10 -> 44986 | X50: =N10/100 -> 96.3316 | Y50: =P10 -> 117.89
I51: =A11 -> 44652 | J51: =B11/100 -> 98.2356 | K51: =D11 -> 198.85866 | W51: =M11 -> 45017 | X51: =N11/100 -> 97.965 | Y51: =P11 -> 214.56
I52: =A12 -> 44682 | J52: =B12/100 -> 105.0389 | K52: =D12 -> 265.41 | W52: =M12 -> 45047 | X52: =N12/100 -> 115.0369 | Y52: =P12 -> 314.16
I53: =A13 -> 44713 | J53: =B13/100 -> 99.3133 | K53: =D13 -> 188.35894 | W53: =M13 -> 45078 | X53: =N13/100 -> 96.3634 | Y53: =P13 -> 199.52
I54: =A14 -> 44743 | J54: =B14/100 -> 96.6873 | K54: =D14 -> 177.69752 | W54: =M14 -> 45108 | X54: =N14/100 -> 100.5165 | Y54: =P14 -> 212.12
I55: =A15 -> 44774 | J55: =B15/100 -> 94.9813 | K55: =D15 -> 190.06218 | W55: =M15 -> 45139 | X55: =N15/100 -> 86.2061 | Y55: =P15 -> 112.32
I56: =A16 -> 44805 | J56: =B16/100 -> 92.8499 | K56: =D16 -> 118.91 | W56: =M16 -> 45170 | X56: =N16/100 -> 90.1366 | Y56: =P16 -> 81.5
I57: =A17 -> 44835 | J57: =B17/100 -> 90.4556 | K57: =D17 -> 112 | W57: =M17 -> 45200 | X57: =N17/100 -> 90.039 | Y57: =P17 -> 70.14
I58: =A18 -> 44866 | J58: =B18/100 -> 96.7681 | K58: =D18 -> 151.82552 | W58: =M18 -> 45231 | X58: =N18/100 -> 100.6005 | Y58: =P18 -> 181.45
I59: =A19 -> 44896 | J59: =B19/100 -> 85.7793 | K59: =D19 -> 41.00712 | W59: =M19 -> 45261 | X59: =N19/100 -> 84.6825 | Y59: =P19 -> 59.85
B67: Comportamiento de indicador de desempeño energético para mezcla asfáltica
J78: [kWh] | K78: kWh/m³ Emulsión
I79: =I48 -> 44562 | J79: =J48 -> 86.7483 | K79: =F8 -> 119.90988
I80: =I49 -> 44593 | J80: =J49 -> 98.9312 | K80: =F9 -> 99.482832
I81: =I50 -> 44621 | J81: =J50 -> 96.8925 | K81: =F10 -> 92.547081
I82: =I51 -> 44652 | J82: =J51 -> 98.2356 | K82: =F11 -> 49.399709
I83: =I52 -> 44682 | J83: =J52 -> 105.0389 | K83: =F12 -> 39.57609
B84: Comportamiento de indicador de desempeño energético para emulsiones asfálticas | I84: =I53 -> 44713 | J84: =J53 -> 99.3133 | K84: =F13 -> 52.725557
I85: =I54 -> 44743 | J85: =J54 -> 96.6873 | K85: =F14 -> 54.41117
I86: =I55 -> 44774 | J86: =J55 -> 94.9813 | K86: =F15 -> 49.973803
I87: =I56 -> 44805 | J87: =J56 -> 92.8499 | K87: =F16 -> 78.084181
I88: =I57 -> 44835 | J88: =J57 -> 90.4556 | K88: =F17 -> 80.763929
I89: =I58 -> 44866 | J89: =J58 -> 96.7681 | K89: =F18 -> 63.736386
I90: =I59 -> 44896 | J90: =J59 -> 85.7793 | K90: =F19 -> 209.18148
B103: Comportamiento de indicador de desempeño energético para mezcla asfáltica
B121: Comportamiento de indicador de desempeño energético para emulsión asfáltica
B140: Indicadores energéticos establecidos para la empresa
C142: Energéticos
B143: 2022 | C143: =F20 -> 82.482675 | D143: [kWh/m³] | E143: Media de producción de mezcla asfáltica | K143: =AVERAGE(C143,C147) -> 81.275505
C144: =G20 -> 62.095025 | D144: [kWh/m³] | E144: Media de producción de emulsión asfáltica | K144: =AVERAGE(C144,C148) -> 59.98047
C145: =J20 -> 2.0889767 | D145: [gal /m³] | E145: Media del consumo de galon de kerosene por producción de emulsión
B147: 2023 | C147: =R20 -> 80.068336 | D147: [kWh/m³] | E147: Media de producción de mezcla asfáltica
C148: =S20 -> 57.865915 | D148: [kWh/m³] | E148: Media de producción de emulsión asfáltica
C149: =V20 -> 2.0212936 | D149: [gal /m³] | E149: Media del consumo de galon de kerosene por producción de emulsión
C152: Ambientales
B153: 2022 | C153: =H20 -> 19.66387 | D153: [kg CO₂/m³] | E153: Media de producción de mezcla asfáltica
C154: =I20 -> 14.803454 | D154: [kg CO₂/m³] | E154: Media de producción de emulsión asfáltica
C155: =H25 -> 0.2384 | D155: Ton de CO₂/MWh (factor por emisión de combustible)
B157: 2023 | C157: =T20 -> 19.088291 | D157: [kg CO₂/m³] | E157: Media de producción de mezcla asfáltica
C158: =U20 -> 13.795234 | D158: [kg CO₂/m³] | E158: Media de producción de emulsión asfáltica
C159: =T25 -> 0.2384 | D159: Ton de CO₂/MWh (factor por emisión de combustible)
C162: https://www.coordinador.cl/novedades/sistema-electrico-redujo-21-sus-emisiones-en-2023-y-se-espera-que-siga-creciendo-participacion-de-energia-renovable-variable/
C164: https://4echile.cl/wp-content/uploads/2023/01/Gui%CC%81a-Complementaria-Herramienta-Costo-de-Abatimiento-GIZ.pdf
C166: http://energiaabierta.cl/visualizaciones/factor-de-emision-sic-sing/

Sheet Emisiones de GEI
D4: Ton de CO₂/MWh (factor por emisión de combustible) | L4: Ton de CO₂/MWh (factor por emisión de combustible)
Q5: Factor de emisiones GEI del Sistema Eléctrico Nacional
D6: factor | F6: emisión [Kg CO₂] | L6: factor | N6: emisión [Kg CO₂] | Q6: https://energia.gob.cl/indicadores-ambientales-factor-de-emisiones-gei-del-sistema-electrico-nacional
C7: =C35 -> 8674.83 | D7: =D52 -> 0.2384 | F7: =C7*D7 -> 2068.0795 | K7: =K35 -> 8475 | L7: =L52 -> 0.2384 | N7: =K7*L7 -> 2020.44
F8: emisión [Ton CO₂] | N8: emisión [Ton CO₂]
F9: =F7/1000 -> 2.0680795 | N9: =N7/1000 -> 2.02044 | Q9: Factor de conversión de GJ a kW
Q10: https://es.converterin.com/economia-de-combustible/gigajoule-to-us-galones-de-kerosene.html
D11: factor | F11: emisión [Ton CO₂] | L11: factor | N11: emisión [Ton CO₂] | Q11: =277.77777778 -> 277.77778
C12: =C35 -> 8674.83 | D12: =D52 -> 0.2384 | F12: =C12*D12/1000 -> 2.0680795 | K12: =K35 -> 8475 | L12: =L52 -> 0.2384 | N12: =K12*L12/1000 -> 2.02044
D15: factor | F15: emisión [Kg CO₂] | L15: factor | N15: emisión [Kg CO₂]
C16: =C35 -> 8674.83 | D16: =D52 -> 0.2384 | F16: =C16*D16 -> 2068.0795 | K16: =K35 -> 8475 | L16: =L52 -> 0.2384 | N16: =K16*L16 -> 2020.44
F17: emisión [Ton CO₂] | N17: emisión [Ton CO₂]
F18: =F16/1000 -> 2.0680795 | N18: =N16/1000 -> 2.02044
C28: Emisiones totales de la empresa 2022 | K28: Emisiones totales de la empresa 2023
D30: Calcular | G30: Calcular | L30: Calcular | O30: Calcular
B31: Mes | C31: Consumo Energía Eléctrica [kWh] | D31: Emisiones totales por consumo eléctrico [Ton CO₂] | F31: Consumo Energía Térmica [GJ] | G31: Emisiones totales por consumo térmico [Ton CO₂] | J31: Mes | K31: Consumo Energía Eléctrica [kWh] | L31: Emisiones totales por consumo eléctrico [Ton CO₂] | N31: Consumo Energía Térmica [GJ] | O31: Emisiones totales por consumo térmico [Ton CO₂]
B35: ='Consumo Eléctrico'!B8 -> 44562 | C35: ='Consumo Eléctrico'!I8 -> 8674.83 | D35: =C35*$D$52/1000 -> 2.0680795 | F35: ='Consumo Térmico de la empresa'!D25 -> 24.826631 | G35: =F35*$Q$11*$G$53/1000 -> 1.7850348 | J35: ='Consumo Eléctrico'!B20 -> 44927 | K35: ='Consumo Eléctrico'!I20 -> 8475 | L35: =K35*$L$52/1000 -> 2.02044 | N35: ='Consumo Térmico de la empresa'!D56 -> 23.186715 | O35: =N35*$Q$11*$G$53/1000 -> 1.6671248
B36: ='Consumo Eléctrico'!B9 -> 44593 | C36: ='Consumo Eléctrico'!I9 -> 9893.12 | D36: =C36*$D$52/1000 -> 2.3585198 | F36: ='Consumo Térmico de la empresa'!D26 -> 32.215048 | G36: =F36*$Q$11*$G$53/1000 -> 2.316262 | J36: ='Consumo Eléctrico'!B21 -> 44958 | K36: ='Consumo Eléctrico'!I21 -> 8802.64 | L36: =K36*$L$52/1000 -> 2.0985494 | N36: ='Consumo Térmico de la empresa'!D57 -> 31.607217 | O36: =N36*$Q$11*$G$53/1000 -> 2.2725589
B37: ='Consumo Eléctrico'!B10 -> 44621 | C37: ='Consumo Eléctrico'!I10 -> 9689.25 | D37: =C37*$D$52/1000 -> 2.3099172 | F37: ='Consumo Térmico de la empresa'!D27 -> 33.644776 | G37: =F37*$Q$11*$G$53/1000 -> 2.4190594 | J37: ='Consumo Eléctrico'!B22 -> 44986 | K37: ='Consumo Eléctrico'!I22 -> 9633.16 | L37: =K37*$L$52/1000 -> 2.2965453 | N37: ='Consumo Térmico de la empresa'!D58 -> 33.009969 | O37: =N37*$Q$11*$G$53/1000 -> 2.3734168
B38: ='Consumo Eléctrico'!B11 -> 44652 | C38: ='Consumo Eléctrico'!I11 -> 9823.56 | D38: =C38*$D$52/1000 -> 2.3419367 | F38: ='Consumo Térmico de la empresa'!D28 -> 59.308394 | G38: =F38*$Q$11*$G$53/1000 -> 4.2642735 | J38: ='Consumo Eléctrico'!B23 -> 45017 | K38: ='Consumo Eléctrico'!I23 -> 9796.5 | L38: =K38*$L$52/1000 -> 2.3354856 | N38: ='Consumo Térmico de la empresa'!D59 -> 58.189368 | O38: =N38*$Q$11*$G$53/1000 -> 4.1838155
B39: ='Consumo Eléctrico'!B12 -> 44682 | C39: ='Consumo Eléctrico'!I12 -> 10503.89 | D39: =C39*$D$52/1000 -> 2.5041274 | F39: ='Consumo Térmico de la empresa'!D29 -> 55.762371 | G39: =F39*$Q$11*$G$53/1000 -> 4.0093144 | J39: ='Consumo Eléctrico'!B24 -> 45047 | K39: ='Consumo Eléctrico'!I24 -> 11503.69 | L39: =K39*$L$52/1000 -> 2.7424797 | N39: ='Consumo Térmico de la empresa'!D60 -> 51.02783 | O39: =N39*$Q$11*$G$53/1000 -> 3.668901
B40: ='Consumo Eléctrico'!B13 -> 44713 | C40: ='Consumo Eléctrico'!I13 -> 9931.33 | D40: =C40*$D$52/1000 -> 2.3676291 | F40: ='Consumo Térmico de la empresa'!D30 -> 56.445959 | G40: =F40*$Q$11*$G$53/1000 -> 4.0584645 | J40: ='Consumo Eléctrico'!B25 -> 45078 | K40: ='Consumo Eléctrico'!I25 -> 9636.34 | L40: =K40*$L$52/1000 -> 2.2973035 | N40: ='Consumo Térmico de la empresa'!D61 -> 49.523342 | O40: =N40*$Q$11*$G$53/1000 -> 3.5607283
B41: ='Consumo Eléctrico'!B14 -> 44743 | C41: ='Consumo Eléctrico'!I14 -> 9668.73 | D41: =C41*$D$52/1000 -> 2.3050252 | F41: ='Consumo Térmico de la empresa'!D31 -> 53.540335 | G41: =F41*$Q$11*$G$53/1000 -> 3.8495501 | J41: ='Consumo Eléctrico'!B26 -> 45108 | K41: ='Consumo Eléctrico'!I26 -> 10051.65 | L41: =K41*$L$52/1000 -> 2.3963134 | N41: ='Consumo Térmico de la empresa'!D62 -> 51.519945 | O41: =N41*$Q$11*$G$53/1000 -> 3.704284
B42: ='Consumo Eléctrico'!B15 -> 44774 | C42: ='Consumo Eléctrico'!I15 -> 9498.13 | D42: =C42*$D$52/1000 -> 2.2643542 | F42: ='Consumo Térmico de la empresa'!D32 -> 56.910621 | G42: =F42*$Q$11*$G$53/1000 -> 4.0918736 | J42: ='Consumo Eléctrico'!B27 -> 45139 | K42: ='Consumo Eléctrico'!I27 -> 8620.61 | L42: =K42*$L$52/1000 -> 2.0551534 | N42: ='Consumo Térmico de la empresa'!D63 -> 54.76305 | O42: =N42*$Q$11*$G$53/1000 -> 3.9374633
B43: ='Consumo Eléctrico'!B16 -> 44805 | C43: ='Consumo Eléctrico'!I16 -> 9284.99 | D43: =C43*$D$52/1000 -> 2.2135416 | F43: ='Consumo Térmico de la empresa'!D33 -> 24.388777 | G43: =F43*$Q$11*$G$53/1000 -> 1.7535531 | J43: ='Consumo Eléctrico'!B28 -> 45170 | K43: ='Consumo Eléctrico'!I28 -> 9013.66 | L43: =K43*$L$52/1000 -> 2.1488565 | N43: ='Consumo Térmico de la empresa'!D64 -> 23.468446 | O43: =N43*$Q$11*$G$53/1000 -> 1.6873812
B44: ='Consumo Eléctrico'!B17 -> 44835 | C44: ='Consumo Eléctrico'!I17 -> 9045.56 | D44: =C44*$D$52/1000 -> 2.1564615 | F44: ='Consumo Térmico de la empresa'!D34 -> 24.229225 | G44: =F44*$Q$11*$G$53/1000 -> 1.7420813 | J44: ='Consumo Eléctrico'!B29 -> 45200 | K44: ='Consumo Eléctrico'!I29 -> 9003.9 | L44: =K44*$L$52/1000 -> 2.1465298 | N44: ='Consumo Térmico de la empresa'!D65 -> 23.25837 | O44: =N44*$Q$11*$G$53/1000 -> 1.6722768
B45: ='Consumo Eléctrico'!B18 -> 44866 | C45: ='Consumo Eléctrico'!I18 -> 9676.81 | D45: =C45*$D$52/1000 -> 2.3069515 | F45: ='Consumo Térmico de la empresa'!D35 -> 46.491478 | G45: =F45*$Q$11*$G$53/1000 -> 3.3427373 | J45: ='Consumo Eléctrico'!B30 -> 45231 | K45: ='Consumo Eléctrico'!I30 -> 10060.05 | L45: =K45*$L$52/1000 -> 2.3983159 | N45: ='Consumo Térmico de la empresa'!D66 -> 44.737083 | O45: =N45*$Q$11*$G$53/1000 -> 3.2165962
B46: ='Consumo Eléctrico'!B19 -> 44896 | C46: ='Consumo Eléctrico'!I19 -> 8577.93 | D46: =C46*$D$52/1000 -> 2.0449785 | F46: ='Consumo Térmico de la empresa'!D36 -> 16.285496 | G46: =F46*$Q$11*$G$53/1000 -> 1.1709271 | J46: ='Consumo Eléctrico'!B31 -> 45261 | K46: ='Consumo Eléctrico'!I31 -> 8468.25 | L46: =K46*$L$52/1000 -> 2.0188308 | N46: ='Consumo Térmico de la empresa'!D67 -> 15.670948 | O46: =N46*$Q$11*$G$53/1000 -> 1.1267412
B47: Media | C47: =AVERAGE(C35:C46) -> 9522.3442 | D47: =AVERAGE(D35:D46) -> 2.2701268 | F47: =AVERAGE(F35:F46) -> 40.337426 | G47: =AVERAGE(G35:G46) -> 2.9002609 | J47: Media | K47: =AVERAGE(K35:K46) -> 9422.1208 | L47: =AVERAGE(L35:L46) -> 2.2462336 | N47: =AVERAGE(N35:N46) -> 38.33019 | O47: =AVERAGE(O35:O46) -> 2.7559407
B48: Total | C48: =SUM(C35:C46) -> 114268.13 | D48: =SUM(D35:D46) -> 27.241522 | F48: =SUM(F35:F46) -> 484.04911 | G48: =SUM(G35:G46) -> 34.803131 | J48: Total | K48: =SUM(K35:K46) -> 113065.45 | L48: =SUM(L35:L46) -> 26.954803 | N48: =SUM(N35:N46) -> 459.96228 | O48: =SUM(O35:O46) -> 33.071288
D49: ✓ | G49: ✓
D51: factor | G51: factor | L51: factor | O51: factor
D52: ='Indicadores Energéticos'!H25 -> 0.2384 | L52: ='Indicadores Energéticos'!T25 -> 0.2384
G53: 0.25884 | O53: 0.2584
G54: 0.298 | O54: 0.298
F56: =F48 -> 484.04911 | G56: =F56*$Q$11*$G$53/1000 -> 34.803131
D58: Desde Propuesta de Mejora | F58: ='Propuesta de Mejora'!C529 -> 877.3822 | G58: =F58*$Q$11*G53/1000 -> 63.08378 | H58: ='Propuesta de Mejora'!C532 -> 63.08378
F59: =F58 -> 877.3822 | G59: =F59*$Q$11*$G$53/1000 -> 63.08378
F60: =F59 -> 877.3822 | G60: =F60*$Q$11*$G$53/1000 -> 63.08378

Sheet Cuantificador
C1: Inventario de motores de la empresa | R1: Inventario de motores de la empresa
B3: Área | C3: Descripción | D3: Capacidad instalada [kW] | E3: Hora de uso diario | F3: Factor de carga | G3: [Kwh]/día | H3: [Kwh]/mes | I3: [Kwh]/año | Q3: Área | R3: Descripción | S3: Capacidad instalada [kW] | T3: Hora de uso diario | U3: Factor de carga | V3: [Kwh]/día | W3: [Kwh]/mes | X3: [Kwh]/año
B4: Agua jabonosa y aditivos | C4: Bomba de pozo | D4: 0.7 | E4: 4 | F4: 0.9 | G4: =D4*E4*F4 -> 2.52 | H4: =G4*5 -> 12.6 | I4: =H4*12 -> 151.2 | J4: ✓ | Q4: Agua jabonosa y aditivos | R4: Bomba de pozo | S4: 0.7 | T4: 4 | U4: 0.9 | V4: =S4*T4*U4 -> 2.52 | W4: =V4*5 -> 12.6 | X4: =W4*12 -> 151.2 | Y4: ✓
C5: Bomba mezclador | D5: 5.6 | E5: 4 | F5: 0.9 | G5: =D5*E5*F5 -> 20.16 | H5: =G5*5 -> 100.8 | I5: =H5*12 -> 1209.6 | J5: ✓ | R5: Bomba mezclador | S5: 5.6 | T5: 4 | U5: 0.9 | V5: =S5*T5*U5 -> 20.16 | W5: =V5*5 -> 100.8 | X5: =W5*12 -> 1209.6 | Y5: ✓
C6: Bomba para ácido | D6: 1.5 | E6: 4 | F6: 0.9 | G6: =D6*E6*F6 -> 5.4 | H6: =G6*5 -> 27 | I6: =H6*12 -> 324 | J6: ✓ | R6: Bomba para ácido | S6: 1.5 | T6: 4 | U6: 0.9 | V6: =S6*T6*U6 -> 5.4 | W6: =V6*5 -> 27 | X6: =W6*12 -> 324 | Y6: ✓
C7: Bomba para jabón (estanque de preparación) | D7: 3 | E7: 4 | F7: 0.9 | G7: =D7*E7*F7 -> 10.8 | H7: =G7*5 -> 54 | I7: =H7*12 -> 648 | J7: ✓ | R7: Bomba para jabón (estanque de preparación) | S7: 3 | T7: 4 | U7: 0.9 | V7: =S7*T7*U7 -> 10.8 | W7: =V7*5 -> 54 | X7: =W7*12 -> 648 | Y7: ✓
C8: Bomba de kereosene (calentar agua) | D8: 0.2 | E8: 4 | F8: 0.9 | G8: =D8*E8*F8 -> 0.72 | H8: =G8*5 -> 3.6 | I8: =H8*12 -> 43.2 | J8: ✓ | R8: Bomba de kereosene (calentar agua) | S8: 0.2 | T8: 4 | U8: 0.9 | V8: =S8*T8*U8 -> 0.72 | W8: =V8*5 -> 3.6 | X8: =W8*12 -> 43.2 | Y8: ✓
C9: Bomba de jabón (agua preparada) | D9: 2.2 | E9: 4 | F9: 0.9 | G9: =D9*E9*F9 -> 7.92 | H9: =G9*5 -> 39.6 | I9: =H9*12 -> 475.2 | J9: ✓ | R9: Bomba de jabón (agua preparada) | S9: 2.2 | T9: 4 | U9: 0.9 | V9: =S9*T9*U9 -> 7.92 | W9: =V9*5 -> 39.6 | X9: =W9*12 -> 475.2 | Y9: ✓
C10: Motor rotador emulsión | D10: 8.2 | E10: 4 | F10: 0.9 | G10: =D10*E10*F10 -> 29.52 | H10: =G10*5 -> 147.6 | I10: =H10*12 -> 1771.2 | J10: ✓ | R10: Motor rotador emulsión | S10: 8.2 | T10: 4 | U10: 0.9 | V10: =S10*T10*U10 -> 29.52 | W10: =V10*5 -> 147.6 | X10: =W10*12 -> 1771.2 | Y10: ✓
B11: Emulsión | C11: Bomba de asfalto ex | D11: 3.7 | E11: 4 | F11: 0.9 | G11: =D11*E11*F11 -> 13.32 | H11: =G11*5 -> 66.6 | I11: =H11*12 -> 799.2 | J11: ✓ | Q11: Emulsión | R11: Bomba de asfalfo ex | S11: 3.7 | T11: 4 | U11: 0.9 | V11: =S11*T11*U11 -> 13.32 | W11: =V11*5 -> 66.6 | X11: =W11*12 -> 799.2 | Y11: ✓
C12: Bomba de asfalto in | D12: 11.2 | E12: 4 | F12: 0.9 | G12: =D12*E12*F12 -> 40.32 | H12: =G12*5 -> 201.6 | I12: =H12*12 -> 2419.2 | J12: ✓ | R12: Bomba de asfalto in | S12: 11.2 | T12: 4 | U12: 0.9 | V12: =S12*T12*U12 -> 40.32 | W12: =V12*5 -> 201.6 | X12: =W12*12 -> 2419.2 | Y12: ✓
C13: Motor aceite térmico | D13: 1.3 | E13: 4 | F13: 0.9 | G13: =D13*E13*F13 -> 4.68 | H13: =G13*5 -> 23.4 | I13: =H13*12 -> 280.8 | J13: ✓ | R13: Motor aceite térmico | S13: 1.3 | T13: 4 | U13: 0.9 | V13: =S13*T13*U13 -> 4.68 | W13: =V13*5 -> 23.4 | X13: =W13*12 -> 280.8 | Y13: ✓
B14: Almacenamiento | C14: Bomba de emulsión | D14: 5.6 | E14: 4 | F14: 0.9 | G14: =D14*E14*F14 -> 20.16 | H14: =G14*5 -> 100.8 | I14: =H14*12 -> 1209.6 | J14: ✓ | Q14: Almacenamiento | R14: Bomba de emulsión | S14: 5.6 | T14: 4 | U14: 0.9 | V14: =S14*T14*U14 -> 20.16 | W14: =V14*5 -> 100.8 | X14: =W14*12 -> 1209.6 | Y14: ✓
B15: Nodriza | C15: Motor de mezcladora | D15: 22.4 | E15: 4 | F15: 0.9 | G15: =D15*E15*F15 -> 80.64 | H15: =G15*5 -> 403.2 | I15: =H15*12 -> 4838.4 | J15: ✓ | Q15: Nodriza | R15: Motor de mezcladora | S15: 22.4 | T15: 4 | U15: 0.9 | V15: =S15*T15*U15 -> 80.64 | W15: =V15*5 -> 403.2 | X15: =W15*12 -> 4838.4 | Y15: ✓
C16: Bomba de emulsiones | D16: 7.5 | E16: 4 | F16: 0.9 | G16: =D16*E16*F16 -> 27 | H16: =G16*5 -> 135 | I16: =H16*12 -> 1620 | J16: ✓ | R16: Bomba de emulsiones | S16: 7.5 | T16: 4 | U16: 0.9 | V16: =S16*T16*U16 -> 27 | W16: =V16*5 -> 135 | X16: =W16*12 -> 1620 | Y16: ✓
C17: Motor de reductores 3/8 | D17: 1.5 | E17: 4 | F17: 0.9 | G17: =D17*E17*F17 -> 5.4 | H17: =G17*5 -> 27 | I17: =H17*12 -> 324 | J17: ✓ | R17: Motor de reductores 3/8 | S17: 1.5 | T17: 4 | U17: 0.9 | V17: =S17*T17*U17 -> 5.4 | W17: =V17*5 -> 27 | X17: =W17*12 -> 324 | Y17: ✓
C18: Motor de reductores 3/4 | D18: 1.5 | E18: 4 | F18: 0.9 | G18: =D18*E18*F18 -> 5.4 | H18: =G18*5 -> 27 | I18: =H18*12 -> 324 | J18: ✓ | R18: Motor de reductores 3/4 | S18: 1.5 | T18: 4 | U18: 0.9 | V18: =S18*T18*U18 -> 5.4 | W18: =V18*5 -> 27 | X18: =W18*12 -> 324 | Y18: ✓
C19: Motor reductor de chispa | D19: 1.5 | E19: 4 | F19: 0.9 | G19: =D19*E19*F19 -> 5.4 | H19: =G19*5 -> 27 | I19: =H19*12 -> 324 | J19: ✓ | R19: Motor reductor de chispa | S19: 1.5 | T19: 4 | U19: 0.9 | V19: =S19*T19*U19 -> 5.4 | W19: =V19*5 -> 27 | X19: =W19*12 -> 324 | Y19: ✓
C20: Motor banda transportadora | D20: 1.6 | E20: 4 | F20: 0.9 | G20: =D20*E20*F20 -> 5.76 | H20: =G20*5 -> 28.8 | I20: =H20*12 -> 345.6 | J20: ✓ | R20: Motor banda transportadora | S20: 1.6 | T20: 4 | U20: 0.9 | V20: =S20*T20*U20 -> 5.76 | W20: =V20*5 -> 28.8 | X20: =W20*12 -> 345.6 | Y20: ✓
C21: Bomba de agua | D21: 1.5 | E21: 4 | F21: 0.9 | G21: =D21*E21*F21 -> 5.4 | H21: =G21*5 -> 27 | I21: =H21*12 -> 324 | J21: ✓ | R21: Bomba de agua | S21: 1.5 | T21: 4 | U21: 0.9 | V21: =S21*T21*U21 -> 5.4 | W21: =V21*5 -> 27 | X21: =W21*12 -> 324 | Y21: ✓
C22: Bomba de asfalto | D22: 0.7 | E22: 4 | F22: 0.9 | G22: =D22*E22*F22 -> 2.52 | H22: =G22*5 -> 12.6 | I22: =H22*12 -> 151.2 | J22: ✓ | R22: Bomba de asfalto | S22: 0.7 | T22: 4 | U22: 0.9 | V22: =S22*T22*U22 -> 2.52 | W22: =V22*5 -> 12.6 | X22: =W22*12 -> 151.2 | Y22: ✓
C23: Bomba contra incendio | D23: 3 | E23: 4 | F23: 0.9 | G23: =D23*E23*F23 -> 10.8 | H23: =G23*5 -> 54 | I23: =H23*12 -> 648 | J23: ✓ | R23: Bomba contra incendio | S23: 3 | T23: 4 | U23: 0.9 | V23: =S23*T23*U23 -> 10.8 | W23: =V23*5 -> 54 | X23: =W23*12 -> 648 | Y23: ✓
C24: Total | D24: =SUM(D4:D23) -> 84.4 | G24: =SUM(G4:G23) -> 303.84 | H24: =SUM(H4:H23) -> 1519.2 | I24: =SUM(I4:I23) -> 18230.4 | R24: Total | S24: =SUM(S4:S23) -> 84.4 | V24: =SUM(V4:V23) -> 303.84 | W24: =SUM(W4:W23) -> 1519.2 | X24: =SUM(X4:X23) -> 18230.4
C31: Datos de consumo eléctrico de molino coloidal | R31: Datos de consumo eléctrico de molino coloidal
B33: Área | C33: Descripción | D33: Capacidad instalada [kW] | E33: Hora de uso diario | F33: Factor de carga | G33: [KWh]/día | H33: [KWh]/mes | I33: [KWh]/año | Q33: Área | R33: Descripción | S33: Capacidad instalada [kW] | T33: Hora de uso diario | U33: Factor de carga | V33: [Kwh]/día | W33: [Kwh]/mes | X33: [Kwh]/año
B34: Emulsión | C34: Molino coloidal | D34: 37.29 | E34: 4 | F34: 0.9 | G34: =D34*E34*F34 -> 134.244 | H34: =G34*5 -> 671.22 | I34: =H34*12 -> 8054.64 | Q34: Emulsión | R34: Molino coloidal | S34: 37.29 | T34: 4 | U34: 0.9 | V34: =S34*T34*U34 -> 134.244 | W34: =V34*5 -> 671.22 | X34: =W34*12 -> 8054.64 | Y34: ✓
C37: Inventario de aires acondicionados de la empresa | R37: Inventario de aires acondicionados de la empresa
B39: Área | C39: Tipo | D39: Capacidad [BTU/h] | E39: Potencia [kW] | F39: EER | G39: Horas Semana | H39: Horas año | I39: Consumo anual [kWh/año] | Q39: Área | R39: Tipo | S39: Capacidad [BTU/h] | T39: Potencia [kW] | U39: EER | V39: Horas Semana | W39: Horas año | X39: Consumo anual [kWh/año]
B40: Lab. de Control | C40: Mini Split | D40: 12000 | E40: 1.26 | F40: =D40/E40/1000 -> 9.5238095 | G40: 60 | H40: =G40*52 -> 3120 | I40: =G40*48*E40*0.8*0.81 -> 2351.4624 | Q40: Lab. de Control | R40: Mini Split | S40: 12000 | T40: 1.26 | U40: =S40/T40/1000 -> 9.5238095 | V40: 60 | W40: =V40*52 -> 3120 | X40: =V40*48*T40*0.8*0.81 -> 2351.4624 | Y40: ✓
B41: Lab. de Control | C41: Central | D41: 60000 | E41: 7.5 | F41: =D41/E41/1000 -> 8 | G41: 60 | H41: =G41*52 -> 3120 | I41: =G41*48*E41*0.8*0.81 -> 13996.8 | Q41: Lab. de Control | R41: Central | S41: 60000 | T41: 7.5 | U41: =S41/T41/1000 -> 8 | V41: 60 | W41: =V41*52 -> 3120 | X41: =V41*48*T41*0.8*0.81 -> 13996.8 | Y41: ✓
B42: Lab. de Suelos | C42: Central | D42: 60000 | E42: 7.5 | F42: =D42/E42/1000 -> 8 | G42: 60 | H42: =G42*52 -> 3120 | I42: =G42*48*E42*0.8*0.81 -> 13996.8 | Q42: Lab. de Suelos | R42: Central | S42: 60000 | T42: 7.5 | U42: =S42/T42/1000 -> 8 | V42: 60 | W42: =V42*52 -> 3120 | X42: =V42*48*T42*0.8*0.81 -> 13996.8 | Y42: ✓
B43: Oficinas 1 | C43: Mini Split | D43: 12000 | E43: 1.3 | F43: =D43/E43/1000 -> 9.2307692 | G43: 60 | H43: =G43*52 -> 3120 | I43: =G43*48*E43*0.8*0.81 -> 2426.112 | Q43: Oficinas 1 | R43: Mini Split | S43: 12000 | T43: 1.3 | U43: =S43/T43/1000 -> 9.2307692 | V43: 60 | W43: =V43*52 -> 3120 | X43: =V43*48*T43*0.8*0.81 -> 2426.112 | Y43: ✓
B44: Oficinas 2 | C44: Mini Split | D44: 12000 | E44: 1.3 | F44: =D44/E44/1000 -> 9.2307692 | G44: 60 | H44: =G44*52 -> 3120 | I44: =G44*48*E44*0.8*0.81 -> 2426.112 | Q44: Oficinas 2 | R44: Mini Split | S44: 12000 | T44: 1.3 | U44: =S44/T44/1000 -> 9.2307692 | V44: 60 | W44: =V44*52 -> 3120 | X44: =V44*48*T44*0.8*0.81 -> 2426.112 | Y44: ✓
B45: Oficinas 3 | C45: Mini Split | D45: 12000 | E45: 1.3 | F45: =D45/E45/1000 -> 9.2307692 | G45: 60 | H45: =G45*52 -> 3120 | I45: =G45*48*E45*0.8*0.81 -> 2426.112 | Q45: Oficinas 3 | R45: Mini Split | S45: 12000 | T45: 1.3 | U45: =S45/T45/1000 -> 9.2307692 | V45: 60 | W45: =V45*52 -> 3120 | X45: =V45*48*T45*0.8*0.81 -> 2426.112 | Y45: ✓
B46: Sala de reuniones | C46: Mini Split | D46: 12000 | E46: 1.3 | F46: =D46/E46/1000 -> 9.2307692 | G46: 60 | H46: =G46*52 -> 3120 | I46: =G46*48*E46*0.8*0.81 -> 2426.112 | Q46: Sala de reuniones | R46: Mini Split | S46: 12000 | T46: 1.3 | U46: =S46/T46/1000 -> 9.2307692 | V46: 60 | W46: =V46*52 -> 3120 | X46: =V46*48*T46*0.8*0.81 -> 2426.112 | Y46: ✓
B47: Total | E47: =SUM(E40:E46) -> 21.46 | G47: =SUM(G40:G46) -> 420 | H47: =SUM(H40:H46) -> 21840 | I47: =SUM(I40:I46) -> 40049.51 | Q47: Total | T47: =SUM(T40:T46) -> 21.46 | V47: =SUM(V40:V46) -> 420 | W47: =SUM(W40:W46) -> 21840 | X47: =SUM(X40:X46) -> 40049.51
M60: Ejemplo | AB60: Ejemplo
D61: Eficiencia energética = (Energía de salida útil / Energía de entrada) x 100% | J61: Factor de carga del equipo | M61: 0.8 | S61: Eficiencia energética = (Energía de salida útil / Energía de entrada) x 100% | Y61: Factor de carga del equipo | AB61: 0.8
D62: EER = 12,000 BTU/h / 1,200 W | J62: Factor de potencia del equipo | M62: 0.75 | S62: EER = 12,000 BTU/h / 1,200 W | Y62: Factor de potencia del equipo | AB62: 0.75
D63: EER = 10 | S63: EER = 10
D64: https://reformaenergeticamalaga.es/como-convertir-btu-en-kw-pasar-transformar.html?btu=1 | S64: https://reformaenergeticamalaga.es/como-convertir-btu-en-kw-pasar-transformar.html?btu=1
C67: Inventario de luminarias de la empresa | R67: Inventario de luminarias de la empresa
B69: Área | C69: Tipo | D69: Potencia [W] | E69: Cantidad | F69: Potencia instalada [W] | G69: Uso aproximado (h/día) | H69: Consumo anual [kWh/año] | Q69: Área | R69: Tipo | S69: Potencia [W] | T69: Cantidad | U69: Potencia instalada [W] | V69: Uso aproximado (h/día) | W69: Consumo anual [kWh/año]
B70: Oficina Lab de Control | C70: Tubo fluorescente | D70: 32 | E70: 24 | F70: =D70*E70 -> 768 | G70: 9 | H70: =F70*G70*313/1000 -> 2163.456 | Q70: Oficina Lab de Control | R70: Tubo fluorescente | S70: 32 | T70: 24 | U70: =S70*T70 -> 768 | V70: 9 | W70: =U70*V70*313/1000 -> 2163.456 | X70: ✓
C71: Foco fluorescente | D71: 25 | E71: 1 | F71: =D71*E71 -> 25 | G71: 9 | H71: =F71*G71*313/1000 -> 70.425 | R71: Foco fluorescente | S71: 25 | T71: 1 | U71: =S71*T71 -> 25 | V71: 9 | W71: =U71*V71*313/1000 -> 70.425 | X71: ✓
B72: Exteriores | C72: Foco fluorescente | D72: 25 | E72: 2 | F72: =D72*E72 -> 50 | G72: 6 | H72: =F72*G72*313/1000 -> 93.9 | Q72: Exteriores | R72: Foco fluorescente | S72: 25 | T72: 2 | U72: =S72*T72 -> 50 | V72: 6 | W72: =U72*V72*313/1000 -> 93.9 | X72: ✓
C73: Perimetrales | D73: 75 | E73: 2 | F73: =D73*E73 -> 150 | G73: 12 | H73: =F73*G73*313/1000 -> 563.4 | R73: Perimetrales | S73: 75 | T73: 2 | U73: =S73*T73 -> 150 | V73: 12 | W73: =U73*V73*313/1000 -> 563.4 | X73: ✓
B74: Lab Suelos | C74: Tubo fluorescente | D74: 32 | E74: 30 | F74: =D74*E74 -> 960 | G74: 9 | H74: =F74*G74*313/1000 -> 2704.32 | Q74: Lab Suelos | R74: Tubo fluorescente | S74: 32 | T74: 30 | U74: =S74*T74 -> 960 | V74: 9 | W74: =U74*V74*313/1000 -> 2704.32 | X74: ✓
B75: Lab I+D | C75: Tubo fluorescente | D75: 32 | E75: 51 | F75: =D75*E75 -> 1632 | G75: 9 | H75: =F75*G75*313/1000 -> 4597.344 | Q75: Lab I+D | R75: Tubo fluorescente | S75: 32 | T75: 51 | U75: =S75*T75 -> 1632 | V75: 9 | W75: =U75*V75*313/1000 -> 4597.344 | X75: ✓
C76: Lámpara fluorescente | D76: 25 | E76: 1 | F76: =D76*E76 -> 25 | G76: 9 | H76: =F76*G76*313/1000 -> 70.425 | R76: Lámpara fluorescente | S76: 25 | T76: 1 | U76: =S76*T76 -> 25 | V76: 9 | W76: =U76*V76*313/1000 -> 70.425 | X76: ✓
B77: Oficinas 1 | C77: Tubo fluorescente | D77: 32 | E77: 8 | F77: =D77*E77 -> 256 | G77: 9 | H77: =F77*G77*313/1000 -> 721.152 | Q77: Oficinas 1 | R77: Tubo fluorescente | S77: 32 | T77: 8 | U77: =S77*T77 -> 256 | V77: 9 | W77: =U77*V77*313/1000 -> 721.152 | X77: ✓
B78: Oficinas 2 | C78: Tubo fluorescente | D78: 32 | E78: 12 | F78: =D78*E78 -> 384 | G78: 9 | H78: =F78*G78*313/1000 -> 1081.728 | Q78: Oficinas 2 | R78: Tubo fluorescente | S78: 32 | T78: 12 | U78: =S78*T78 -> 384 | V78: 9 | W78: =U78*V78*313/1000 -> 1081.728 | X78: ✓
B79: Baños | C79: Tubo fluorescente | D79: 32 | E79: 2 | F79: =D79*E79 -> 64 | G79: 1 | H79: =F79*G79*313/1000 -> 20.032 | Q79: Baños | R79: Tubo fluorescente | S79: 32 | T79: 2 | U79: =S79*T79 -> 64 | V79: 1 | W79: =U79*V79*313/1000 -> 20.032 | X79: ✓
B80: Oficinas 3 | C80: Tubo fluorescente | D80: 32 | E80: 3 | F80: =D80*E80 -> 96 | G80: 9 | H80: =F80*G80*313/1000 -> 270.432 | Q80: Oficinas 3 | R80: Tubo fluorescente | S80: 32 | T80: 3 | U80: =S80*T80 -> 96 | V80: 9 | W80: =U80*V80*313/1000 -> 270.432 | X80: ✓
B81: Pasillo | C81: Tubo fluorescente | D81: 32 | E81: 6 | F81: =D81*E81 -> 192 | G81: 9 | H81: =F81*G81*313/1000 -> 540.864 | Q81: Pasillo | R81: Tubo fluorescente | S81: 32 | T81: 6 | U81: =S81*T81 -> 192 | V81: 9 | W81: =U81*V81*313/1000 -> 540.864 | X81: ✓
B82: Cocina | C82: Foco fluorescente | D82: 25 | E82: 2 | F82: =D82*E82 -> 50 | G82: 4 | H82: =F82*G82*313/1000 -> 62.6 | Q82: Cocina | R82: Foco fluorescente | S82: 25 | T82: 2 | U82: =S82*T82 -> 50 | V82: 4 | W82: =U82*V82*313/1000 -> 62.6 | X82: ✓
B83: Sala de reuniones | C83: Tubo fluorescente | D83: 32 | E83: 12 | F83: =D83*E83 -> 384 | G83: 0.3 | H83: =F83*G83*313/1000 -> 36.0576 | Q83: Sala de reuniones | R83: Tubo fluorescente | S83: 32 | T83: 12 | U83: =S83*T83 -> 384 | V83: 0.3 | W83: =U83*V83*313/1000 -> 36.0576 | X83: ✓
B84: Total | F84: =SUM(F70:F83) -> 5036 | H84: =SUM(H70:H83) -> 12996.136 | Q84: Total | U84: =SUM(U70:U83) -> 5036 | W84: =SUM(W70:W83) -> 12996.136
C101: Inventario de equipo de laboratorio de mayor uso
R102: Inventario de equipo de laboratorio de mayor uso
B103: Descripción | C103: Capacidad instalada [kW] | D103: Horas de uso /día | E103: [kWh]/día | F103: [kWh]/mes | G103: [kWh]/año | Q103: Descripción | R103: Capacidad instalada [kW] | S103: Horas de uso /día | T103: [kWh]/día | U103: [kWh]/mes | V103: [kWh]/año
B105: Reómetro | C105: 0.0095 | D105: 3 | E105: =C105*D105 -> 0.0285 | F105: =E105*5 -> 0.1425 | G105: =F105*12 -> 1.71 | Q105: Reómetro | R105: 0.0095 | S105: 3 | T105: =R105*S105 -> 0.0285 | U105: =T105*5 -> 0.1425 | V105: =U105*12 -> 1.71 | W105: ✓
B106: Hornos (3) | C106: 1.92 | D106: 24 | E106: =C106*D106*5 -> 230.4 | F106: =E106*5 -> 1152 | G106: =F106*12 -> 13824 | Q106: Hornos (3) | R106: 1.92 | S106: 24 | T106: =R106*S106*5 -> 230.4 | U106: =T106*5 -> 1152 | V106: =U106*12 -> 13824 | W106: ✓
B107: RTFO | C107: 1.5 | D107: 3 | E107: =C107*D107 -> 4.5 | F107: =E107*5 -> 22.5 | G107: =F107*12 -> 270 | Q107: RTFO | R107: 1.5 | S107: 3 | T107: =R107*S107 -> 4.5 | U107: =T107*5 -> 22.5 | V107: =U107*12 -> 270 | W107: ✓
B108: Compresor | C108: 12 | D108: 16 | E108: =C108*D108 -> 192 | F108: =E108*5 -> 960 | G108: =F108*12 -> 11520 | Q108: Compresor | R108: 12 | S108: 16 | T108: =R108*S108 -> 192 | U108: =T108*5 -> 960 | V108: =U108*12 -> 11520 | W108: ✓
C109: =SUM(C105:C108) -> 15.4295 | E109: =SUM(E105:E108) -> 426.9285 | F109: =SUM(F105:F108) -> 2134.6425 | G109: =SUM(G105:G108) -> 25615.71 | R109: =SUM(R105:R108) -> 15.4295 | T109: =SUM(T105:T108) -> 426.9285 | U109: =SUM(U105:U108) -> 2134.6425 | V109: =SUM(V105:V108) -> 25615.71
C115: Inventario de quemadores de queroseno | R115: Inventario de quemadores de queroseno
Q116: Área | R116: Descripción | S116: Capacidad de procesamiento gal/hora (placa) | T116: Capacidad de generación de energía kBTU/hora (placa) | U116: Combustible consumido gal/mes | V116: Consumo anual gal/año
B117: Área | C117: Descripción | D117: Capacidad de procesamiento gal/hora (placa) | E117: Capacidad de generación de energía kBTU/hora (placa) | F117: Combustible consumido gal/mes | G117: Consumo anual gal/año
I120: Dato identificado en Balance térmico; Calentamiento de Agua | Q120: Agua jabonosa y aditivos | R120: Quemador kerosene | S120: 1,2 a 5,5 | T120: 175 a 170 | U120: ='Balance Térmico'!S76 -> 31.633869 | V120: =U120*12 -> 379.60643 | W120: =V120 -> 379.60643 | X120: Dato identificado en Balance térmico; Calentamiento de Agua
B121: Agua jabonosa y aditivos | C121: Quemador kerosene | D121: 1,2 a 5,5 | E121: 175 a 170 | F121: ='Balance Térmico'!G76 -> 31.633869 | G121: =F121*12 -> 379.60643 | H121: =G121 -> 379.60643
I122: Dato identificado en Balance térmico; Calentamiento Asfalto | L122: =IF(H123>H127,"Mayor","-") -> - | Q122: Almacenamiento y recirculación de asfalto | R122: Quemador kerosene | S122: 1,2 a 5,5 | T122: 175 a 170 | U122: ='Balance Térmico'!S74 -> 103.04626 | V122: =U122*12 -> 1236.5552 | W122: =V122+V124 -> 1236.5552 | X122: Dato identificado en Balance térmico; Calentamiento Asfalto | AA122: =IF(W122>W126,"Mayor","-") -> -
B123: Almacenamiento y recirculación de asfalto | C123: Quemador kerosene | D123: 1,2 a 5,5 | E123: 175 a 170 | F123: ='Balance Térmico'!G74 -> 105.48043 | G123: =F123*12 -> 1265.7651 | H123: =G123+G125 -> 1265.7651
R124: Quemador kerosene | S124: 1,2 a 5,5 | T124: 175 a 170
C125: Quemador kerosene | D125: 1,2 a 5,5 | E125: 175 a 170
I126: Dato identificado en Balance térmico; Calentamiento Aceite Térmico | L126: =IF(H127>H123,"Mayor","-") -> Mayor | Q126: Emulsión | R126: Quemador kerosene (recirculación aceite térmico) | S126: 1,2 a 5,5 | T126: 175 a 170 | U126: ='Balance Térmico'!S75 -> 135.42778 | V126: =U126*12 -> 1625.1334 | W126: =V126+V128 -> 1625.1334 | X126: Dato identificado en Balance térmico; Calentamiento Aceite Térmico | AA126: =IF(W126>W122,"Mayor","-") -> Mayor
B127: Emulsión | C127: Quemador kerosene (recirculación aceite térmico) | D127: 1,2 a 5,5 | E127: 175 a 170 | F127: ='Balance Térmico'!G75 -> 149.98088 | G127: =F127*12 -> 1799.7705 | H127: =G127+G129 -> 1799.7705
R128: Quemador kerosene (caldera aceite térmico) | S128: 1,2 a 5,5 | T128: 175 a 170
C129: Quemador kerosene (caldera aceite térmico) | D129: 1,2 a 5,5 | E129: 175 a 170
Q130: Total | U130: =SUM(U120:U129) -> 270.10791 | V130: =SUM(V120:V129) -> 3241.295
B131: Total | F131: =SUM(F121:F130) -> 287.09517 | G131: =SUM(G121:G130) -> 3445.1421

Sheet Inventario
B3: Área | C3: Tipo | D3: Potencia [W] | E3: Cantidad | F3: Potencia instalada [W] | G3: Uso aproximado (h/día) | H3: Consumo anual [kWh/año]
B4: Oficina Lab de Control | C4: Tubo fluorescente | D4: 32 | E4: 24 | F4: =D4*E4 -> 768 | G4: 9 | H4: =F4*G4*313/1000 -> 2163.456
C5: Foco fluorescente | D5: 25 | E5: 1 | F5: =D5*E5 -> 25 | G5: 9 | H5: =F5*G5*313/1000 -> 70.425
B6: Exteriores | C6: Foco fluorescente | D6: 25 | E6: 2 | F6: =D6*E6 -> 50 | G6: 6 | H6: =F6*G6*313/1000 -> 93.9
C7: Perimetrales | D7: 75 | E7: 2 | F7: =D7*E7 -> 150 | G7: 12 | H7: =F7*G7*313/1000 -> 563.4
B8: Lab Suelos | C8: Tubo fluorescente | D8: 32 | E8: 30 | F8: =D8*E8 -> 960 | G8: 9 | H8: =F8*G8*313/1000 -> 2704.32
B9: Lab I+D | C9: Tubo fluorescente | D9: 32 | E9: 51 | F9: =D9*E9 -> 1632 | G9: 9 | H9: =F9*G9*313/1000 -> 4597.344
C10: Lámpara fluorescente | D10: 25 | E10: 1 | F10: =D10*E10 -> 25 | G10: 9 | H10: =F10*G10*313/1000 -> 70.425
B11: Oficinas 1 | C11: Tubo fluorescente | D11: 32 | E11: 8 | F11: =D11*E11 -> 256 | G11: 9 | H11: =F11*G11*313/1000 -> 721.152
B12: Oficinas 2 | C12: Tubo fluorescente | D12: 32 | E12: 12 | F12: =D12*E12 -> 384 | G12: 9 | H12: =F12*G12*313/1000 -> 1081.728
B13: Baños | C13: Tubo fluorescente | D13: 32 | E13: 2 | F13: =D13*E13 -> 64 | G13: 1 | H13: =F13*G13*313/1000 -> 20.032
B14: Oficinas 3 | C14: Tubo fluorescente | D14: 32 | E14: 3 | F14: =D14*E14 -> 96 | G14: 9 | H14: =F14*G14*313/1000 -> 270.432
B15: Pasillo | C15: Tubo fluorescente | D15: 32 | E15: 6 | F15: =D15*E15 -> 192 | G15: 9 | H15: =F15*G15*313/1000 -> 540.864
B16: Cocina | C16: Foco fluorescente | D16: 25 | E16: 2 | F16: =D16*E16 -> 50 | G16: 4 | H16: =F16*G16*313/1000 -> 62.6
B17: Sala de reuniones | C17: Tubo fluorescente | D17: 32 | E17: 12 | F17: =D17*E17 -> 384 | G17: 0.3 | H17: =F17*G17*313/1000 -> 36.0576
B18: Total | F18: =SUM(F4:F17) -> 5036 | H18: =SUM(H4:H17) -> 12996.136
J22: Área | K22: Tipo | L22: Capacidad [BTU/h] | M22: Potencia [kW] | N22: EER | O22: Horas Semana | P22: Horas año | Q22: Consumo anual [kWh/año]
J23: Lab. de Control | K23: Mini Split | L23: 12000 | M23: 1.26 | N23: =L23/M23/1000 -> 9.5238095 | O23: 60 | P23: =O23*52 -> 3120 | Q23: =O23*48*M23*0.8*0.81 -> 2351.4624
J24: Lab. de Control | K24: Central | L24: 60000 | M24: 7.5 | N24: =L24/M24/1000 -> 8 | O24: 60 | P24: =O24*52 -> 3120 | Q24: =O24*48*M24*0.8*0.81 -> 13996.8
J25: Lab. de Suelos | K25: Central | L25: 60000 | M25: 7.5 | N25: =L25/M25/1000 -> 8 | O25: 60 | P25: =O25*52 -> 3120 | Q25: =O25*48*M25*0.8*0.81 -> 13996.8
J26: Oficinas 1 | K26: Mini Split | L26: 12000 | M26: 1.3 | N26: =L26/M26/1000 -> 9.2307692 | O26: 60 | P26: =O26*52 -> 3120 | Q26: =O26*48*M26*0.8*0.81 -> 2426.112
J27: Oficinas 2 | K27: Mini Split | L27: 12000 | M27: 1.3 | N27: =L27/M27/1000 -> 9.2307692 | O27: 60 | P27: =O27*52 -> 3120 | Q27: =O27*48*M27*0.8*0.81 -> 2426.112
J28: Oficinas 3 | K28: Mini Split | L28: 12000 | M28: 1.3 | N28: =L28/M28/1000 -> 9.2307692 | O28: 60 | P28: =O28*52 -> 3120 | Q28: =O28*48*M28*0.8*0.81 -> 2426.112
J29: Sala de reuniones | K29: Mini Split | L29: 12000 | M29: 1.3 | N29: =L29/M29/1000 -> 9.2307692 | O29: 60 | P29: =O29*52 -> 3120 | Q29: =O29*48*M29*0.8*0.81 -> 2426.112
J30: Total | M30: =SUM(M23:M29) -> 21.46 | O30: =SUM(O23:O29) -> 420 | P30: =SUM(P23:P29) -> 21840 | Q30: =SUM(Q23:Q29) -> 40049.51
S32: Área | T32: Descripción | U32: Capacidad instalada [kW] | V32: Hora de uso diario | W32: Factor de carga | X32: [Kwh]/día | Y32: [Kwh]/mes | Z32: [Kwh]/año
S33: Agua jabonosa y aditivos | T33: Bomba de pozo | U33: 0.7 | V33: 4 | W33: 0.9 | X33: =U33*V33*W33 -> 2.52 | Y33: =X33*5 -> 12.6 | Z33: =Y33*12 -> 151.2
T34: Bomba mezclador | U34: 5.6 | V34: 4 | W34: 0.9 | X34: =U34*V34*W34 -> 20.16 | Y34: =X34*5 -> 100.8 | Z34: =Y34*12 -> 1209.6
T35: Bomba para ácido | U35: 1.5 | V35: 4 | W35: 0.9 | X35: =U35*V35*W35 -> 5.4 | Y35: =X35*5 -> 27 | Z35: =Y35*12 -> 324
T36: Bomba para jabón (estanque de preparación) | U36: 3 | V36: 4 | W36: 0.9 | X36: =U36*V36*W36 -> 10.8 | Y36: =X36*5 -> 54 | Z36: =Y36*12 -> 648
T37: Bomba de kereosene (calentar agua) | U37: 0.2 | V37: 4 | W37: 0.9 | X37: =U37*V37*W37 -> 0.72 | Y37: =X37*5 -> 3.6 | Z37: =Y37*12 -> 43.2
T38: Bomba de jabón (agua preparada) | U38: 2.2 | V38: 4 | W38: 0.9 | X38: =U38*V38*W38 -> 7.92 | Y38: =X38*5 -> 39.6 | Z38: =Y38*12 -> 475.2
T39: Motor rotador emulsión | U39: 8.2 | V39: 4 | W39: 0.9 | X39: =U39*V39*W39 -> 29.52 | Y39: =X39*5 -> 147.6 | Z39: =Y39*12 -> 1771.2
S40: Emulsión | T40: Bomba de asfalto ex | U40: 3.7 | V40: 4 | W40: 0.9 | X40: =U40*V40*W40 -> 13.32 | Y40: =X40*5 -> 66.6 | Z40: =Y40*12 -> 799.2
T41: Bomba de asfalto in | U41: 11.2 | V41: 4 | W41: 0.9 | X41: =U41*V41*W41 -> 40.32 | Y41: =X41*5 -> 201.6 | Z41: =Y41*12 -> 2419.2
T42: Motor aceite térmico | U42: 1.3 | V42: 4 | W42: 0.9 | X42: =U42*V42*W42 -> 4.68 | Y42: =X42*5 -> 23.4 | Z42: =Y42*12 -> 280.8
S43: Almacenamiento | T43: Bomba de emulsión | U43: 5.6 | V43: 4 | W43: 0.9 | X43: =U43*V43*W43 -> 20.16 | Y43: =X43*5 -> 100.8 | Z43: =Y43*12 -> 1209.6
S44: Nodriza | T44: Motor de mezcladora | U44: 22.4 | V44: 4 | W44: 0.9 | X44: =U44*V44*W44 -> 80.64 | Y44: =X44*5 -> 403.2 | Z44: =Y44*12 -> 4838.4
T45: Bomba de emulsiones | U45: 7.5 | V45: 4 | W45: 0.9 | X45: =U45*V45*W45 -> 27 | Y45: =X45*5 -> 135 | Z45: =Y45*12 -> 1620
T46: Motor de reductores 3/8 | U46: 1.5 | V46: 4 | W46: 0.9 | X46: =U46*V46*W46 -> 5.4 | Y46: =X46*5 -> 27 | Z46: =Y46*12 -> 324
T47: Motor de reductores 3/4 | U47: 1.5 | V47: 4 | W47: 0.9 | X47: =U47*V47*W47 -> 5.4 | Y47: =X47*5 -> 27 | Z47: =Y47*12 -> 324
T48: Motor reductor de chispa | U48: 1.5 | V48: 4 | W48: 0.9 | X48: =U48*V48*W48 -> 5.4 | Y48: =X48*5 -> 27 | Z48: =Y48*12 -> 324
T49: Motor banda transportadora | U49: 1.6 | V49: 4 | W49: 0.9 | X49: =U49*V49*W49 -> 5.76 | Y49: =X49*5 -> 28.8 | Z49: =Y49*12 -> 345.6
T50: Bomba de agua | U50: 1.5 | V50: 4 | W50: 0.9 | X50: =U50*V50*W50 -> 5.4 | Y50: =X50*5 -> 27 | Z50: =Y50*12 -> 324
T51: Bomba de asfalto | U51: 0.7 | V51: 4 | W51: 0.9 | X51: =U51*V51*W51 -> 2.52 | Y51: =X51*5 -> 12.6 | Z51: =Y51*12 -> 151.2
T52: Bomba contra incendio | U52: 3 | V52: 4 | W52: 0.9 | X52: =U52*V52*W52 -> 10.8 | Y52: =X52*5 -> 54 | Z52: =Y52*12 -> 648
T53: Total | U53: =SUM(U33:U52) -> 84.4 | X53: =SUM(X33:X52) -> 303.84 | Y53: =SUM(Y33:Y52) -> 1519.2 | Z53: =SUM(Z33:Z52) -> 18230.4
AB56: Descripción | AC56: Capacidad instalada [kW] | AD56: Horas de uso /día | AE56: [kWh]/día | AF56: [kWh]/mes | AG56: [kWh]/año
AB58: Reómetro | AC58: 0.0095 | AD58: 3 | AE58: =AC58*AD58 -> 0.0285 | AF58: =AE58*5 -> 0.1425 | AG58: =AF58*12 -> 1.71
AB59: Hornos (3) | AC59: 1.92 | AD59: 24 | AE59: =AC59*AD59*5 -> 230.4 | AF59: =AE59*5 -> 1152 | AG59: =AF59*12 -> 13824
AB60: RTFO | AC60: 1.5 | AD60: 3 | AE60: =AC60*AD60 -> 4.5 | AF60: =AE60*5 -> 22.5 | AG60: =AF60*12 -> 270
AB61: Compresor | AC61: 12 | AD61: 16 | AE61: =AC61*AD61 -> 192 | AF61: =AE61*5 -> 960 | AG61: =AF61*12 -> 11520
AC62: =SUM(AC58:AC61) -> 15.4295 | AE62: =SUM(AE58:AE61) -> 426.9285 | AF62: =SUM(AF58:AF61) -> 2134.6425 | AG62: =SUM(AG58:AG61) -> 25615.71
AI64: Área | AJ64: Descripción | AK64: Capacidad de procesamiento gal/hora (placa) | AL64: Capacidad de generación de energía kBTU/hora (placa) | AM64: Combustible consumido gal/mes | AN64: Consumo anual gal/año
AI68: Agua jabonosa y aditivos | AJ68: Quemador kerosene | AK68: 1,2 a 5,5 | AL68: 175 a 170 | AM68: =Cuantificador!F121 -> 31.633869 | AN68: =AM68*12 -> 379.60643
AI70: Almacenamiento y recirculación de asfalto | AJ70: Quemador kerosene | AK70: 1,2 a 5,5 | AL70: 175 a 170 | AM70: =Cuantificador!F123 -> 105.48043 | AN70: =AM70*12 -> 1265.7651
AJ72: Quemador kerosene | AK72: 1,2 a 5,5 | AL72: 175 a 170
AI74: Emulsión | AJ74: Quemador kerosene (recirculación aceite térmico) | AK74: 1,2 a 5,5 | AL74: 175 a 170 | AM74: =Cuantificador!F127 -> 149.98088 | AN74: =AM74*12 -> 1799.7705
AJ76: Quemador kerosene (caldera aceite térmico) | AK76: 1,2 a 5,5 | AL76: 175 a 170
AI78: Total | AM78: =SUM(AM68:AM77) -> 287.09517 | AN78: =SUM(AN68:AN77) -> 3445.1421
AP81: Área | AQ81: Descripción | AR81: Capacidad instalada [kW] | AS81: Hora de uso diario | AT81: Factor de carga | AU81: [KWh]/día | AV81: [KWh]/mes | AW81: [KWh]/año
AP82: Emulsión | AQ82: Molino coloidal | AR82: 37.29 | AS82: 4 | AT82: 0.9 | AU82: =AR82*AS82*AT82 -> 134.244 | AV82: =AU82*5 -> 671.22 | AW82: =AV82*12 -> 8054.64
AY85: PERÍODO FACTURA | BC85: CONSUMO [kWh]
AY86: Mes | AZ86: Inicio | BA86: Término | BB86: Días | BC86: Horario Llano (08:00 - 18:00) | BD86: Horario Punta (18:00 - 22:00) | BE86: Horario Valle (22:00 - 08:00) | BF86: Total Consumo [kWh]
AY88: 44562 | AZ88: 44564 | BA88: 44595 | BB88: =BA88-AZ88 -> 31 | BC88: 4846.99 | BD88: 1648.32 | BE88: 1779.62 | BF88: =SUM(BC88:BE88) -> 8274.93
AY89: 44593 | AZ89: =BA88 -> 44595 | BA89: 44625 | BB89: =BA89-AZ89 -> 30 | BC89: 7003.34 | BD89: 1467.53 | BE89: 1632.16 | BF89: =SUM(BC89:BE89) -> 10103.03
AY90: 44621 | AZ90: =BA89 -> 44625 | BA90: 44655 | BB90: =BA90-AZ90 -> 30 | BC90: 7339.67 | BD90: 1476.62 | BE90: 1730.13 | BF90: =SUM(BC90:BE90) -> 10546.42
AY91: 44652 | AZ91: =BA90 -> 44655 | BA91: 44686 | BB91: =BA91-AZ91 -> 31 | BC91: 6355.93 | BD91: 1402.89 | BE91: 1664.48 | BF91: =SUM(BC91:BE91) -> 9423.3
AY92: 44682 | AZ92: =BA91 -> 44686 | BA92: 44716 | BB92: =BA92-AZ92 -> 30 | BC92: 9939.41 | BD92: 1755.38 | BE92: 1886.68 | BF92: =SUM(BC92:BE92) -> 13581.47
AY93: 44713 | AZ93: =BA92 -> 44716 | BA93: 44747 | BB93: =BA93-AZ93 -> 31 | BC93: 7217.46 | BD93: 1246.34 | BE93: 1467.53 | BF93: =SUM(BC93:BE93) -> 9931.33
AY94: 44743 | AZ94: =BA93 -> 44747 | BA94: 44777 | BB94: =BA94-AZ94 -> 30 | BC94: 6847.8 | BD94: 1287.75 | BE94: 1533.18 | BF94: =SUM(BC94:BE94) -> 9668.73
AY95: 44774 | AZ95: =BA94 -> 44777 | BA95: 44807 | BB95: =BA95-AZ95 -> 30 | BC95: 5962.03 | BD95: 1156.45 | BE95: 1410.97 | BF95: =SUM(BC95:BE95) -> 8529.45
AY96: 44805 | AZ96: =BA95 -> 44807 | BA96: 44837 | BB96: =BA96-AZ96 -> 30 | BC96: 6987.18 | BD96: 1230.18 | BE96: 1467.53 | BF96: =SUM(BC96:BE96) -> 9684.89
AY97: 44835 | AZ97: =BA96 -> 44837 | BA97: 44868 | BB97: =BA97-AZ97 -> 31 | BC97: 6495.31 | BD97: 1172.61 | BE97: 1377.64 | BF97: =SUM(BC97:BE97) -> 9045.56
AY98: 44866 | AZ98: =BA97 -> 44868 | BA98: 44899 | BB98: =BA98-AZ98 -> 31 | BC98: 6921.53 | BD98: 1262.5 | BE98: 1492.78 | BF98: =SUM(BC98:BE98) -> 9676.81
AY99: 44896 | AZ99: =BA98 -> 44899 | BA99: 44929 | BB99: =BA99-AZ99 -> 30 | BC99: 6019.6 | BD99: 1188.77 | BE99: 1369.56 | BF99: =SUM(BC99:BE99) -> 8577.93
AY100: 44927 | AZ100: =BA99 -> 44929 | BA100: 44960 | BB100: =BA100-AZ100 -> 31 | BC100: 4703.02 | BD100: 1599.36 | BE100: 1726.76 | BF100: =SUM(BC100:BE100) -> 8029.14
... AY111: 45261 | AZ111: =BA110 -> 45263 | BA111: 45294 | BB111: =BA111-AZ111 -> 31 | BC111: 5662 | BD111: 1118.15 | BE111: 1288.2 | BF111: =SUM(BC111:BE111) -> 8068.35
AY112: Media (mes) 2022 | BC112: =AVERAGE(BC88:BC99) -> 6828.0208 | BD112: =AVERAGE(BD88:BD99) -> 1357.945 | BE112: =AVERAGE(BE88:BE99) -> 1567.6883 | BF112: =AVERAGE(BF88:BF99) -> 9753.6542
AY113: Total (anual) 2022 | BC113: =SUM(BC88:BC99) -> 81936.25 | BD113: =SUM(BD88:BD99) -> 16295.34 | BE113: =SUM(BE88:BE99) -> 18812.26 | BF113: =SUM(BF88:BF99) -> 117043.85
AY114: Media (mes) 2023 | BC114: =AVERAGE(BC100:BC111) -> 6589.73 | BD114: =AVERAGE(BD100:BD111) -> 1311.2517 | BE114: =AVERAGE(BE100:BE111) -> 1515.8033 | BF114: =AVERAGE(BF100:BF111) -> 9416.785
AY115: Total (anual) 2023 | BC115: =SUM(BC100:BC111) -> 79076.76 | BD115: =SUM(BD100:BD111) -> 15735.02 | BE115: =SUM(BE100:BE111) -> 18189.64 | BF115: =SUM(BF100:BF111) -> 113001.42

Sheet Pareto
C1: Inventario de motores de la empresa
B3: Área | C3: Descripción | D3: Capacidad instalada [kW] | E3: Hora de uso diario | F3: Factor de carga | G3: [Kwh]/día | H3: [Kwh]/mes | I3: [Kwh]/año | L3: [Kwh]/año | Y3: Diseño en .vsd, by PGF
B4: Agua jabonosa y aditivos | C4: Bomba de pozo | D4: 0.7 | E4: 4 | F4: 0.9 | G4: =D4*E4*F4 -> 2.52 | H4: =G4*5 -> 12.6 | I4: =H4*12 -> 151.2 | J4: ✓ | K4: Proceso 02 | L4: =SUM(I4:I14) -> 9331.2
C5: Bomba mezclador | D5: 5.6 | E5: 4 | F5: 0.9 | G5: =D5*E5*F5 -> 20.16 | H5: =G5*5 -> 100.8 | I5: =H5*12 -> 1209.6 | J5: ✓
C6: Bomba para ácido | D6: 1.5 | E6: 4 | F6: 0.9 | G6: =D6*E6*F6 -> 5.4 | H6: =G6*5 -> 27 | I6: =H6*12 -> 324 | J6: ✓
C7: Bomba para jabón (estanque de preparación) | D7: 3 | E7: 4 | F7: 0.9 | G7: =D7*E7*F7 -> 10.8 | H7: =G7*5 -> 54 | I7: =H7*12 -> 648 | J7: ✓
C8: Bomba de kereosene (calentar agua) | D8: 0.2 | E8: 4 | F8: 0.9 | G8: =D8*E8*F8 -> 0.72 | H8: =G8*5 -> 3.6 | I8: =H8*12 -> 43.2 | J8: ✓
C9: Bomba de jabón (agua preparada) | D9: 2.2 | E9: 4 | F9: 0.9 | G9: =D9*E9*F9 -> 7.92 | H9: =G9*5 -> 39.6 | I9: =H9*12 -> 475.2 | J9: ✓
C10: Motor rotador emulsión | D10: 8.2 | E10: 4 | F10: 0.9 | G10: =D10*E10*F10 -> 29.52 | H10: =G10*5 -> 147.6 | I10: =H10*12 -> 1771.2 | J10: ✓
B11: Emulsión | C11: Bomba de asfalto ex | D11: 3.7 | E11: 4 | F11: 0.9 | G11: =D11*E11*F11 -> 13.32 | H11: =G11*5 -> 66.6 | I11: =H11*12 -> 799.2 | J11: ✓
C12: Bomba de asfalto in | D12: 11.2 | E12: 4 | F12: 0.9 | G12: =D12*E12*F12 -> 40.32 | H12: =G12*5 -> 201.6 | I12: =H12*12 -> 2419.2 | J12: ✓
C13: Motor aceite térmico | D13: 1.3 | E13: 4 | F13: 0.9 | G13: =D13*E13*F13 -> 4.68 | H13: =G13*5 -> 23.4 | I13: =H13*12 -> 280.8 | J13: ✓
B14: Almacenamiento | C14: Bomba de emulsión | D14: 5.6 | E14: 4 | F14: 0.9 | G14: =D14*E14*F14 -> 20.16 | H14: =G14*5 -> 100.8 | I14: =H14*12 -> 1209.6 | J14: ✓
B15: Nodriza | C15: Motor de mezcladora | D15: 22.4 | E15: 4 | F15: 0.9 | G15: =D15*E15*F15 -> 80.64 | H15: =G15*5 -> 403.2 | I15: =H15*12 -> 4838.4 | J15: ✓ | K15: Proceso 03 | L15: =SUM(I15:I23) -> 8899.2
C16: Bomba de emulsiones | D16: 7.5 | E16: 4 | F16: 0.9 | G16: =D16*E16*F16 -> 27 | H16: =G16*5 -> 135 | I16: =H16*12 -> 1620 | J16: ✓
C17: Motor de reductores 3/8 | D17: 1.5 | E17: 4 | F17: 0.9 | G17: =D17*E17*F17 -> 5.4 | H17: =G17*5 -> 27 | I17: =H17*12 -> 324 | J17: ✓
C18: Motor de reductores 3/4 | D18: 1.5 | E18: 4 | F18: 0.9 | G18: =D18*E18*F18 -> 5.4 | H18: =G18*5 -> 27 | I18: =H18*12 -> 324 | J18: ✓
C19: Motor reductor de chispa | D19: 1.5 | E19: 4 | F19: 0.9 | G19: =D19*E19*F19 -> 5.4 | H19: =G19*5 -> 27 | I19: =H19*12 -> 324 | J19: ✓
C20: Motor banda transportadora | D20: 1.6 | E20: 4 | F20: 0.9 | G20: =D20*E20*F20 -> 5.76 | H20: =G20*5 -> 28.8 | I20: =H20*12 -> 345.6 | J20: ✓
C21: Bomba de agua | D21: 1.5 | E21: 4 | F21: 0.9 | G21: =D21*E21*F21 -> 5.4 | H21: =G21*5 -> 27 | I21: =H21*12 -> 324 | J21: ✓
C22: Bomba de asfalto | D22: 0.7 | E22: 4 | F22: 0.9 | G22: =D22*E22*F22 -> 2.52 | H22: =G22*5 -> 12.6 | I22: =H22*12 -> 151.2 | J22: ✓
C23: Bomba contra incendio | D23: 3 | E23: 4 | F23: 0.9 | G23: =D23*E23*F23 -> 10.8 | H23: =G23*5 -> 54 | I23: =H23*12 -> 648 | J23: ✓
C24: Total | D24: =SUM(D4:D23) -> 84.4 | G24: =SUM(G4:G23) -> 303.84 | H24: =SUM(H4:H23) -> 1519.2 | I24: =SUM(I4:I23) -> 18230.4
H26: 1519.2 | I26: 18230.4
C39: Datos de consumo eléctrico de molino coloidal
S40: [Kwh]/año | W40: [Kwh]/año
B41: Área | C41: Descripción | D41: Capacidad instalada [kW] | E41: Hora de uso diario | F41: Factor de carga | G41: [KWh]/día | H41: [KWh]/mes | I41: [KWh]/año | L41: [Kwh]/año | Q41: Eléctrico | S41: =L4+L15+L42+L48+L51+L80+L87+L115 -> 104946.4 | V41: Combustible | W41: =N131+N133+N137 -> 134455.55
B42: Emulsión | C42: Molino coloidal | D42: 37.29 | E42: 4 | F42: 0.9 | G42: =D42*E42*F42 -> 134.244 | H42: =G42*5 -> 671.22 | I42: =H42*12 -> 8054.64 | J42: ✓ | K42: Proceso 02 | L42: =I42 -> 8054.64
Q43: Factura E | S43: ='Consumo Eléctrico'!I33 -> 114268.13 | V43: Factura C | W43: ='Consumo Térmico de la empresa'!S39 -> 134458.09
H44: 671.22 | I44: 8054.64
C45: Inventario de aires acondicionados de la empresa | Q45: Otros | S45: =S43-S41 -> 9321.734 | V45: Delta | W45: =W43-W41 -> 2.5383688
S46: =S45/12 -> 776.81117
B47: Área | C47: Tipo | D47: Capacidad [BTU/h] | E47: Potencia [kW] | F47: EER | G47: Horas Semana | H47: Horas año | I47: Consumo anual [kWh/año] | L47: [Kwh]/año
B48: Lab. de Control | C48: Mini Split | D48: 12000 | E48: 1.26 | F48: =D48/E48/1000 -> 9.5238095 | G48: 60 | H48: =G48*52 -> 3120 | I48: =G48*48*E48*0.8*0.81 -> 2351.4624 | J48: ✓ | K48: Sector 02 | L48: =SUM(I48:I50) -> 30345.062 | Q48: Consumo Energético Total
B49: Lab. de Control | C49: Central | D49: 60000 | E49: 7.5 | F49: =D49/E49/1000 -> 8 | G49: 60 | H49: =G49*52 -> 3120 | I49: =G49*48*E49*0.8*0.81 -> 13996.8 | J49: ✓ | Q49: [Kwh]/año | Z49: [Kwh]/año
B50: Lab. de Suelos | C50: Central | D50: 60000 | E50: 7.5 | F50: =D50/E50/1000 -> 8 | G50: 60 | H50: =G50*52 -> 3120 | I50: =G50*48*E50*0.8*0.81 -> 13996.8 | J50: ✓ | Q50: Electricidad | S50: Kerosene | U50: % | V50: % acum | Z50: Electricidad | AA50: Kerosene | AB50: % | AC50: % acum | AO50: USE´s | AP50: Electricidad GEI | AQ50: Kerosene GEI | AR50: % | AS50: % acum | BE50: =AO50 -> USE´s | BF50: Emisiones GEI | BG50: =AR50 -> % | BH50: =AS50 -> % acum
B51: Oficinas 1 | C51: Mini Split | D51: 12000 | E51: 1.3 | F51: =D51/E51/1000 -> 9.2307692 | G51: 60 | H51: =G51*52 -> 3120 | I51: =G51*48*E51*0.8*0.81 -> 2426.112 | J51: ✓ | K51: Sector 01 | L51: =SUM(I51:I54) -> 9704.448 | P51: Proceso 01 | S51: =N133 -> 49399.746 | U51: =(Q51+S51)/($Q$58+$S$58) -> 0.19861296 | V51: =U51 -> 0.19861296 | Y51: =P52 -> Proceso 02 | Z51: =Q52 -> 17385.84 | AA51: =S52 -> 85055.802 | AB51: =(Z51+AA51)/($Z$58+$AA$58) -> 0.41186928 | AC51: =AB51 -> 0.41186928 | AO51: =Y51 -> Proceso 02 | AP51: =Z51*'Emisiones de GEI'!$D$52/1000 -> 4.1447843 | AQ51: =AA51*'Emisiones de GEI'!$G$53/1000 -> 22.015844 | AR51: =(AP51+AQ51)/($AP$58+$AQ$58) -> 0.42164641 | AS51: =AR51 -> 0.42164641 | BE51: =AO51 -> Proceso 02 | BF51: =AP51+AQ51 -> 26.160628 | BG51: =BF51/$BF$58 -> 0.42164641 | BH51: =BG51 -> 0.42164641
B52: Oficinas 2 | C52: Mini Split | D52: 12000 | E52: 1.3 | F52: =D52/E52/1000 -> 9.2307692 | G52: 60 | H52: =G52*52 -> 3120 | I52: =G52*48*E52*0.8*0.81 -> 2426.112 | J52: ✓ | P52: Proceso 02 | Q52: =L4+L42 -> 17385.84 | S52: =N131+N137 -> 85055.802 | U52: =(Q52+S52)/($Q$58+$S$58) -> 0.41186928 | V52: =V51+U52 -> 0.61048224 | Y52: =P55 -> Sector 02 | Z52: =Q55 -> 66224.042 | AA52: =S55 -> 0 | AB52: =(Z52+AA52)/($Z$58+$AA$58) -> 0.26625548 | AC52: =AC51+AB52 -> 0.67812476 | AO52: =Y52 -> Sector 02 | AP52: =Z52*'Emisiones de GEI'!$D$52/1000 -> 15.787812 | AQ52: =AA52*'Emisiones de GEI'!$G$53/1000 -> 0 | AR52: =(AP52+AQ52)/($AP$58+$AQ$58) -> 0.25446155 | AS52: =AS51+AR52 -> 0.67610796 | BE52: =AO52 -> Sector 02 | BF52: =AP52+AQ52 -> 15.787812 | BG52: =BF52/$BF$58 -> 0.25446155 | BH52: =BH51+BG52 -> 0.67610796
B53: Oficinas 3 | C53: Mini Split | D53: 12000 | E53: 1.3 | F53: =D53/E53/1000 -> 9.2307692 | G53: 60 | H53: =G53*52 -> 3120 | I53: =G53*48*E53*0.8*0.81 -> 2426.112 | J53: ✓ | P53: Proceso 03 | Q53: =L15 -> 8899.2 | U53: =(Q53+S53)/($Q$58+$S$58) -> 0.035779464 | V53: =V52+U53 -> 0.6462617 | Y53: =P51 -> Proceso 01 | Z53: =Q51 -> 0 | AA53: =S51 -> 49399.746 | AB53: =(Z53+AA53)/($Z$58+$AA$58) -> 0.19861296 | AC53: =AC52+AB53 -> 0.87673772 | AO53: =Y53 -> Proceso 01 | AP53: =Z53*'Emisiones de GEI'!$D$52/1000 -> 0 | AQ53: =AA53*'Emisiones de GEI'!$G$53/1000 -> 12.78663 | AR53: =(AP53+AQ53)/($AP$58+$AQ$58) -> 0.20608973 | AS53: =AS52+AR53 -> 0.88219769 | BE53: =AO53 -> Proceso 01 | BF53: =AP53+AQ53 -> 12.78663 | BG53: =BF53/$BF$58 -> 0.20608973 | BH53: =BH52+BG53 -> 0.88219769
B54: Sala de reuniones | C54: Mini Split | D54: 12000 | E54: 1.3 | F54: =D54/E54/1000 -> 9.2307692 | G54: 60 | H54: =G54*52 -> 3120 | I54: =G54*48*E54*0.8*0.81 -> 2426.112 | J54: ✓ | P54: Sector 01 | Q54: =L51+L87 -> 12437.314 | U54: =(Q54+S54)/($Q$58+$S$58) -> 0.050004542 | V54: =V53+U54 -> 0.69626625 | Y54: =P54 -> Sector 01 | Z54: =Q54 -> 12437.314 | AA54: =S54 -> 0 | AB54: =(Z54+AA54)/($Z$58+$AA$58) -> 0.050004542 | AC54: =AC53+AB54 -> 0.92674226 | AO54: =Y54 -> Sector 01 | AP54: =Z54*'Emisiones de GEI'!$D$52/1000 -> 2.9650556 | AQ54: =AA54*'Emisiones de GEI'!$G$53/1000 -> 0 | AR54: =(AP54+AQ54)/($AP$58+$AQ$58) -> 0.047789565 | AS54: =AS53+AR54 -> 0.92998725 | BE54: =AO54 -> Sector 01 | BF54: =AP54+AQ54 -> 2.9650556 | BG54: =BF54/$BF$58 -> 0.047789565 | BH54: =BH53+BG54 -> 0.92998725
B55: Total | E55: =SUM(E48:E54) -> 21.46 | G55: =SUM(G48:G54) -> 420 | H55: =SUM(H48:H54) -> 21840 | I55: =SUM(I48:I54) -> 40049.51 | P55: Sector 02 | Q55: =L48+L80+L115 -> 66224.042 | U55: =(Q55+S55)/($Q$58+$S$58) -> 0.26625548 | V55: =V54+U55 -> 0.96252173 | Y55: =P56 -> Otros | Z55: =Q56 -> 9321.734 | AA55: =S56 -> 0 | AB55: =(Z55+AA55)/($Z$58+$AA$58) -> 0.037478273 | AC55: =AC54+AB55 -> 0.96422054 | AO55: =Y55 -> Otros | AP55: =Z55*'Emisiones de GEI'!$D$52/1000 -> 2.2223014 | AQ55: =AA55*'Emisiones de GEI'!$G$53/1000 -> 0 | AR55: =(AP55+AQ55)/($AP$58+$AQ$58) -> 0.035818154 | AS55: =AS54+AR55 -> 0.96580541 | BE55: =AO55 -> Otros | BF55: =AP55+AQ55 -> 2.2223014 | BG55: =BF55/$BF$58 -> 0.035818154 | BH55: =BH54+BG55 -> 0.96580541
P56: Otros | Q56: =S45 -> 9321.734 | U56: =(Q56+S56)/($Q$58+$S$58) -> 0.037478273 | V56: =V55+U56 -> 1 | Y56: =P53 -> Proceso 03 | Z56: =Q53 -> 8899.2 | AA56: =S53 -> 0 | AB56: =(Z56+AA56)/($Z$58+$AA$58) -> 0.035779464 | AC56: =AC55+AB56 -> 1 | AO56: =Y56 -> Proceso 03 | AP56: =Z56*'Emisiones de GEI'!$D$52/1000 -> 2.1215693 | AQ56: =AA56*'Emisiones de GEI'!$G$53/1000 -> 0 | AR56: =(AP56+AQ56)/($AP$58+$AQ$58) -> 0.034194594 | AS56: =AS55+AR56 -> 1 | BE56: =AO56 -> Proceso 03 | BF56: =AP56+AQ56 -> 2.1215693 | BG56: =BF56/$BF$58 -> 0.034194594 | BH56: =BH55+BG56 -> 1
H57: 21840 | I57: 40049.51
P58: Total | Q58: =SUM(Q52:Q56) -> 114268.13 | S58: =SUM(S51:S56) -> 134455.55 | U58: =SUM(U51:U56) -> 1 | V58: =V56 -> 1 | Y58: Total | Z58: =SUM(Z51:Z57) -> 114268.13 | AA58: =SUM(AA51:AA57) -> 134455.55 | AB58: =SUM(AB51:AB56) -> 1 | AC58: =AC56 -> 1 | AO58: Total | AP58: =SUM(AP51:AP56) -> 27.241522 | AQ58: =SUM(AQ51:AQ56) -> 34.802474 | AR58: =SUM(AR51:AR56) -> 1 | AS58: =AS56 -> 1 | BE58: =AO58 -> Total | BF58: =SUM(BF51:BF57) -> 62.043996 | BG58: =SUM(BG51:BG57) -> 1 | BH58: =BH56 -> 1
Q59: =SUM(Q58:S58) -> 248723.68
Q60: =Q58/$Q$59 -> 0.45941798 | S60: =S58/$Q$59 -> 0.54058202
D61: Proceso 01 (almacenamiento y aceite térmico) | H61: =S65/$S$77 -> 0.36740578 | Z61: Consumo energético anual por uso energético
D62: Proceso 02 (agua jabonosa y aditivos) | H62: =S66/$S$77 -> 0.110186 | N62: 9 | O62: Porcentaje de consumo energético anual por área (PCEAA)
D63: Proceso 02 (Emulsión) | H63: =S67/$S$77 -> 0.52240821 | Q63: [Kwh]/año | Z63: [Kwh]/año
O64: Uso de Energía | P64: Equipamiento | Q64: Electricidad | S64: Kerosene | U64: % | V64: % acum | Z64: Electricidad | AA64: Kerosene | AB64: % | AC64: % acum | AP64: Electricidad | AQ64: Kerosene GEI | AR64: % | AS64: % acum | BF64: Emisiones GEI | BG64: =AR64 -> % | BH64: =AS64 -> % acum
F65: =G65/Q59 -> 0.19861296 | G65: =S65 -> 49399.746 | H65: =T65 -> 0.36740578 | O65: Proceso 01 | P65: Quemadores (Almacenamiento y aceite térmico) | R65: =Q65/$Q$77 -> 0 | S65: =N133 -> 49399.746 | T65: =S65/$S$77 -> 0.36740578 | U65: =(Q65+S65)/($Q$77+$S$77) -> 0.19861296 | V65: =U65 -> 0.19861296 | W65: =U65 -> 0.19861296 | X65: 1 | Y65: =P67 -> Bombas-Motores (Emulsión) | Z65: =Q67 -> 11553.84 | AA65: =S67 -> 70240.683 | AB65: =(Z65+AA65)/($Z$77+$AA$77) -> 0.328857 | AC65: =AB65 -> 0.328857 | AO65: =Y65 -> Bombas-Motores (Emulsión) | AP65: =Z65*'Emisiones de GEI'!$D$52/1000 -> 2.7544355 | AQ65: =AA65*'Emisiones de GEI'!$G$53/1000 -> 18.181098 | AR65: =(AP65+AQ65)/($AP$77+$AQ$77) -> 0.33743045 | AS65: =AR65 -> 0.33743045 | BE65: =AO65 -> Bombas-Motores (Emulsión) | BF65: =AP65+AQ65 -> 20.935534 | BG65: =BF65/$BF$77 -> 0.33743045 | BH65: =BG65 -> 0.33743045
F66: =G66/Q59 -> 0.34196906 | G66: =S66+S67+S68+S69 -> 85055.802 | H66: =T66+T67+T68+T69 -> 0.63259422 | L66: =M66/Q59 -> 0.069900221 | M66: =Q66+Q67+Q68 -> 17385.84 | N66: =R66+R67+R68+R69 -> 0.23002949 | O66: Proceso 02 | P66: Bombas-Motores (Agua jabonosa y aditivos) | Q66: =I4+I5+I6+I7+I8+I9+I10 -> 4622.4 | R66: =Q66/$Q$77 -> 0.040452224 | S66: =N131 -> 14815.119 | T66: =S66/$S$77 -> 0.110186 | U66: =(Q66+S66)/($Q$77+$S$77) -> 0.07814905 | V66: =V65+U66 -> 0.27676201 | W66: =U66+U67+U68 -> 0.41186928 | X66: 2 | Y66: =P65 -> Quemadores (Almacenamiento y aceite térmico) | Z66: =Q65 -> 0 | AA66: =S65 -> 49399.746 | AB66: =(Z66+AA66)/($Z$77+$AA$77) -> 0.19861296 | AC66: =AC65+AB66 -> 0.52746996 | AO66: =Y66 -> Quemadores (Almacenamiento y aceite térmico) | AP66: =Z66*'Emisiones de GEI'!$D$52/1000 -> 0 | AQ66: =AA66*'Emisiones de GEI'!$G$53/1000 -> 12.78663 | AR66: =(AP66+AQ66)/($AP$77+$AQ$77) -> 0.20608973 | AS66: =AS65+AR66 -> 0.54352018 | BE66: =AO66 -> Quemadores (Almacenamiento y aceite térmico) | BF66: =AP66+AQ66 -> 12.78663 | BG66: =BF66/$BF$77 -> 0.20608973 | BH66: =BH65+BG66 -> 0.54352018
P67: Bombas-Motores (Emulsión) | Q67: =I11+I12+I13+I42 -> 11553.84 | R67: =Q67/$Q$77 -> 0.10111166 | S67: =N137 -> 70240.683 | T67: =S67/$S$77 -> 0.52240821 | U67: =(Q67+S67)/($Q$77+$S$77) -> 0.328857 | V67: =V66+U67 -> 0.60561901 | X67: 3 | Y67: =P72 -> Aires Acondicionados (Laboratorios) | Z67: =Q72 -> 30345.062 | AA67: =S72 -> 0 | AB67: =(Z67+AA67)/($Z$77+$AA$77) -> 0.12200311 | AC67: =AC66+AB67 -> 0.64947307 | AO67: =Y67 -> Aires Acondicionados (Laboratorios) | AP67: =Z67*'Emisiones de GEI'!$D$52/1000 -> 7.2342629 | AQ67: =AA67*'Emisiones de GEI'!$G$53/1000 -> 0 | AR67: =(AP67+AQ67)/($AP$77+$AQ$77) -> 0.11659892 | AS67: =AS66+AR67 -> 0.6601191 | BE67: =AO67 -> Aires Acondicionados (Laboratorios) | BF67: =AP67+AQ67 -> 7.2342629 | BG67: =BF67/$BF$77 -> 0.11659892 | BH67: =BH66+BG67 -> 0.6601191
P68: Bomba (Almacenamiento) | Q68: =I14 -> 1209.6 | R68: =Q68/$Q$77 -> 0.010585629 | T68: =S68/$S$77 -> 0 | U68: =(Q68+S68)/($Q$77+$S$77) -> 0.0048632282 | V68: =V67+U68 -> 0.61048224 | X68: 4 | Y68: =P74 -> Equipos (Laboratorios) | Z68: =Q74 -> 25615.71 | AA68: =S74 -> 0 | AB68: =(Z68+AA68)/($Z$77+$AA$77) -> 0.10298863 | AC68: =AC67+AB68 -> 0.7524617 | AO68: =Y68 -> Equipos (Laboratorios) | AP68: =Z68*'Emisiones de GEI'!$D$52/1000 -> 6.1067853 | AQ68: =AA68*'Emisiones de GEI'!$G$53/1000 -> 0 | AR68: =(AP68+AQ68)/($AP$77+$AQ$77) -> 0.098426691 | AS68: =AS67+AR68 -> 0.75854579 | BE68: =AO68 -> Equipos (Laboratorios) | BF68: =AP68+AQ68 -> 6.1067853 | BG68: =BF68/$BF$77 -> 0.098426691 | BH68: =BH67+BG68 -> 0.75854579
F69: =SUM(F65:F68) -> 0.54058202 | L69: =M69/Q59 -> 0.035779464 | M69: =Q69 -> 8899.2 | N69: =R69 -> 0.077879983 | O69: Proceso 03 | P69: Bombas-Motores (Nodriza) | Q69: =L15 -> 8899.2 | R69: =Q69/$Q$77 -> 0.077879983 | T69: =S69/$S$77 -> 0 | U69: =(Q69+S69)/($Q$77+$S$77) -> 0.035779464 | V69: =V68+U69 -> 0.6462617 | W69: =U69 -> 0.035779464 | X69: 5 | Y69: =P66 -> Bombas-Motores (Agua jabonosa y aditivos) | Z69: =Q66 -> 4622.4 | AA69: =S66 -> 14815.119 | AB69: =(Z69+AA69)/($Z$77+$AA$77) -> 0.07814905 | AC69: =AC68+AB69 -> 0.83061075 | AO69: =Y69 -> Bombas-Motores (Agua jabonosa y aditivos) | AP69: =Z69*'Emisiones de GEI'!$D$52/1000 -> 1.1019802 | AQ69: =AA69*'Emisiones de GEI'!$G$53/1000 -> 3.8347454 | AR69: =(AP69+AQ69)/($AP$77+$AQ$77) -> 0.079568144 | AS69: =AS68+AR69 -> 0.83811393 | BE69: =AO69 -> Bombas-Motores (Agua jabonosa y aditivos) | BF69: =AP69+AQ69 -> 4.9367256 | BG69: =BF69/$BF$77 -> 0.079568144 | BH69: =BH68+BG69 -> 0.83811393
L70: =M70/Q59 -> 0.050004542 | M70: =Q70+Q71 -> 12437.314 | N70: =R70+R71 -> 0.10884324 | O70: Sector 01 | P70: Aires Acondicionados (Oficinas) | Q70: =L51 -> 9704.448 | R70: =Q70/$Q$77 -> 0.084926987 | T70: =S70/$S$77 -> 0 | U70: =(Q70+S70)/($Q$77+$S$77) -> 0.039016985 | V70: =V69+U70 -> 0.68527869 | W70: =U70+U71 -> 0.050004542 | X70: 6 | Y70: =P75 -> Varios | Z70: =Q75 -> 9321.734 | AA70: =S72 -> 0 | AB70: =(Z70+AA70)/($Z$77+$AA$77) -> 0.037478273 | AC70: =AC69+AB70 -> 0.86808902 | AO70: =Y70 -> Varios | AP70: =Z70*'Emisiones de GEI'!$D$52/1000 -> 2.2223014 | AQ70: =AA70*'Emisiones de GEI'!$G$53/1000 -> 0 | AR70: =(AP70+AQ70)/($AP$77+$AQ$77) -> 0.035818154 | AS70: =AS69+AR70 -> 0.87393209 | BE70: =AO70 -> Varios | BF70: =AP70+AQ70 -> 2.2223014 | BG70: =BF70/$BF$77 -> 0.035818154 | BH70: =BH69+BG70 -> 0.87393209
P71: Luminarias (Oficinas) | Q71: =L87 -> 2732.8656 | R71: =Q71/$Q$77 -> 0.023916254 | T71: =S71/$S$77 -> 0 | U71: =(Q71+S71)/($Q$77+$S$77) -> 0.010987557 | V71: =V70+U71 -> 0.69626625 | X71: 7 | Y71: =P73 -> Luminarias (Laboratorios) | Z71: =Q73 -> 10263.27 | AA71: =S73 -> 0 | AB71: =(Z71+AA71)/($Z$77+$AA$77) -> 0.041263743 | AC71: =AC70+AB71 -> 0.90935277 | AO71: =Y71 -> Luminarias (Laboratorios) | AP71: =Z71*'Emisiones de GEI'!$D$52/1000 -> 2.4467636 | AQ71: =AA71*'Emisiones de GEI'!$G$53/1000 -> 0 | AR71: =(AP71+AQ71)/($AP$77+$AQ$77) -> 0.039435944 | AS71: =AS70+AR71 -> 0.91336803 | BE71: =AO71 -> Luminarias (Laboratorios) | BF71: =AP71+AQ71 -> 2.4467636 | BG71: =BF71/$BF$77 -> 0.039435944 | BH71: =BH70+BG71 -> 0.91336803
G72: Total USEs | H72: =F65+F66+L66+L69+L70+L72 -> 0.96252173 | L72: =M72/Q59 -> 0.26625548 | M72: =Q72+Q73+Q74 -> 66224.042 | N72: =R72+R73+R74 -> 0.57954954 | O72: Sector 02 | P72: Aires Acondicionados (Laboratorios) | Q72: =L48 -> 30345.062 | R72: =Q72/$Q$77 -> 0.26556016 | T72: =S72/$S$77 -> 0 | U72: =(Q72+S72)/($Q$77+$S$77) -> 0.12200311 | V72: =V71+U72 -> 0.81826936 | W72: =U72+U73+U74 -> 0.26625548 | X72: 8 | Y72: =P70 -> Aires Acondicionados (Oficinas) | Z72: =Q70 -> 9704.448 | AA72: =S70 -> 0 | AB72: =(Z72+AA72)/($Z$77+$AA$77) -> 0.039016985 | AC72: =AC71+AB72 -> 0.94836975 | AO72: =Y72 -> Aires Acondicionados (Oficinas) | AP72: =Z72*'Emisiones de GEI'!$D$52/1000 -> 2.3135404 | AQ72: =AA72*'Emisiones de GEI'!$G$53/1000 -> 0 | AR72: =(AP72+AQ72)/($AP$77+$AQ$77) -> 0.037288707 | AS72: =AS71+AR72 -> 0.95065674 | BE72: =AO72 -> Aires Acondicionados (Oficinas) | BF72: =AP72+AQ72 -> 2.3135404 | BG72: =BF72/$BF$77 -> 0.037288707 | BH72: =BH71+BG72 -> 0.95065674
G73: Otros | H73: =Q75/Q59 -> 0.037478273 | P73: Luminarias (Laboratorios) | Q73: =L80 -> 10263.27 | R73: =Q73/$Q$77 -> 0.089817432 | T73: =S73/$S$77 -> 0 | U73: =(Q73+S73)/($Q$77+$S$77) -> 0.041263743 | V73: =V72+U73 -> 0.8595331 | X73: 9 | Y73: =P69 -> Bombas-Motores (Nodriza) | Z73: =Q69 -> 8899.2 | AA73: =S69 -> 0 | AB73: =(Z73+AA73)/($Z$77+$AA$77) -> 0.035779464 | AC73: =AC72+AB73 -> 0.98414921 | AO73: =Y73 -> Bombas-Motores (Nodriza) | AP73: =Z73*'Emisiones de GEI'!$D$52/1000 -> 2.1215693 | AQ73: =AA73*'Emisiones de GEI'!$G$53/1000 -> 0 | AR73: =(AP73+AQ73)/($AP$77+$AQ$77) -> 0.034194594 | AS73: =AS72+AR73 -> 0.98485133 | BE73: =AO73 -> Bombas-Motores (Nodriza) | BF73: =AP73+AQ73 -> 2.1215693 | BG73: =BF73/$BF$77 -> 0.034194594 | BH73: =BH72+BG73 -> 0.98485133
G74: Total-Total | H74: =SUM(H72:H73) -> 1 | P74: Equipos (Laboratorios) | Q74: =L115 -> 25615.71 | R74: =Q74/$Q$77 -> 0.22417195 | T74: =S74/$S$77 -> 0 | U74: =(Q74+S74)/($Q$77+$S$77) -> 0.10298863 | V74: =V73+U74 -> 0.96252173 | X74: 10 | Y74: =P71 -> Luminarias (Oficinas) | Z74: =Q71 -> 2732.8656 | AA74: =S71 -> 0 | AB74: =(Z74+AA74)/($Z$77+$AA$77) -> 0.010987557 | AC74: =AC73+AB74 -> 0.99513677 | AO74: =Y74 -> Luminarias (Oficinas) | AP74: =Z74*'Emisiones de GEI'!$D$52/1000 -> 0.65151516 | AQ74: =AA74*'Emisiones de GEI'!$G$53/1000 -> 0 | AR74: =(AP74+AQ74)/($AP$77+$AQ$77) -> 0.010500857 | AS74: =AS73+AR74 -> 0.99535219 | BE74: =AO74 -> Luminarias (Oficinas) | BF74: =AP74+AQ74 -> 0.65151516 | BG74: =BF74/$BF$77 -> 0.010500857 | BH74: =BH73+BG74 -> 0.99535219
L75: =SUM(L66:L74) -> 0.42193971 | O75: Otros | P75: Varios | Q75: =S45 -> 9321.734 | R75: =Q75/$Q$77 -> 0.081577724 | T75: =S75/$S$77 -> 0 | U75: =(Q75+S75)/($Q$77+$S$77) -> 0.037478273 | V75: =V74+U75 -> 1 | W75: =U75 -> 0.037478273 | X75: 11 | Y75: =P68 -> Bomba (Almacenamiento) | Z75: =Q68 -> 1209.6 | AA75: =S68 -> 0 | AB75: =(Z75+AA75)/($Z$77+$AA$77) -> 0.0048632282 | AC75: =AC74+AB75 -> 1 | AO75: =Y75 -> Bomba (Almacenamiento) | AP75: =Z75*'Emisiones de GEI'!$D$52/1000 -> 0.28836864 | AQ75: =AA75*'Emisiones de GEI'!$G$53/1000 -> 0 | AR75: =(AP75+AQ75)/($AP$77+$AQ$77) -> 0.0046478089 | AS75: =AS74+AR75 -> 1 | BE75: =AO75 -> Bomba (Almacenamiento) | BF75: =AP75+AQ75 -> 0.28836864 | BG75: =BF75/$BF$77 -> 0.0046478089 | BH75: =BH74+BG75 -> 1
M76: =F69+L75+H73 -> 1
C77: Inventario de luminarias de la empresa | P77: Total | Q77: =SUM(Q66:Q76) -> 114268.13 | R77: =SUM(R65:R76) -> 1 | S77: =SUM(S65:S73) -> 134455.55 | T77: =SUM(T65:T75) -> 1 | U77: =SUM(U65:U75) -> 1 | V77: =V75 -> 1 | Y77: Total | Z77: =SUM(Z65:Z75) -> 114268.13 | AA77: =SUM(AA65:AA75) -> 134455.55 | AB77: =SUM(AB65:AB75) -> 1 | AC77: =AC75 -> 1 | AO77: Total | AP77: =SUM(AP65:AP75) -> 27.241522 | AQ77: =SUM(AQ65:AQ75) -> 34.802474 | AR77: =SUM(AR65:AR75) -> 1 | AS77: =AS75 -> 1 | BE77: =AO77 -> Total | BF77: =SUM(BF65:BF76) -> 62.043996 | BG77: =SUM(BG65:BG76) -> 1 | BH77: =BH75 -> 1
B79: Área | C79: Tipo | D79: Potencia [W] | E79: Cantidad | F79: Potencia instalada [W] | G79: Uso aproximado (h/día) | H79: Consumo anual [kWh/año] | L79: [Kwh]/año
B80: Oficina Lab de Control | C80: Tubo fluorescente | D80: 32 | E80: 24 | F80: =D80*E80 -> 768 | G80: 9 | H80: =F80*G80*313/1000 -> 2163.456 | I80: ✓ | K80: Sector 02 | L80: =SUM(H80:H86) -> 10263.27
C81: Foco fluorescente | D81: 25 | E81: 1 | F81: =D81*E81 -> 25 | G81: 9 | H81: =F81*G81*313/1000 -> 70.425 | I81: ✓
B82: Exteriores | C82: Foco fluorescente | D82: 25 | E82: 2 | F82: =D82*E82 -> 50 | G82: 6 | H82: =F82*G82*313/1000 -> 93.9 | I82: ✓
C83: Perimetrales | D83: 75 | E83: 2 | F83: =D83*E83 -> 150 | G83: 12 | H83: =F83*G83*313/1000 -> 563.4 | I83: ✓
B84: Lab Suelos | C84: Tubo fluorescente | D84: 32 | E84: 30 | F84: =D84*E84 -> 960 | G84: 9 | H84: =F84*G84*313/1000 -> 2704.32 | I84: ✓
B85: Lab I+D | C85: Tubo fluorescente | D85: 32 | E85: 51 | F85: =D85*E85 -> 1632 | G85: 9 | H85: =F85*G85*313/1000 -> 4597.344 | I85: ✓
C86: Lámpara fluorescente | D86: 25 | E86: 1 | F86: =D86*E86 -> 25 | G86: 9 | H86: =F86*G86*313/1000 -> 70.425 | I86: ✓
B87: Oficinas 1 | C87: Tubo fluorescente | D87: 32 | E87: 8 | F87: =D87*E87 -> 256 | G87: 9 | H87: =F87*G87*313/1000 -> 721.152 | I87: ✓ | K87: Sector 01 | L87: =SUM(H87:H93) -> 2732.8656
B88: Oficinas 2 | C88: Tubo fluorescente | D88: 32 | E88: 12 | F88: =D88*E88 -> 384 | G88: 9 | H88: =F88*G88*313/1000 -> 1081.728 | I88: ✓
B89: Baños | C89: Tubo fluorescente | D89: 32 | E89: 2 | F89: =D89*E89 -> 64 | G89: 1 | H89: =F89*G89*313/1000 -> 20.032 | I89: ✓
B90: Oficinas 3 | C90: Tubo fluorescente | D90: 32 | E90: 3 | F90: =D90*E90 -> 96 | G90: 9 | H90: =F90*G90*313/1000 -> 270.432 | I90: ✓
B91: Pasillo | C91: Tubo fluorescente | D91: 32 | E91: 6 | F91: =D91*E91 -> 192 | G91: 9 | H91: =F91*G91*313/1000 -> 540.864 | I91: ✓
B92: Cocina | C92: Foco fluorescente | D92: 25 | E92: 2 | F92: =D92*E92 -> 50 | G92: 4 | H92: =F92*G92*313/1000 -> 62.6 | I92: ✓
B93: Sala de reuniones | C93: Tubo fluorescente | D93: 32 | E93: 12 | F93: =D93*E93 -> 384 | G93: 0.3 | H93: =F93*G93*313/1000 -> 36.0576 | I93: ✓
B94: Total | E94: =SUM(E80:E93) -> 156 | F94: =SUM(F80:F93) -> 5036 | H94: =SUM(H80:H93) -> 12996.136
G96: Anual | H96: 12996.136
G97: Mensual | H97: =H96/12 -> 1083.0113
C112: Inventario de equipo de laboratorio de mayor uso
B113: Descripción | C113: Capacidad instalada [kW] | D113: Horas de uso /día | E113: [kWh]/día | F113: [kWh]/mes | G113: [kWh]/año
L114: [Kwh]/año
B115: Reómetro | C115: 0.0095 | D115: 3 | E115: =C115*D115 -> 0.0285 | F115: =E115*5 -> 0.1425 | G115: =F115*12 -> 1.71 | H115: ✓ | K115: Sector 02 | L115: =SUM(G115:G118) -> 25615.71
B116: Hornos (5) | C116: 1.92 | D116: 24 | E116: =C116*D116*5 -> 230.4 | F116: =E116*5 -> 1152 | G116: =F116*12 -> 13824 | H116: ✓
B117: RTFO | C117: 1.5 | D117: 3 | E117: =C117*D117 -> 4.5 | F117: =E117*5 -> 22.5 | G117: =F117*12 -> 270 | H117: ✓
B118: Compresor | C118: 12 | D118: 16 | E118: =C118*D118 -> 192 | F118: =E118*5 -> 960 | G118: =F118*12 -> 11520 | H118: ✓
C119: =SUM(C115:C118) -> 15.4295 | E119: =SUM(E115:E118) -> 426.9285 | F119: =SUM(F115:F118) -> 2134.6425 | G119: =SUM(G115:G118) -> 25615.71
F121: 2134.6425 | G121: 25615.71
C126: Inventario de quemadores de queroseno
B127: Área | C127: Descripción | D127: Capacidad de procesamiento gal/hora (placa) | E127: Capacidad de generación de energía kBTU/hora (placa) | F127: Combustible consumido gal/mes | G127: Consumo anual gal/año
N130: [Kwh]/año
B131: Agua jabonosa y aditivos | C131: Quemador kerosene | D131: 1,2 a 5,5 | E131: 175 a 170 | F131: ='Balance Térmico'!G76 -> 31.633869 | G131: =F131*12 -> 379.60643 | H131: =G131 -> 379.60643 | I131: Dato identificado en Balance térmico; Calentamiento de Agua | M131: Proceso 02 | N131: =G131*'Consumo Térmico de la empresa'!$B$5*10.31 -> 14815.119
B133: Almacenamiento y recirculación de asfalto | C133: Quemador kerosene | D133: 1,2 a 5,5 | E133: 175 a 170 | F133: ='Balance Térmico'!G74 -> 105.48043 | G133: =F133*12 -> 1265.7651 | H133: =G133+G135 -> 1265.7651 | I133: Dato identificado en Balance térmico; Calentamiento Asfalto | L133: =IF(H133>H137,"Mayor","-") -> - | M133: Proceso 01 | N133: =G133*'Consumo Térmico de la empresa'!$B$5*10.31 -> 49399.746
C135: Quemador kerosene | D135: 1,2 a 5,5 | E135: 175 a 170
B137: Emulsión | C137: Quemador kerosene (recirculación aceite térmico) | D137: 1,2 a 5,5 | E137: 175 a 170 | F137: ='Balance Térmico'!G75 -> 149.98088 | G137: =F137*12 -> 1799.7705 | H137: =G137+G139 -> 1799.7705 | I137: Dato identificado en Balance térmico; Calentamiento Aceite Térmico | L137: =IF(H137>H133,"Mayor","-") -> Mayor | M137: Proceso 02 | N137: =G137*'Consumo Térmico de la empresa'!$B$5*10.31 -> 70240.683
C139: Quemador kerosene (caldera aceite térmico) | D139: 1,2 a 5,5 | E139: 175 a 170
B141: Total | F141: =SUM(F131:F140) -> 287.09517 | G141: =SUM(G131:G140) -> 3445.1421 | N141: =G141*'Consumo Térmico de la empresa'!B5*10.31 -> 134455.55
F143: 287.09517 | G143: 3445.1421

Sheet Balance Energético
B4: USE´s | C4: Nomenclatura USE´s | D4: Electricidad | E4: Combustible | I4: =C5 -> Proc-01 (Quem) | J4: =C6 -> Proc-02 (Mot A J) | K4: =C7 -> Proc-02 (Mot E) | L4: =C8 -> Proc-02 (BB Alm) | M4: =C9 -> Proc-03 (BBs y Mots Nod) | N4: =C10 -> Sect_01 (AA Of) | O4: =C11 -> Sect_01 (Lum Of) | P4: =C12 -> Sect_02 (AA Of) | Q4: =C13 -> Sect_02 (Lum Of) | R4: =C14 -> Sect_02 (Eq Lab) | S4: =C15 -> Varios
B5: Proc-01 Quemadores | C5: Proc-01 (Quem) | D5: =Pareto!R65 -> 0 | E5: =Pareto!T65 -> 0.36740578 | F5: =(D5+E5)/2 -> 0.18370289 | H5: Electricidad | I5: =D5 -> 0 | J5: =D6 -> 0.040452224 | K5: =D7 -> 0.10111166 | L5: =D8 -> 0.010585629 | M5: =D9 -> 0.077879983 | N5: =D10 -> 0.084926987 | O5: =D11 -> 0.023916254 | P5: =D12 -> 0.26556016 | Q5: =D13 -> 0.089817432 | R5: =D14 -> 0.22417195 | S5: =D15 -> 0.081577724 | T5: =SUM(I5:S5) -> 1
B6: Proc-02 (Motores Agua jabonosa) | C6: Proc-02 (Mot A J) | D6: =Pareto!R66 -> 0.040452224 | E6: =Pareto!T66 -> 0.110186 | F6: =(D6+E6)/2 -> 0.075319113 | H6: Combustible | I6: =E5 -> 0.36740578 | J6: =E6 -> 0.110186 | K6: =E7 -> 0.52240821 | L6: =E8 -> 0 | M6: =E9 -> 0 | N6: =E10 -> 0 | O6: =E11 -> 0 | P6: =E12 -> 0 | Q6: =E13 -> 0 | R6: =E14 -> 0 | S6: =E15 -> 0 | T6: =SUM(I6:S6) -> 1
B7: Proc-02 (Motores Emulsión) | C7: Proc-02 (Mot E) | D7: =Pareto!R67 -> 0.10111166 | E7: =Pareto!T67 -> 0.52240821 | F7: =(D7+E7)/2 -> 0.31175994 | H7: Totales | I7: =SUM(I5:I6) -> 0.36740578 | J7: =SUM(J5:J6) -> 0.15063823 | K7: =SUM(K5:K6) -> 0.62351987 | L7: =SUM(L5:L6) -> 0.010585629 | M7: =SUM(M5:M6) -> 0.077879983 | N7: =SUM(N5:N6) -> 0.084926987 | O7: =SUM(O5:O6) -> 0.023916254 | P7: =SUM(P5:P6) -> 0.26556016 | ... S7: =SUM(S5:S6) -> 0.081577724 | T7: =SUM(I7:S7) -> 2
B8: Proc-02 (Bomba Almacenamiento) | C8: Proc-02 (BB Alm) | D8: =Pareto!R68 -> 0.010585629 | E8: =Pareto!T68 -> 0 | F8: =(D8+E8)/2 -> 0.0052928144 | I8: =I7/$T$7 -> 0.18370289 | J8: =J7/$T$7 -> 0.075319113 | K8: =K7/$T$7 -> 0.31175994 | L8: =L7/$T$7 -> 0.0052928144 | M8: =M7/$T$7 -> 0.038939991 | N8: =N7/$T$7 -> 0.042463494 | O8: =O7/$T$7 -> 0.011958127 | P8: =P7/$T$7 -> 0.13278008 | ... T8: =T7/$T$7 -> 1
B9: Proc-03 (Bombas y Motores Nodriza) | C9: Proc-03 (BBs y Mots Nod) | D9: =Pareto!R69 -> 0.077879983 | E9: =Pareto!T69 -> 0 | F9: =(D9+E9)/2 -> 0.038939991
B10: Sect_01 (AA Oficinas) | C10: Sect_01 (AA Of) | D10: =Pareto!R70 -> 0.084926987 | E10: =Pareto!T70 -> 0 | F10: =(D10+E10)/2 -> 0.042463494 | H10: Total | I10: =I8+J8+K8+P8+R8 -> 0.815648
B11: Sect_01 (Luminarias Oficinas) | C11: Sect_01 (Lum Of) | D11: =Pareto!R71 -> 0.023916254 | E11: =Pareto!T71 -> 0 | F11: =(D11+E11)/2 -> 0.011958127
B12: Sect_02 (AA Oficinas) | C12: Sect_02 (AA Of) | D12: =Pareto!R72 -> 0.26556016 | E12: =Pareto!T72 -> 0 | F12: =(D12+E12)/2 -> 0.13278008
B13: Sect_02 (Luminarias Oficinas) | C13: Sect_02 (Lum Of) | D13: =Pareto!R73 -> 0.089817432 | E13: =Pareto!T73 -> 0 | F13: =(D13+E13)/2 -> 0.044908716
B14: Sect_02 (Equipos Laboratorios) | C14: Sect_02 (Eq Lab) | D14: =Pareto!R74 -> 0.22417195 | E14: =Pareto!T74 -> 0 | F14: =(D14+E14)/2 -> 0.11208598
B15: Varios | C15: Varios | D15: =Pareto!R75 -> 0.081577724 | E15: =Pareto!T75 -> 0 | F15: =(D15+E15)/2 -> 0.040788862
C17: Total | D17: =SUM(D5:D15) -> 1 | E17: =SUM(E5:E15) -> 1 | F17: =SUM(F5:F15) -> 1
B23: =B5 -> Proc-01 Quemadores | E23: =E5 -> 0.36740578
B24: =B7 -> Proc-02 (Motores Emulsión) | E24: =E7 -> 0.52240821
E25: =SUM(E23:E24) -> 0.889814

Sheet Balance Térmico
B2: Historia de consumo de combustible y energía de la empresa 2022 | N2: Historia de consumo de combustible y energía de la empresa 2023
B4: Mes | C4: Kerosene [gal] | D4: Total Energía [GJ] | N4: Mes | O4: Kerosene [gal] | P4: Total Energía [GJ]
B5: ='Consumo Térmico de la empresa'!B25 -> 44562 | C5: ='Consumo Térmico de la empresa'!C25 -> 176.702 | D5: ='Consumo Térmico de la empresa'!D25 -> 24.826631 | N5: ='Consumo Térmico de la empresa'!B56 -> 44927 | O5: ='Consumo Térmico de la empresa'!C56 -> 165.03 | P5: ='Consumo Térmico de la empresa'!D56 -> 23.186715
B6: ='Consumo Térmico de la empresa'!B26 -> 44593 | C6: ='Consumo Térmico de la empresa'!C26 -> 229.2886 | D6: ='Consumo Térmico de la empresa'!D26 -> 32.215048 | N6: ='Consumo Térmico de la empresa'!B57 -> 44958 | O6: ='Consumo Térmico de la empresa'!C57 -> 224.9624 | P6: ='Consumo Térmico de la empresa'!D57 -> 31.607217
B7: ='Consumo Térmico de la empresa'!B27 -> 44621 | C7: ='Consumo Térmico de la empresa'!C27 -> 239.4646 | D7: ='Consumo Térmico de la empresa'!D27 -> 33.644776 | N7: ='Consumo Térmico de la empresa'!B58 -> 44986 | O7: ='Consumo Térmico de la empresa'!C58 -> 234.9464 | P7: ='Consumo Térmico de la empresa'!D58 -> 33.009969
B8: ='Consumo Térmico de la empresa'!B28 -> 44652 | C8: ='Consumo Térmico de la empresa'!C28 -> 422.1238 | D8: ='Consumo Térmico de la empresa'!D28 -> 59.308394 | N8: ='Consumo Térmico de la empresa'!B59 -> 45017 | O8: ='Consumo Térmico de la empresa'!C59 -> 414.1592 | P8: ='Consumo Térmico de la empresa'!D59 -> 58.189368
B9: ='Consumo Térmico de la empresa'!B29 -> 44682 | C9: ='Consumo Térmico de la empresa'!C29 -> 396.8852 | D9: ='Consumo Térmico de la empresa'!D29 -> 55.762371 | N9: ='Consumo Térmico de la empresa'!B60 -> 45047 | O9: ='Consumo Térmico de la empresa'!C60 -> 363.1874 | P9: ='Consumo Térmico de la empresa'!D60 -> 51.02783
B10: ='Consumo Térmico de la empresa'!B30 -> 44713 | C10: ='Consumo Térmico de la empresa'!C30 -> 401.7506 | D10: ='Consumo Térmico de la empresa'!D30 -> 56.445959 | N10: ='Consumo Térmico de la empresa'!B61 -> 45078 | O10: ='Consumo Térmico de la empresa'!C61 -> 352.4793 | P10: ='Consumo Térmico de la empresa'!D61 -> 49.523342
B11: ='Consumo Térmico de la empresa'!B31 -> 44743 | C11: ='Consumo Térmico de la empresa'!C31 -> 381.07 | D11: ='Consumo Térmico de la empresa'!D31 -> 53.540335 | N11: ='Consumo Térmico de la empresa'!B62 -> 45108 | O11: ='Consumo Térmico de la empresa'!C62 -> 366.69 | P11: ='Consumo Térmico de la empresa'!D62 -> 51.519945
B12: ='Consumo Térmico de la empresa'!B32 -> 44774 | C12: ='Consumo Térmico de la empresa'!C32 -> 405.0578 | D12: ='Consumo Térmico de la empresa'!D32 -> 56.910621 | N12: ='Consumo Térmico de la empresa'!B63 -> 45139 | O12: ='Consumo Térmico de la empresa'!C63 -> 389.7726 | P12: ='Consumo Térmico de la empresa'!D63 -> 54.76305
B13: ='Consumo Térmico de la empresa'!B33 -> 44805 | C13: ='Consumo Térmico de la empresa'!C33 -> 173.5856 | D13: ='Consumo Térmico de la empresa'!D33 -> 24.388777 | N13: ='Consumo Térmico de la empresa'!B64 -> 45170 | O13: ='Consumo Térmico de la empresa'!C64 -> 167.0352 | P13: ='Consumo Térmico de la empresa'!D64 -> 23.468446
B14: ='Consumo Térmico de la empresa'!B34 -> 44835 | C14: ='Consumo Térmico de la empresa'!C34 -> 172.45 | D14: ='Consumo Térmico de la empresa'!D34 -> 24.229225 | N14: ='Consumo Térmico de la empresa'!B65 -> 45200 | O14: ='Consumo Térmico de la empresa'!C65 -> 165.54 | P14: ='Consumo Térmico de la empresa'!D65 -> 23.25837
B15: ='Consumo Térmico de la empresa'!B35 -> 44866 | C15: ='Consumo Térmico de la empresa'!C35 -> 330.9002 | D15: ='Consumo Térmico de la empresa'!D35 -> 46.491478 | N15: ='Consumo Térmico de la empresa'!B66 -> 45231 | O15: ='Consumo Térmico de la empresa'!C66 -> 318.4134 | P15: ='Consumo Térmico de la empresa'!D66 -> 44.737083
B16: ='Consumo Térmico de la empresa'!B36 -> 44896 | C16: ='Consumo Térmico de la empresa'!C36 -> 115.911 | D16: ='Consumo Térmico de la empresa'!D36 -> 16.285496 | N16: ='Consumo Térmico de la empresa'!B67 -> 45261 | O16: ='Consumo Térmico de la empresa'!C67 -> 111.537 | P16: ='Consumo Térmico de la empresa'!D67 -> 15.670948
B17: Media Consumo mes | C17: =AVERAGE(C5:C16) -> 287.09912 | D17: =AVERAGE(D5:D16) -> 40.337426 | N17: Media Consumo mes | O17: =AVERAGE(O5:O16) -> 272.81274 | P17: =AVERAGE(P5:P16) -> 38.33019
B18: Total (anual) 2022 | C18: =SUM(C5:C16) -> 3445.1894 | D18: =SUM(D5:D16) -> 484.04911 | N18: Total (anual) 2022 | O18: =SUM(O5:O16) -> 3273.7529 | P18: =SUM(P5:P16) -> 459.96228
B21: Energía total mensual requerida por el proceso | N21: Energía total mensual requerida por el proceso
B23: Descripción | C23: Valor | D23: Unidades | N23: Descripción | O23: Valor | P23: Unidades
B24: Densidad Kerosene | C24: 3.03 | D24: [kg/gal] | G24: Asfalto (gal) | N24: Densidad Kerosene | O24: 3 | P24: [kg/gal] | S24: Asfalto (gal)
B25: Poder calorífico | C25: 46369 | D25: [kJ/kg] | F25: =C36/C41 -> 616.22807 | N25: Poder calorífico | O25: 46369 | P25: [kJ/kg] | R25: =O36/O41 -> 616.22807
B26: Media consumo Kerosene | C26: =C17 -> 287.09912 | D26: [gal/mes] | G26: 220401.1 | H26: =G26/1000/C26 -> 0.76768296 | N26: Media consumo Kerosene | O26: =O17 -> 272.81274 | P26: [gal/mes] | S26: 214210.6 | T26: =S26/1000/O26 -> 0.7851928
B27: Total Energía mensual | C27: =(C26*C25*C24)/1000000 -> 40.336872 | D27: [GJ] | N27: Total Energía mensual | O27: =(O26*O25*O24)/1000000 -> 37.950162 | P27: [GJ]
B31: Energía total mensual requerida para calentamiento de asfalto | N31: Energía total mensual requerida para calentamiento de asfalto
B33: Descripción | C33: Valor | D33: Unidades | N33: Descripción | O33: Valor | P33: Unidades
B34: Energía para calentar asfalto | C34: =C36*C37*(C40-C39) -> 14820000 | D34: [KJ/mes] | N34: Energía para calentar asfalto | O34: =O36*O37*(O40-O39) -> 14478000 | P34: [KJ/mes]
C35: =C34/1000000 -> 14.82 | D35: [GJ/mes] | O35: =O34/1000000 -> 14.478 | P35: [GJ/mes]
B36: Cantidad de asfalto mensual | C36: 65000 | D36: [gal/mes] | J36: =C36 -> 65000 | K36: =O36 -> 63500 | N36: Cantidad de asfalto mensual | O36: 63500 | P36: [gal/mes]
B37: Capacidad calórica del asfalto | C37: 1.9 | D37: [kJ/kg] °C | J37: =C35 -> 14.82 | K37: =O35 -> 14.478 | N37: Capacidad calórica del asfalto | O37: 1.9 | P37: [kJ/kg] °C
B38: Densidad del asfalto | C38: 3.5 | D38: [kg/galón] | H38: Q= Energía requerida [Gj] | N38: Densidad del asfalto | O38: 3.5 | P38: [kg/galón]
B39: Temperatura inicial | C39: 25 | D39: °C | H39: m= Masa del asfalto [kg] | N39: Temperatura inicial | O39: 25 | P39: °C
B40: Temperatura final | C40: 145 | D40: °C | H40: Cp= Capacidad calórifica del asfalto [kJ/kg°C] | N40: Temperatura final | O40: 145 | P40: °C
B41: Cantidad de combustible | C41: =G74 -> 105.48043 | D41: [gal/mes] | H41: ▲T= Delta de temperatura [°C] | N41: Cantidad de combustible | O41: =S74 -> 103.04626 | P41: [gal/mes]
B42: Porcentaje de combustible | C42: =D74 -> 0.36740578 | N42: Porcentaje de combustible | O42: 0.44
B46: Energía total mensual requerida para calentamiento de agua | N46: Energía total mensual requerida para calentamiento de agua
I47: Q= | J47: =J36*C37*(C40-C39)/1000000 -> 14.82 | K47: [GJ/mes]
B48: Descripción | C48: Valor | D48: Unidades | N48: Descripción | O48: Valor | P48: Unidades
B49: Energía para calentar agua | C49: =C51*C52*(C55-C54) -> 4444558.6 | D49: [KJ/mes] | N49: Energía para calentar agua | O49: =O51*O52*(O55-O54) -> 4444558.6 | P49: [KJ/mes]
C50: =C49/1000000 -> 4.4445586 | D50: [GJ/mes] | O50: =O49/1000000 -> 4.4445586 | P50: [GJ/mes]
B51: Cantidad de agua mensual | C51: 42491 | D51: [kg/mes] | N51: Cantidad de agua mensual | O51: 42491 | P51: [gal/mes]
B52: Capacidad calórica del agua | C52: 4.184 | D52: [kJ/kg] °C | N52: Capacidad calórica del agua | O52: 4.184 | P52: [kJ/kg] °C
B53: Densidad del agua | C53: 3.8 | D53: [kg/galón] | N53: Densidad del agua | O53: 3.8 | P53: [kg/galón]
B54: Temperatura inicial | C54: 25 | D54: °C | N54: Temperatura inicial | O54: 25 | P54: °C
B55: Temperatura final | C55: 50 | D55: °C | N55: Temperatura final | O55: 50 | P55: °C
B56: Cantidad de combustible | C56: =G76 -> 31.633869 | D56: [kg/mes] | N56: Cantidad de combustible | O56: =S76 -> 31.633869 | P56: [kg/mes]
B57: Porcentaje de combustible | C57: =D76 -> 0.110186 | N57: Porcentaje de combustible | O57: 0.13
B61: Energía total mensual requerida para calentamiento de aceite térmico | N61: Energía total mensual requerida para calentamiento de aceite térmico
B63: Descripción | C63: Valor | D63: Unidades | N63: Descripción | O63: Valor | P63: Unidades
B64: Energía para calentar aceite térmico | C64: =C27-C50-C35 -> 21.072313 | D64: [GJ/mes] | N64: Energía para calentar aceite térmico | O64: =O27-O50-O35 -> 19.027603 | P64: [GJ/mes]
C65: =C64*1000000 -> 21072313 | D65: [KJ/mes] | O65: =O64*1000000 -> 19027603 | P65: [KJ/mes]
B66: Cantidad de combustible | C66: =G75 -> 149.98088 | D66: [gal/mes] | N66: Cantidad de combustible | O66: =S75 -> 135.42778 | P66: [gal/mes]
B67: Porcentaje de combustible | C67: =D75 -> 0.52240821 | N67: Porcentaje de combustible | O67: 0.13
B71: Distribución de consumo de kerosene 2022 | N71: Distribución de consumo de kerosene 2023
F72: real
B73: Distribución | C73: gal kerosene/año | D73: Porcentaje | E73: [GJ/año] | F73: Porcentaje | G73: [gal/mes] | H73: [GJ/mes] | N73: Distribución | O73: gal kerosene/año | P73: Porcentaje | Q73: [GJ/año] | R73: Porcentaje | S73: [gal/mes] | T73: [GJ/mes]
B74: Calentamiento de asfalto | C74: =G74*12 -> 1265.7651 | D74: =C74/$C$77 -> 0.36740578 | E74: =H74*12 -> 177.84 | F74: =E74/$E$77 -> 0.36740578 | G74: =H74/'Consumo Térmico de la empresa'!$O$8 -> 105.48043 | H74: =C35 -> 14.82 | N74: Calentamiento de asfalto | O74: =S74*12 -> 1236.5552 | P74: =O74/$O$77 -> 0.38150035 | Q74: =T74*12 -> 173.736 | R74: =Q74/$Q$77 -> 0.38150035 | S74: =T74/'Consumo Térmico de la empresa'!$O$8 -> 103.04626 | T74: =O35 -> 14.478
B75: Calentamiento aceite térmico | C75: =G75*12 -> 1799.7705 | D75: =C75/$C$77 -> 0.52240821 | E75: =H75*12 -> 252.86776 | F75: =E75/$E$77 -> 0.52240821 | G75: =H75/'Consumo Térmico de la empresa'!$O$8 -> 149.98088 | H75: =C64 -> 21.072313 | N75: Calentamiento aceite térmico | O75: =S75*12 -> 1625.1334 | P75: =O75/$O$77 -> 0.50138398 | Q75: =T75*12 -> 228.33124 | R75: =Q75/$Q$77 -> 0.50138398 | S75: =T75/'Consumo Térmico de la empresa'!$O$8 -> 135.42778 | T75: =O64 -> 19.027603
B76: Calentamiento de agua | C76: =G76*12 -> 379.60643 | D76: =C76/$C$77 -> 0.110186 | E76: =H76*12 -> 53.334703 | F76: =E76/$E$77 -> 0.110186 | G76: =H76/'Consumo Térmico de la empresa'!$O$8 -> 31.633869 | H76: =C50 -> 4.4445586 | N76: Calentamiento de agua | O76: =S76*12 -> 379.60643 | P76: =O76/$O$77 -> 0.11711567 | Q76: =T76*12 -> 53.334703 | R76: =Q76/$Q$77 -> 0.11711567 | S76: =T76/'Consumo Térmico de la empresa'!$O$8 -> 31.633869 | T76: =O50 -> 4.4445586
B77: Total | C77: =SUM(C74:C76) -> 3445.1421 | D77: =SUM(D74:D76) -> 1 | E77: =SUM(E74:E76) -> 484.04246 | F77: =E77/$E$77 -> 1 | G77: =SUM(G74:G76) -> 287.09517 | H77: =SUM(H74:H76) -> 40.336872 | N77: Total | O77: =SUM(O74:O76) -> 3241.295 | P77: =SUM(P74:P76) -> 1 | Q77: =SUM(Q74:Q76) -> 455.40194 | R77: =Q77/$E$77 -> 0.94083057 | S77: =SUM(S74:S76) -> 270.10791 | T77: =SUM(T74:T76) -> 37.950162

Sheet Balance Eléctrico
B2: Balance eléctrico de la planta | K2: Balance eléctrico de la planta
B4: Consumidor | C4: Consumo mensual [kWh/mes] - 2022 | D4: % | K4: Consumidor | L4: Consumo mensual [kWh/mes] -2023 | M4: %
A6: ✓ | B6: Nodriza | C6: =SUM(Cuantificador!H15:H23) -> 741.6 | D6: =C6/$C$12 -> 0.077879983 | J6: ✓ | K6: Nodriza | L6: =SUM(Cuantificador!W15:W23) -> 741.6 | M6: =L6/$L$12 -> 0.077879983
A7: ✓ | B7: Emulsiones | C7: =SUM(Cuantificador!H11:H13)+SUM(Cuantificador!H4:H10)+Cuantificador!H34+Cuantificador!H14 -> 1448.82 | D7: =C7/$C$12 -> 0.15214951 | J7: ✓ | K7: Emulsiones | L7: =SUM(Cuantificador!W11:W13)+SUM(Cuantificador!W4:W10)+Cuantificador!W34+Cuantificador!H14 -> 1448.82 | M7: =L7/$L$12 -> 0.15214951
A8: ✓ | B8: Aires acondicionados | C8: =SUM(Cuantificador!I40:I46)/12 -> 3337.4592 | D8: =C8/$C$12 -> 0.35048714 | J8: ✓ | K8: Aires acondicionados | L8: =SUM(Cuantificador!X40:X46)/12 -> 3337.4592 | M8: =L8/$L$12 -> 0.35048714
A9: ✓ | B9: Luminarias | C9: =Cuantificador!H84/12 -> 1083.0113 | D9: =C9/$C$12 -> 0.11373369 | J9: ✓ | K9: Luminarias | L9: =Cuantificador!H84/12 -> 1083.0113 | M9: =L9/$L$12 -> 0.11373369
A10: ✓ | B10: Equipos de laboratorio | C10: =Cuantificador!G109/12 -> 2134.6425 | D10: =C10/$C$12 -> 0.22417195 | J10: ✓ | K10: Equipos de laboratorio | L10: =Cuantificador!V109/12 -> 2134.6425 | M10: =L10/$L$12 -> 0.22417195
A11: ✓ | B11: Otros | C11: =Pareto!S46 -> 776.81117 | D11: =C11/$C$12 -> 0.081577724 | J11: ✓ | K11: Otros | L11: =C11 -> 776.81117 | M11: =L11/$L$12 -> 0.081577724
B12: Consumo ref. factura | C12: =SUM(C6:C11) -> 9522.3442 | D12: =SUM(D6:D11) -> 1 | K12: Consumo ref. factura | L12: =SUM(L6:L11) -> 9522.3442 | M12: =SUM(M6:M11) -> 1

Sheet Balance de Materia
B2: Emulsión asfáltica | K2: Emulsión asfáltica
B3: Volúmenes de composición anual de emulsión asfáltica | K3: Volúmenes de composición anual de emulsión asfáltica
B4: Producción total anual (gal) | C4: Asfalto (gal) | D4: Agua (gal) | E4: Otros (gal) | K4: Producción total anual (gal) | L4: Asfalto (gal) | M4: Agua (gal) | N4: Otros (gal)
B6: =SUM(C6:E6) -> 364057.1 | C6: 220401.1 | D6: 134701.1 | E6: 8954.9 | K6: =SUM(L6:N6) -> 355724.55 | L6: 214210.6 | M6: 132810.57 | N6: 8703.3799
C9: Agua | L9: Agua
C10: =D6/B6 -> 0.36999993 | L10: =M6/K6 -> 0.37335228
B15: Asfalto | K15: Asfalto
B16: =C6/B6 -> 0.60540256 | F16: Emulsión | K16: =L6/K6 -> 0.60218109 | O16: Emulsión
F17: =B16+C10+C26 -> 1 | O17: =K16+L10+L26 -> 1
C25: Otros | L25: Otros
C26: =E6/B6 -> 0.024597515 | L26: =N6/K6 -> 0.024466627
B30: Mezcla asfáltica en frío | K30: Mezcla asfáltica en frío
B31: Volúmenes de composición anual de emulsión asfáltica | K31: Volúmenes de composición anual de emulsión asfáltica
B32: Producción total anual (gal) | C32: Grava(kg) | D32: Asfalto (gal) | E32: Agua (gal) | F32: Otros (gal) | K32: Producción total anual (gal) | L32: Grava(kg) | M32: Asfalto (gal) | N32: Agua (gal) | O32: Otros (gal)
B34: 5489733.2 | C34: 1932877.3 | D34: 411620.3 | E34: 77447.1 | F34: 3067788.4 | K34: 5489733.2 | L34: 1932877.3 | M34: 411620.3 | N34: 77447.1 | O34: 3067788.4

Sheet Propuesta de Mejora
B2: Propuestas
C4: Cambios
C5: Luminarias | D5: Aires acondicionados | E5: Motores | F5: Quemadores | G5: Tuberías
B6: Situación actual | C6: ✓ | D6: ✓ | E6: ✓ | F6: ✓ | G6: ✓
B7: Situación propuesta | D7: ✓ | E7: ✓ | F7: ✓ | G7: ✓
B8: Viabilidad técnica | C8: ✓ | D8: ✓ | E8: ✓ | F8: ✓ | G8: ✓
B9: Pérdidas sin aislamiento | G9: ✓
B10: Pérdidas con aislamiento | G10: ✓
B11: Viabilidad económica | C11: ✓ | D11: ✓ | E11: ✓ | F11: ✓ | G11: ✓
B12: Viabilidad ambiental | C12: ✓ | D12: ✓ | E12: ✓ | F12: ✓ | G12: ✓
B17: Luminarias
A18: Ir a Inicio | B18: =B6 -> Situación actual
B19: Convencionales | C19: 150 | D19: =C19/C21 -> 0.96153846
B20: Tecnología LED | C20: 6
B21: Total | C21: =SUM(C19:C20) -> 156
A23: Área | B23: Tipo | C23: Potencia [W] | D23: Cantidad | E23: Potencia instalada [W] | F23: Uso aproximado (h/día) | G23: Consumo anual [kWh/año]
A24: Oficina Lab de Control | B24: Tubo fluorescente | C24: =Cuantificador!D70 -> 32 | D24: =Cuantificador!E70 -> 24 | E24: =C24*D24 -> 768 | F24: =Cuantificador!G70 -> 9 | G24: =E24*F24*313/1000 -> 2163.456
B25: Foco fluorescente | C25: =Cuantificador!D71 -> 25 | D25: =Cuantificador!E71 -> 1 | E25: =C25*D25 -> 25 | F25: =Cuantificador!G71 -> 9 | G25: =E25*F25*313/1000 -> 70.425
A26: Exteriores | B26: Foco fluorescente | C26: =Cuantificador!D72 -> 25 | D26: =Cuantificador!E72 -> 2 | E26: =C26*D26 -> 50 | F26: =Cuantificador!G72 -> 6 | G26: =E26*F26*313/1000 -> 93.9
B27: Perimetrales | C27: =Cuantificador!D73 -> 75 | D27: =Cuantificador!E73 -> 2 | E27: =C27*D27 -> 150 | F27: =Cuantificador!G73 -> 12 | G27: =E27*F27*313/1000 -> 563.4
A28: Lab Suelos | B28: Tubo fluorescente | C28: =Cuantificador!D74 -> 32 | D28: =Cuantificador!E74 -> 30 | E28: =C28*D28 -> 960 | F28: =Cuantificador!G74 -> 9 | G28: =E28*F28*313/1000 -> 2704.32
A29: Lab I+D | B29: Tubo fluorescente | C29: =Cuantificador!D75 -> 32 | D29: =Cuantificador!E75 -> 51 | E29: =C29*D29 -> 1632 | F29: =Cuantificador!G75 -> 9 | G29: =E29*F29*313/1000 -> 4597.344
B30: Lámpara fluorescente | C30: =Cuantificador!D76 -> 25 | D30: =Cuantificador!E76 -> 1 | E30: =C30*D30 -> 25 | F30: =Cuantificador!G76 -> 9 | G30: =E30*F30*313/1000 -> 70.425
A31: Oficinas 1 | B31: Tubo fluorescente | C31: =Cuantificador!D77 -> 32 | D31: =Cuantificador!E77 -> 8 | E31: =C31*D31 -> 256 | F31: =Cuantificador!G77 -> 9 | G31: =E31*F31*313/1000 -> 721.152
A32: Oficinas 2 | B32: Tubo fluorescente | C32: =Cuantificador!D78 -> 32 | D32: =Cuantificador!E78 -> 12 | E32: =C32*D32 -> 384 | F32: =Cuantificador!G78 -> 9 | G32: =E32*F32*313/1000 -> 1081.728
A33: Baños | B33: Tubo fluorescente | C33: =Cuantificador!D79 -> 32 | D33: =Cuantificador!E79 -> 2 | E33: =C33*D33 -> 64 | F33: =Cuantificador!G79 -> 1 | G33: =E33*F33*313/1000 -> 20.032
A34: Oficinas 3 | B34: Tubo fluorescente | C34: =Cuantificador!D80 -> 32 | D34: =Cuantificador!E80 -> 3 | E34: =C34*D34 -> 96 | F34: =Cuantificador!G80 -> 9 | G34: =E34*F34*313/1000 -> 270.432
A35: Pasillo | B35: Tubo fluorescente | C35: =Cuantificador!D81 -> 32 | D35: =Cuantificador!E81 -> 6 | E35: =C35*D35 -> 192 | F35: =Cuantificador!G81 -> 9 | G35: =E35*F35*313/1000 -> 540.864
A36: Cocina | B36: Foco fluorescente | C36: =Cuantificador!D82 -> 25 | D36: =Cuantificador!E82 -> 2 | E36: =C36*D36 -> 50 | F36: =Cuantificador!G82 -> 4 | G36: =E36*F36*313/1000 -> 62.6
A37: Sala de reuniones | B37: Tubo fluorescente | C37: =Cuantificador!D83 -> 32 | D37: =Cuantificador!E83 -> 12 | E37: =C37*D37 -> 384 | F37: =Cuantificador!G83 -> 0.3 | G37: =E37*F37*313/1000 -> 36.0576
A38: Total | D38: =SUM(D24:D37) -> 156 | E38: =SUM(E24:E37) -> 5036 | G38: =SUM(G24:G37) -> 12996.136
A41: Ir a Inicio | B41: =B8 -> Viabilidad técnica
A43: Área | B43: Tipo | C43: Potencia [W] | D43: Cantidad | E43: Potencia instalada [W] | F43: Uso aproximado (h/día) | G43: Nuevo Consumo [kWh/año] | H43: Ahorro [kWh/año]
A44: Oficina Lab de Control | B44: =B20 -> Tecnología LED | C44: 18 | D44: =D24 -> 24 | E44: =C44*D44 -> 432 | F44: =F24 -> 9 | G44: =E44*F44*313/1000 -> 1216.944 | H44: =G24-G44 -> 946.512
B45: Foco fluorescente | C45: =C25 -> 25 | D45: =D25 -> 1 | E45: =C45*D45 -> 25 | F45: =F25 -> 9 | G45: =E45*F45*313/1000 -> 70.425 | H45: =G25-G45 -> 0
A46: Exteriores | B46: Foco fluorescente | C46: =C26 -> 25 | D46: =D26 -> 2 | E46: =C46*D46 -> 50 | F46: =F26 -> 6 | G46: =E46*F46*313/1000 -> 93.9 | H46: =G26-G46 -> 0
B47: Perimetrales | C47: =C27 -> 75 | D47: =D27 -> 2 | E47: =C47*D47 -> 150 | F47: =F27 -> 12 | G47: =E47*F47*313/1000 -> 563.4 | H47: =G27-G47 -> 0
A48: Lab Suelos | B48: =B20 -> Tecnología LED | C48: 18 | D48: =D28 -> 30 | E48: =C48*D48 -> 540 | F48: =F28 -> 9 | G48: =E48*F48*313/1000 -> 1521.18 | H48: =G28-G48 -> 1183.14
A49: Lab I+D | B49: =B20 -> Tecnología LED | C49: 18 | D49: =D29 -> 51 | E49: =C49*D49 -> 918 | F49: =F29 -> 9 | G49: =E49*F49*313/1000 -> 2586.006 | H49: =G29-G49 -> 2011.338
B50: Lámpara fluorescente | C50: =C30 -> 25 | D50: =D30 -> 1 | E50: =C50*D50 -> 25 | F50: =F30 -> 9 | G50: =E50*F50*313/1000 -> 70.425 | H50: =G30-G50 -> 0
A51: Oficinas 1 | B51: =B20 -> Tecnología LED | C51: 18 | D51: =D31 -> 8 | E51: =C51*D51 -> 144 | F51: =F31 -> 9 | G51: =E51*F51*313/1000 -> 405.648 | H51: =G31-G51 -> 315.504
A52: Oficinas 2 | B52: =B20 -> Tecnología LED | C52: 18 | D52: =D32 -> 12 | E52: =C52*D52 -> 216 | F52: =F32 -> 9 | G52: =E52*F52*313/1000 -> 608.472 | H52: =G32-G52 -> 473.256
A53: Baños | B53: =B20 -> Tecnología LED | C53: 18 | D53: =D33 -> 2 | E53: =C53*D53 -> 36 | F53: =F33 -> 1 | G53: =E53*F53*313/1000 -> 11.268 | H53: =G33-G53 -> 8.764
A54: Oficinas 3 | B54: =B20 -> Tecnología LED | C54: 18 | D54: =D34 -> 3 | E54: =C54*D54 -> 54 | F54: =F34 -> 9 | G54: =E54*F54*313/1000 -> 152.118 | H54: =G34-G54 -> 118.314
A55: Pasillo | B55: =B20 -> Tecnología LED | C55: 18 | D55: =D35 -> 6 | E55: =C55*D55 -> 108 | F55: =F35 -> 9 | G55: =E55*F55*313/1000 -> 304.236 | H55: =G35-G55 -> 236.628
A56: Cocina | B56: Foco fluorescente | C56: =C36 -> 25 | D56: =D36 -> 2 | E56: =C56*D56 -> 50 | F56: =F36 -> 4 | G56: =E56*F56*313/1000 -> 62.6 | H56: =G36-G56 -> 0
A57: Sala de reuniones | B57: =B20 -> Tecnología LED | C57: 18 | D57: =D37 -> 12 | E57: =C57*D57 -> 216 | F57: =F37 -> 0.3 | G57: =E57*F57*313/1000 -> 20.2824 | H57: =G37-G57 -> 15.7752
A58: Total | D58: =SUM(D44:D57) -> 156 | E58: =SUM(E44:E57) -> 2964 | G58: =SUM(G44:G57) -> 7686.9044 | H58: =SUM(H44:H57) -> 5309.2312
D59: =D58-D45-D46-D47-D50-D56 -> 148
D60: =D59/D58 -> 0.94871795
A61: Ir a Inicio | B61: =B11 -> Viabilidad económica
B65: Ejemplo Oficina de Control
C72: Beneficio económico = | E72: =D78*H44 -> 372973.05
E73: =E72/980 -> 380.58475 | F73: [US$/año]
B75: https://www.sasipa.cl/tarifas-electricas/
B76: Precio de la energía Chile
D78: 394.05 | E78: Beneficio económico | G78: =D78*H58 -> 2092102.6
G79: =G78/980 -> 2134.7985 | H79: [US$/año]
D81: 101.92 | E81: Beneficio económico | G81: =D78*H58 -> 2092102.6
D82: 225.84 | G82: =G81/980 -> 2134.7985 | H82: [US$/año]
D83: 375.28
B86: Costo Tecnología LED 18 W | C86: 1690 | D86: https://powerenergy.cl/producto/tubo-de-vidrio-t8-120cm-18w-frio
B87: Convencionales a reemplazar | C87: 130
B88: Costo inversión | C88: =C86*C87 -> 219700
B90: Período simple de recuperación | C90: =B88 -> Costo inversión | D90: =C88 -> 219700 | E90: =D90/D91 -> 0.10501397
C91: =E81 -> Beneficio económico | D91: =G81 -> 2092102.6
A94: Ir a Inicio | B94: =B12 -> Viabilidad ambiental
A96: Dato Clave | B96: ='Indicadores Energéticos'!C155 -> 0.2384 | C96: ='Indicadores Energéticos'!D155 -> Ton de CO₂/MWh (factor por emisión de combustible)
B103: Beneficio ambiental = | C103: =(B96*H58)/1000 -> 1.2657207
B106: Resumen viabilidad económica y ambiental | D106: Luminarias
B108: Medida de EE | C108: Luminarias
B109: Propuesta | C109: Cambio por tecnología LED
B110: Consumo actual | C110: =G38 -> 12996.136
B111: Consumo propuesto | C111: =G58 -> 7686.9044
B112: Ahorro | C112: =H58 -> 5309.2312
B113: % de ahorro | C113: =C112/C110 -> 0.40852384
B114: Beneficio ecnómico | C114: =D91 -> 2092102.6 | D114: =C114 -> 2092102.6
B115: Inversión | C115: =D90 -> 219700
B116: PSRI | C116: =E90 -> 0.10501397
B117: Vida útil | C117: 40000
B118: Beneficio ambiental | C118: =C103 -> 1.2657207
B123: Aires Acondicionados
A124: Ir a Inicio | B124: =B6 -> Situación actual
C125: Nr | D125: EER | E125: Unidad de calor
B126: Tipo Central | C126: 2 | D126: =E133 -> 8 | E126: 60000
B127: Mini Split | C127: 4 | D127: =E135 -> 9.2307692 | E127: 12000
B128: Mini Split | C128: 1 | D128: =E132 -> 9.5238095 | E128: 12000
B129: Total | C129: =SUM(C126:C128) -> 7 | E129: =SUM(E126:E128) -> 84000
A131: Área | B131: Tipo | C131: Capacidad [BTU/h] | D131: Potencia [kW] | E131: EER | F131: Horas Semana | G131: Horas año | H131: Consumo anual [kWh/año]
A132: Lab. de Control | B132: =Cuantificador!C40 -> Mini Split | C132: =Cuantificador!D40 -> 12000 | D132: =Cuantificador!E40 -> 1.26 | E132: =Cuantificador!F40 -> 9.5238095 | F132: =Cuantificador!G40 -> 60 | G132: =F132*52 -> 3120 | H132: =Cuantificador!I40 -> 2351.4624
A133: Lab. de Control | B133: =Cuantificador!C41 -> Central | C133: =Cuantificador!D41 -> 60000 | D133: =Cuantificador!E41 -> 7.5 | E133: =Cuantificador!F41 -> 8 | F133: =Cuantificador!G41 -> 60 | G133: =F133*52 -> 3120 | H133: =Cuantificador!I41 -> 13996.8
A134: Lab. de Suelos | B134: =Cuantificador!C42 -> Central | C134: =Cuantificador!D42 -> 60000 | D134: =Cuantificador!E42 -> 7.5 | E134: =Cuantificador!F42 -> 8 | F134: =Cuantificador!G42 -> 60 | G134: =F134*52 -> 3120 | H134: =Cuantificador!I42 -> 13996.8
A135: Oficinas 1 | B135: =Cuantificador!C43 -> Mini Split | C135: =Cuantificador!D43 -> 12000 | D135: =Cuantificador!E43 -> 1.3 | E135: =Cuantificador!F43 -> 9.2307692 | F135: =Cuantificador!G43 -> 60 | G135: =F135*52 -> 3120 | H135: =Cuantificador!I43 -> 2426.112
A136: Oficinas 2 | B136: =Cuantificador!C44 -> Mini Split | C136: =Cuantificador!D44 -> 12000 | D136: =Cuantificador!E44 -> 1.3 | E136: =Cuantificador!F44 -> 9.2307692 | F136: =Cuantificador!G44 -> 60 | G136: =F136*52 -> 3120 | H136: =Cuantificador!I44 -> 2426.112
A137: Oficinas 3 | B137: =Cuantificador!C45 -> Mini Split | C137: =Cuantificador!D45 -> 12000 | D137: =Cuantificador!E45 -> 1.3 | E137: =Cuantificador!F45 -> 9.2307692 | F137: =Cuantificador!G45 -> 60 | G137: =F137*52 -> 3120 | H137: =Cuantificador!I45 -> 2426.112
A138: Sala de reuniones | B138: =Cuantificador!C46 -> Mini Split | C138: =Cuantificador!D46 -> 12000 | D138: =Cuantificador!E46 -> 1.3 | E138: =Cuantificador!F46 -> 9.2307692 | F138: =Cuantificador!G46 -> 60 | G138: =F138*52 -> 3120 | H138: =Cuantificador!I46 -> 2426.112
A139: Total | D139: =SUM(D132:D138) -> 21.46 | F139: =SUM(F132:F138) -> 420 | G139: =SUM(G132:G138) -> 21840 | H139: =SUM(H132:H138) -> 40049.51
A142: Ir a Inicio | B142: =B7 -> Situación propuesta
B143: Sustituir aires acondicionados Mini split por modelos que posean la misma capcidad de enfriamiento, pero con un consumo menor de potencia
B144: Con tecnología más eficiente logrando un ERR de 11
...

Sheet Análisis costos
B2: Parámetros iniciales a considerar en Flujo de Caja
B4: Descricpción | D4: Valor
B5: Tasa de inflación | D5: 0.042
B6: Tasa incremental del costo de energía eléctrica anual | D6: 0.0821
B7: Tasa incremental del costo de kerosene | D7: 0.24
B8: Periodo de análisis | D8: 15 años
B9: Capital propio | D9: 0.8
B10: Premio al riesgo | D10: 0.0525
B11: Capital no propio | D11: 0.2
B12: Tasa activa bancaria | D12: 0.035
B13: TMAR | D13: =D9*(D5+D10)+(D11*D12) -> 0.0826
B17: Costos Energía Eléctrica y Kerosene
B19: Descripción | C19: Precio
B20: Energía Eléctrica | C20: ='Propuesta de Mejora'!D78 -> 394.05
B21: Combustible (Kerosene) | C21: ='Consumo Térmico de la empresa'!D5 -> 4129.8823
B24: Ahorros energéticos
C26: Medidas a implementar | E26: Ahorro por año
B27: Energía Eléctrica | C27: ='Propuesta de Mejora'!D5 -> Aires acondicionados | E27: ='Propuesta de Mejora'!C219 -> 10376.294
C28: ='Propuesta de Mejora'!C5 -> Luminarias | E28: ='Propuesta de Mejora'!C112 -> 5309.2312
C29: ='Propuesta de Mejora'!E5 -> Motores | E29: ='Propuesta de Mejora'!C422 -> 1016.0764
C31: Medidas a implementar | E31: Ahorro por año
B32: Energía Térmica | C32: ='Propuesta de Mejora'!F5 -> Quemadores | E32: -
C33: ='Propuesta de Mejora'!G5 -> Tuberías | E33: ='Propuesta de Mejora'!C908 -> 118.73018
B36: Ahorros de costos por medidas a implementar
C38: Anual
B39: =C32 -> Quemadores | C39: ='Propuesta de Mejora'!C554 -> 13481662
B40: =C33 -> Tuberías | C40: ='Propuesta de Mejora'!C910*'Consumo Térmico de la empresa'!D6 -> 490341.68
C41: =SUM(C39:C40) -> 13972004
C43: Anual
B44: Luminarias | C44: ='Propuesta de Mejora'!C114 -> 2092102.6
B45: Aires acondicionados | C45: ='Propuesta de Mejora'!C221 -> 4088778.8
B46: Motores | C46: ='Propuesta de Mejora'!C424 -> 1150384.9
C47: =SUM(C44:C46) -> 7331266.3
B50: Ahorro total | C50: =C41+C47 -> 21303270 | D50: =C50 -> 21303270
B54: Ahorros anuales por implementación de medidas de eficiencia energética | V54: Ahorros anuales por implementación de medidas de eficiencia energética
B56: Concepto | C56: 1 | D56: 2 | E56: 3 | F56: 4 | G56: 5 | H56: 6 | I56: 7 | J56: 8 | K56: 9 | L56: 10 | M56: 11 | N56: 12 | O56: 13 | P56: 14 | Q56: 15 | V56: Concepto | W56: 1 | X56: 2 | Y56: 3 | Z56: 4 | AA56: 5 | AB56: 6 | AC56: 7 | AD56: 8 | AE56: 9 | AF56: 10 | AG56: 11 | AH56: 12 | AI56: 13 | AJ56: 14 | AK56: 15
B57: =B45 -> Aires acondicionados | C57: ='Propuesta de Mejora'!D221 -> 4088778.8 | D57: =C57*1.025 -> 4190998.3 | E57: =D57*1.025 -> 4295773.2 | F57: =E57*1.025 -> 4403167.6 | G57: =F57*1.025 -> 4513246.8 | H57: =G57*1.025 -> 4626077.9 | I57: =H57*1.025 -> 4741729.9 | J57: =I57*1.025 -> 4860273.1 | K57: =J57*1.025 -> 4981779.9 | ... Q57: =P57*1.025 -> 5777337.4 | V57: =B57 -> Aires acondicionados | W57: =C57 -> 4088778.8 | X57: =W57*1.025 -> 4190998.3 | Y57: =X57*1.025 -> 4295773.2 | Z57: =Y57*1.025 -> 4403167.6 | AA57: =Z57*1.025 -> 4513246.8 | AB57: =AA57*1.025 -> 4626077.9 | AC57: =AB57*1.025 -> 4741729.9 | AD57: =AC57*1.025 -> 4860273.1 | AE57: =AD57*1.025 -> 4981779.9 | ... AK57: =AJ57*1.025 -> 5777337.4
B58: =B40 -> Tuberías | C58: ='Propuesta de Mejora'!D910 -> 490341.68 | D58: =C58*1.025 -> 502600.22 | E58: =D58*1.025 -> 515165.22 | F58: =E58*1.025 -> 528044.35 | G58: =F58*1.025 -> 541245.46 | H58: =G58*1.025 -> 554776.6 | I58: =H58*1.025 -> 568646.01 | J58: =I58*1.025 -> 582862.16 | K58: =J58*1.025 -> 597433.72 | ... Q58: =P58*1.025 -> 692839.95 | V58: =B58 -> Tuberías | W58: =C58 -> 490341.68 | X58: =W58*1.025 -> 502600.22 | Y58: =X58*1.025 -> 515165.22 | Z58: =Y58*1.025 -> 528044.35 | AA58: =Z58*1.025 -> 541245.46 | AB58: =AA58*1.025 -> 554776.6 | AC58: =AB58*1.025 -> 568646.01 | AD58: =AC58*1.025 -> 582862.16 | AE58: =AD58*1.025 -> 597433.72 | ... AK58: =AJ58*1.025 -> 692839.95
B59: =B46 -> Motores | C59: ='Propuesta de Mejora'!D424 -> 1150384.9 | D59: =C59*1.025 -> 1179144.5 | E59: =D59*1.025 -> 1208623.1 | F59: =E59*1.025 -> 1238838.7 | G59: =F59*1.025 -> 1269809.7 | H59: =G59*1.025 -> 1301554.9 | I59: =H59*1.025 -> 1334093.8 | J59: =I59*1.025 -> 1367446.1 | K59: =J59*1.025 -> 1401632.3 | ... Q59: =P59*1.025 -> 1625463.7 | V59: =B59 -> Motores | W59: =C59 -> 1150384.9 | X59: =W59*1.025 -> 1179144.5 | Y59: =X59*1.025 -> 1208623.1 | Z59: =Y59*1.025 -> 1238838.7 | AA59: =Z59*1.025 -> 1269809.7 | AB59: =AA59*1.025 -> 1301554.9 | AC59: =AB59*1.025 -> 1334093.8 | AD59: =AC59*1.025 -> 1367446.1 | AE59: =AD59*1.025 -> 1401632.3 | ... AK59: =AJ59*1.025 -> 1625463.7
B60: =B39 -> Quemadores | C60: ='Propuesta de Mejora'!D554 -> 13481662 | D60: =C60*1.025 -> 13818704 | E60: =D60*1.025 -> 14164171 | F60: =E60*1.025 -> 14518275 | G60: =F60*1.025 -> 14881232 | H60: =G60*1.025 -> 15253263 | I60: =H60*1.025 -> 15634595 | J60: =I60*1.025 -> 16025460 | K60: =J60*1.025 -> 16426096 | ... Q60: =P60*1.025 -> 19049236 | V60: =B60 -> Quemadores | W60: =C60 -> 13481662 | X60: =W60*1.025 -> 13818704 | Y60: =X60*1.025 -> 14164171 | Z60: =Y60*1.025 -> 14518275 | AA60: =Z60*1.025 -> 14881232 | AB60: =AA60*1.025 -> 15253263 | AC60: =AB60*1.025 -> 15634595 | AD60: =AC60*1.025 -> 16025460 | AE60: =AD60*1.025 -> 16426096 | ... AK60: =AJ60*1.025 -> 19049236
B61: =B44 -> Luminarias | C61: ='Propuesta de Mejora'!D114 -> 2092102.6 | D61: =C61*1.025 -> 2144405.1 | E61: =D61*1.025 -> 2198015.2 | F61: =E61*1.025 -> 2252965.6 | G61: =F61*1.025 -> 2309289.8 | H61: =G61*1.025 -> 2367022 | I61: =H61*1.025 -> 2426197.6 | J61: =I61*1.025 -> 2486852.5 | K61: =J61*1.025 -> 2549023.8 | ... Q61: =P61*1.025 -> 2956086.1 | V61: =B61 -> Luminarias | W61: =C61 -> 2092102.6 | X61: =W61*1.025 -> 2144405.1 | Y61: =X61*1.025 -> 2198015.2 | Z61: =Y61*1.025 -> 2252965.6 | AA61: =Z61*1.025 -> 2309289.8 | AB61: =AA61*1.025 -> 2367022 | AC61: =AB61*1.025 -> 2426197.6 | AD61: =AC61*1.025 -> 2486852.5 | AE61: =AD61*1.025 -> 2549023.8 | ... AK61: =AJ61*1.025 -> 2956086.1
B62: Ahorro total | C62: =SUM(C57:C61) -> 21303270 | D62: =SUM(D57:D61) -> 21835852 | E62: =SUM(E57:E61) -> 22381748 | F62: =SUM(F57:F61) -> 22941292 | G62: =SUM(G57:G61) -> 23514824 | H62: =SUM(H57:H61) -> 24102695 | I62: =SUM(I57:I61) -> 24705262 | J62: =SUM(J57:J61) -> 25322894 | ... Q62: =SUM(Q57:Q61) -> 30100963 | V62: Ahorro total | W62: =SUM(W57:W61) -> 21303270 | X62: =SUM(X57:X61) -> 21835852 | Y62: =SUM(Y57:Y61) -> 22381748 | Z62: =SUM(Z57:Z61) -> 22941292 | AA62: =SUM(AA57:AA61) -> 23514824 | AB62: =SUM(AB57:AB61) -> 24102695 | AC62: =SUM(AC57:AC61) -> 24705262 | AD62: =SUM(AD57:AD61) -> 25322894 | ... AK62: =SUM(AK57:AK61) -> 30100963
B66: Inversiones por medidas de EE
B68: Medidas | C68: Inversión
B69: =C28 -> Luminarias | C69: ='Propuesta de Mejora'!C115 -> 219700
B70: =C27 -> Aires acondicionados | C70: ='Propuesta de Mejora'!C222 -> 10778876
B71: =C29 -> Motores | C71: ='Propuesta de Mejora'!C425 -> 3294000
B72: =C32 -> Quemadores | C72: ='Propuesta de Mejora'!C555 -> 7552500
B73: =C33 -> Tuberías | C73: ='Propuesta de Mejora'!C911*'Consumo Térmico de la empresa'!D6 -> 500872.9
B74: Total | C74: =SUM(C69:C73) -> 22345949
B77: Depreciaciones
B84: Valor libro
B89: Depreciación cambio de aires acondicionados
B90: Precio | C90: =C70 -> 10778876 | D90: Vida útil | E90: 10
B91: Depreciación anual | E91: =C90/10 -> 1077887.6
B92: Año | C92: Depreciación | D92: Depreciación acumulada | E92: Venta en libros
B93: 1 | C93: =$E$91 -> 1077887.6 | D93: =C93 -> 1077887.6 | E93: =$C$90-D93 -> 9700988.6
B94: 2 | C94: =$E$91 -> 1077887.6 | D94: =D93+C94 -> 2155775.2 | E94: =$C$90-D94 -> 8623101
B95: 3 | C95: =$E$91 -> 1077887.6 | D95: =D94+C95 -> 3233662.9 | E95: =$C$90-D95 -> 7545213.3
B96: 4 | C96: =$E$91 -> 1077887.6 | D96: =D95+C96 -> 4311550.5 | E96: =$C$90-D96 -> 6467325.7
B97: 5 | C97: =$E$91 -> 1077887.6 | D97: =D96+C97 -> 5389438.1 | E97: =$C$90-D97 -> 5389438.1
B98: 6 | C98: =$E$91 -> 1077887.6 | D98: =D97+C98 -> 6467325.7 | E98: =$C$90-D98 -> 4311550.5
B99: 7 | C99: =$E$91 -> 1077887.6 | D99: =D98+C99 -> 7545213.3 | E99: =$C$90-D99 -> 3233662.9
B100: 8 | C100: =$E$91 -> 1077887.6 | D100: =D99+C100 -> 8623101 | E100: =$C$90-D100 -> 2155775.2
B101: 9 | C101: =$E$91 -> 1077887.6 | D101: =D100+C101 -> 9700988.6 | E101: =$C$90-D101 -> 1077887.6
B102: 10 | C102: =$E$91 -> 1077887.6 | D102: =D101+C102 -> 10778876 | E102: =$C$90-D102 -> 0
B105: Depreciación cambio de motores
B106: Precio | C106: =C71 -> 3294000 | D106: Vida útil | E106: 15
B107: Depreciación anual | E107: =C106/15 -> 219600
B108: Año | C108: Depreciación | D108: Depreciación acumulada | E108: Venta en libros
B109: 1 | C109: =$E$107 -> 219600 | D109: =C109 -> 219600 | E109: =$C$106-D109 -> 3074400
B110: 2 | C110: =$E$107 -> 219600 | D110: =D109+C110 -> 439200 | E110: =$C$106-D110 -> 2854800
B111: 3 | C111: =$E$107 -> 219600 | D111: =D110+C111 -> 658800 | E111: =$C$106-D111 -> 2635200
B112: 4 | C112: =$E$107 -> 219600 | D112: =D111+C112 -> 878400 | E112: =$C$106-D112 -> 2415600
B113: 5 | C113: =$E$107 -> 219600 | D113: =D112+C113 -> 1098000 | E113: =$C$106-D113 -> 2196000
B114: 6 | C114: =$E$107 -> 219600 | D114: =D113+C114 -> 1317600 | E114: =$C$106-D114 -> 1976400
B115: 7 | C115: =$E$107 -> 219600 | D115: =D114+C115 -> 1537200 | E115: =$C$106-D115 -> 1756800
B116: 8 | C116: =$E$107 -> 219600 | D116: =D115+C116 -> 1756800 | E116: =$C$106-D116 -> 1537200
B117: 9 | C117: =$E$107 -> 219600 | D117: =D116+C117 -> 1976400 | E117: =$C$106-D117 -> 1317600
B118: 10 | C118: =$E$107 -> 219600 | D118: =D117+C118 -> 2196000 | E118: =$C$106-D118 -> 1098000
B119: 11 | C119: =$E$107 -> 219600 | D119: =D118+C119 -> 2415600 | E119: =$C$106-D119 -> 878400
B120: 12 | C120: =$E$107 -> 219600 | D120: =D119+C120 -> 2635200 | E120: =$C$106-D120 -> 658800
B121: 13 | C121: =$E$107 -> 219600 | D121: =D120+C121 -> 2854800 | E121: =$C$106-D121 -> 439200
... B123: 15 | C123: =$E$107 -> 219600 | D123: =D122+C123 -> 3294000 | E123: =$C$106-D123 -> 0
B126: Depreciación cambio de quemadores
B127: Precio | C127: =C72 -> 7552500 | D127: Vida útil | E127: 15
B128: Depreciación anual | E128: =C127/15 -> 503500
B129: Año | C129: Depreciación | D129: Depreciación acumulada | E129: Venta en libros
B130: 1 | C130: =$E$107 -> 219600 | D130: =C130 -> 219600 | E130: =$C$106-D130 -> 3074400
B131: 2 | C131: =$E$107 -> 219600 | D131: =D130+C131 -> 439200 | E131: =$C$106-D131 -> 2854800
B132: 3 | C132: =$E$107 -> 219600 | D132: =D131+C132 -> 658800 | E132: =$C$106-D132 -> 2635200
B133: 4 | C133: =$E$107 -> 219600 | D133: =D132+C133 -> 878400 | E133: =$C$106-D133 -> 2415600
B134: 5 | C134: =$E$107 -> 219600 | D134: =D133+C134 -> 1098000 | E134: =$C$106-D134 -> 2196000
B135: 6 | C135: =$E$107 -> 219600 | D135: =D134+C135 -> 1317600 | E135: =$C$106-D135 -> 1976400
B136: 7 | C136: =$E$107 -> 219600 | D136: =D135+C136 -> 1537200 | E136: =$C$106-D136 -> 1756800
B137: 8 | C137: =$E$107 -> 219600 | D137: =D136+C137 -> 1756800 | E137: =$C$106-D137 -> 1537200
B138: 9 | C138: =$E$107 -> 219600 | D138: =D137+C138 -> 1976400 | E138: =$C$106-D138 -> 1317600
B139: 10 | C139: =$E$107 -> 219600 | D139: =D138+C139 -> 2196000 | E139: =$C$106-D139 -> 1098000
B140: 11 | C140: =$E$107 -> 219600 | D140: =D139+C140 -> 2415600 | E140: =$C$106-D140 -> 878400
B141: 12 | C141: =$E$107 -> 219600 | D141: =D140+C141 -> 2635200 | E141: =$C$106-D141 -> 658800
...
